Workbook

Sheet INFORME EXTERNOS 2022
B2: ENERO 2022
B4: VICTOR VALENCIA | K4: POR CONSIGNACION
B5: CONSIGNACIONES | C5: CONTRATO | D5: % PROPIETARIO | E5: INMUEBLE | F5: CANON | G5: % | H5: COMISION | I5: CONSIGNO | J5: INVENTARIO | K5: EJECUTIVO | L5: CONTRATO | M5: INMUEBLE | N5: CANON | O5: % | P5: COMISION
B6: =CAPTACIONES!L29 -> 23 | C6: 13102 | D6: 0.1 | E6: PENTAGRAMA 2216 | F6: 1500000 | G6: 0.06 | H6: =G6*F6 -> 90000 | I6: PORTADA | J6: CAMILO | K6: STEFANY AGUDELO | L6: 13033 | M6: CARRERA 84 35-62 APT 301 | N6: 1200000 | O6: 0.05 | P6: =O6*N6 -> 60000
C7: 13098 | D7: 0.1 | E7: LOS CABOS 1101 SUBROGACION | F7: 1800000 | G7: 0.05 | H7: =G7*F7 -> 90000 | I7: PORTADA | J7: CAMILO | K7: STEFANY AGUDELO | L7: 13121 | M7: PORTAL DE LAS AMERICAS 206 | N7: 2300000 | O7: 0.05 | P7: =O7*N7 -> 115000
C8: 13110 | D8: 0.1 | E8: CALLE 42 C N° 63C - 35 AP 901 | F8: 2750000 | G8: 0.1 | H8: =G8*F8 -> 275000 | I8: VICTOR VALENCIA | J8: CAMILO | K8: LUISA MARIN | L8: 13052 | M8: CIUDADELA DEL PARQUE 1821 | N8: 1450000 | O8: 0.05 | P8: =O8*N8 -> 72500
C9: 13118 | D9: 0.1 | E9: RODEO VERDE 622 | F9: 1100000 | G9: 0.06 | H9: =G9*F9 -> 66000 | I9: PORTADA | J9: CAMILO | K9: LUISA MARIN
M10: TOTAL | N10: =SUM(N6:N8) -> 4950000 | O10: TOTAL | P10: =SUM(P6:P8) -> 247500
B11: TOTAL | F11: =SUM(F6:F10) -> 7150000 | G11: TOTAL | H11: =SUM(H6:H10) -> 521000 | M11: TOTAL--------------------------------------> | P11: =H11+P10 -> 768500
B13: ALEJANDRA RESTREPO | K13: POR CONSIGNACION
B14: CONSIGNACIONES | C14: CONTRATO | D14: % PROPIETARIO | E14: INMUEBLE | F14: CANON | G14: % | H14: COMISION | I14: CONSIGNO | J14: INVENTARIO | K14: EJECUTIVO | L14: CONTRATO | M14: INMUEBLE | N14: CANON | O14: % | P14: COMISION
B15: =CAPTACIONES!L47 -> 13 | C15: 12961 | D15: 0.1 | E15: LOS CABOS 630 | F15: 1700000 | G15: 0.05 | H15: =G15*F15 -> 85000 | I15: PORTADA | J15: CAMILO | K15: CRISTIAN | L15: 12947 | M15: ENTRE BOSQUES 1616 | N15: 1700000 | O15: 0.04 | P15: =O15*N15 -> 68000
C16: 12956 | D16: 0.1 | E16: EDIFICIO BENIDORM 302 | F16: 1350000 | G16: 0.04 | H16: =G16*F16 -> 54000 | I16: JULIAN SOLIS | J16: CAMILO | K16: CRISTIAN
C17: 12993 | D17: 0.1 | E17: VILLA DE ABURRA 201 | F17: 1850000 | G17: 0.08 | H17: =G17*F17 -> 148000 | I17: ALEJANDRA RESTREPO | J17: CAMILO | K17: STEFANNY AGUDELO
C18: DESISTIDO | D18: 0.1 | E18: CARRERA 83A 32EE-44 SUBROGACIÓN - 1.300.000 | I18: PORTADA | J18: El inquilino actual desiste de la subrogación y continua en el inmueble | K18: STEFANNY AGUDELO
C19: DESISTIDO | D19: 0.1 | E19: RODEO VERDE 912 - 1.200.000 | J19: Vendieron el carro y no les servia el sector así | K19: STEFANNY AGUDELO
C20: DESISTIDO | D20: 0.1 | E20: CAMINO DEL PARQUE 2512 - 1.700.000 | J20: Propietario lo arrendo | K20: ANDREA
C21: DESISTIDO | D21: 0.1 | E21: MARQUEZ DE CACERES 802 - 1.500.000 | J21: Propietario lo arrendo | K21: STEFANY AGUDELO
C22: DESISTIDO | D22: 0.1 | E22: ARBOLEDA DEL RODEO 1808 - 1.400.000 | J22: Inquilinio desistio | K22: STEFANNY AGUDELO
M23: TOTAL | N23: =SUM(N15:N17) -> 1700000 | O23: TOTAL | P23: =SUM(P15:P16) -> 68000
B24: TOTAL | F24: =SUM(F15:F23) -> 4900000 | G24: TOTAL | H24: =SUM(H15:H23) -> 287000 | M24: TOTAL--------------------------------------> | P24: =H24+P23 -> 355000
B27: JULIAN SOLIS | K27: POR CONSIGNACION
B28: CONSIGNACIONES | C28: CONTRATO | D28: % PROPIETARIO | E28: INMUEBLE | F28: CANON | G28: % | H28: COMISION | I28: CONSIGNO | J28: INVENTARIO | K28: EJECUTIVO | L28: CONTRATO | M28: INMUEBLE | N28: CANON | O28: % | P28: COMISION
B29: =CAPTACIONES!L64 -> 13 | C29: 12924 | D29: 0.1 | E29: GUADARRAMA 526 | F29: 1600000 | G29: 0.08 | H29: =G29*F29 -> 128000 | I29: JULIAN SOLIS | J29: CAMILO | K29: ANDREA | L29: 12956 | M29: EDIFICIO BENIDORM 302 | N29: 1350000 | O29: 0.04 | P29: =O29*N29 -> 54000
C30: 12970 | D30: 0.1 | E30: ALPES PLAZA 1803 | F30: 1650000 | G30: 0.04 | H30: =G30*F30 -> 66000 | I30: LUIS CORREA | J30: CAMILO | K30: CRISTIAN
C31: 12996 | D31: 0.1 | E31: LOS CABOS 322 | F31: 2100000 | G31: 0.05 | H31: =G31*F31 -> 105000 | I31: PORTADA | J31: CAMILO | K31: STEFANNY AGUDELO
C32: 12963 | D32: 0.1 | E32: ZAPZURRO 201 | F32: 1850000 | G32: 0.04 | H32: =G32*F32 -> 74000 | I32: ALONSO | J32: CAMILO | K32: ANDREA
C33: 13005 | D33: 0.1 | E33: CAMINO DEL PARQUE 2512 | F33: 1700000 | G33: 0.04 | H33: =G33*F33 -> 68000 | I33: ALEJANDRO VILLEGAS | J33: CAMILO | K33: STEFANNY AGUDELO
C34: 13026 | D34: 0.1 | E34: LOS CABOS 9926 | F34: 1950000 | G34: 0.05 | H34: =G34*F34 -> 97500 | I34: PORTADA | J34: CAMILO | K34: STEFANY AGUDELO
C35: 13033 | D35: 0.1 | E35: CARRERA 84 35-62 APT 301 | F35: 1200000 | G35: 0.04 | H35: =G35*F35 -> 48000 | I35: VICTOR VALENCIA | J35: CAMILO | K35: ANDREA
C36: 13117 | D36: 0.1 | E36: RODEO VERDE 725 SUBROGACION | F36: 1200000 | G36: 0.04 | H36: =G36*F36 -> 48000 | I36: PORTADA | J36: CAMILO | K36: LUISA MARIN
C37: DESISTIDO | D37: 0.1 | E37: ARBOLEDA DEL RODEO 1808 - 1.400.000 | I37: YERMANY | J37: El cliente decide seguir buscando, no estaba convencido | K37: LUISA MARIN
C38: DESISTIDO | D38: 0.1 | E38: CALLE 35 80-42 - 2.200.000 | J38: iInquillino desiste porque dice que ya no le sirve sin parqueadero | K38: LUISA MARIN
C39: DESISTIDO | D39: 0.1 | E39: ANKARA 401 - 2.300.000 | J39: Propietario dice que no puede enviar composición accionaria de la empresa que aparece como propietaria, dice que no le queda posible. | K39: AURA POSSO | M39: TOTAL | N39: =SUM(N29:N33) -> 1350000 | O39: TOTAL | P39: =SUM(P29:P33) -> 54000
B40: TOTAL | F40: =SUM(F29:F39) -> 13250000 | G40: TOTAL | H40: =SUM(H29:H39) -> 634500 | M40: TOTAL--------------------------------------> | P40: =H40+P39 -> 688500
B42: FELIPE ECHEVERRI | K42: POR CONSIGNACION
B43: CONSIGNACIONES | C43: CONTRATO | D43: % PROPIETARIO | E43: INMUEBLE | F43: CANON | G43: % | H43: COMISION | I43: CONSIGNO | J43: INVENTARIO | K43: EJECUTIVO | L43: CONTRATO | M43: INMUEBLE | N43: CANON | O43: % | P43: COMISION
B44: =CAPTACIONES!L81 -> 0
M49: TOTAL | N49: =SUM(N44:N48) -> 0 | O49: TOTAL | P49: =SUM(P44:P48) -> 0
B50: TOTAL | F50: =SUM(F44:F49) -> 0 | G50: TOTAL | H50: =SUM(H44:H49) -> 0 | M50: TOTAL--------------------------------------> | P50: =H50+P49 -> 0
B52: PORTADA | K52: POR CONSIGNACION
B53: CONSIGNACIONES | C53: CONTRATO | D53: % PROPIETARIO | E53: INMUEBLE | F53: CANON | G53: % | H53: COMISION | I53: CONSIGNO | J53: INVENTARIO | K53: EJECUTIVO | L53: CONTRATO | M53: INMUEBLE | N53: CANON | O53: % | P53: COMISION
B54: =CAPTACIONES!L79 -> 1 | C54: 13094 | D54: 0.08 | E54: CALLE 65C 94 - 51 AP 101 | F54: 750000 | G54: 0.04 | H54: =G54*F54 -> 30000 | I54: CARLOS VALLEJO | J54: CAMILO | K54: STEFANNY AGUDELO | L54: 13102 | M54: PENTAGRAMA 2216 | N54: 1500000 | O54: 0.05 | P54: =O54*N54 -> 75000
L55: 13098 | M55: LOS CABOS 1101 SUBROGACION | N55: 1800000 | O55: 0.05 | P55: =O55*N55 -> 90000
L56: 13118 | M56: RODEO VERDE 622 | N56: 1200000 | O56: 0.06 | P56: =O56*N56 -> 72000
L57: 12961 | M57: LOS CABOS 630 | N57: 1700000 | O57: 0.05 | P57: =O57*N57 -> 85000
L58: 12996 | M58: LOS CABOS 322 | N58: 2100000 | O58: 0.05 | P58: =O58*N58 -> 105000
L59: 13026 | M59: LOS CABOS 9926 | N59: 1950000 | O59: 0.05 | P59: =O59*N59 -> 97500
M60: TOTAL | N60: =SUM(N54:N59) -> 10250000 | O60: TOTAL | P60: =SUM(P54:P55) -> 165000
B61: TOTAL | F61: =SUM(F54:F60) -> 750000 | G61: TOTAL | H61: =SUM(H54:H60) -> 30000 | M61: TOTAL--------------------------------------> | P61: =H61+P60 -> 195000
B63: =B54+B44+B29+B15+B6 -> 50 | C63: TOTAL FIRMADO | F63: =F61+F50+F40+F24+F11 -> 26050000
C64: TOTAL APROBADO EN PROCESO DE FIRMAS
C65: TOTAL EN ESTUDIO
B67: SECTOR | C67: CAPTACIONES | D67: ARRIENDOS ($) | E67: TOTAL INMUEBLES ARRENDADOS
B69: LAURELES
B71: BELEN
B73: OTRAS ZONAS
B75: TOTAL | C75: =SUM(C69:C72) -> 0 | D75: =SUM(D68:D72) -> 0 | E75: =SUM(E68:E72) -> 0
B79: FEBRERO 2022
B81: VICTOR VALENCIA | K81: POR CONSIGNACION
B82: CONSIGNACIONES | C82: CONTRATO | D82: % PROPIETARIO | E82: INMUEBLE | F82: CANON | G82: % | H82: COMISION | I82: CONSIGNO | J82: INVENTARIO | K82: EJECUTIVO | L82: CONTRATO | M82: INMUEBLE | N82: CANON | O82: % | P82: COMISION
B83: =CAPTACIONES!L109 -> 23 | C83: 13149 | D83: 0.1 | E83: MAZIRUMA 301 | F83: 1300000 | G83: 0.07 | H83: =G83*F83 -> 91000 | I83: ALEJANDRO OCAMPO | J83: CAMILO | K83: STEFANY AGUDELO | L83: 13177 | M83: CAMINO DEL PARQUE 1710 | N83: 1850000 | O83: 0.04 | P83: =O83*N83 -> 74000
C84: 13190 | D84: 0.08 | E84: CIUDADELA DE LOS LAURELES 405 EMPALME | F84: 2500000 | G84: 0.06 | H84: =G84*F84 -> 150000 | I84: PORTADA | J84: SEBASTIAN | K84: TABATHA | L84: 13280 | M84: ATLANTA 401 | N84: 2000000 | O84: 0.04 | P84: =O84*N84 -> 80000
C85: 13206 | D85: 0.08 | E85: MIRADOR DE LA ARBOLEDA 1401 | F85: 1350000 | G85: 0.1 | H85: =G85*F85 -> 135000 | I85: VICTOR VALENCIA | J85: CAMILO | K85: STEFANNY AGUDELO | M85: CALLE 42 C N° 63C - 35 AP 201 | N85: 3250000 | O85: 0.05 | P85: =O85*N85 -> 162500
C86: 13269 | D86: 0.1 | E86: LA GRAN ESQUINA 707 | F86: 1500000 | G86: 0.12 | H86: =G86*F86 -> 180000 | I86: VICTOR VALENCIA | J86: CAMILO | K86: LUISA MARIN
C87: 13234 | D87: 0.08 | E87: LOCAL BAHIA BLANCA | F87: 1200000 | G87: 0.06 | H87: =G87*F87 -> 72000 | I87: JULIAN SOLIS | J87: CAMILO | K87: LUISA MARIN
C88: 13245 | D88: 0.1 | E88: SAN MARTIN 201 | F88: 1650000 | G88: 0.07 | H88: =G88*F88 -> 115500 | I88: JULIAN SOLIS | J88: CAMILO | K88: STEFANNY AGUDELO
C89: 13257 | D89: 0.08 | E89: SAN PATRICIO 1001 EMPALME | F89: 3700000 | G89: 0.06 | H89: =G89*F89 -> 222000 | I89: PORTADA | J89: CAMILO | K89: STEFANNY AGUDELO
C90: 13260 | D90: 0.08 | E90: NANTES 202 | F90: 1300000 | G90: 0.06 | H90: =G90*F90 -> 78000 | I90: PORTADA | J90: CAMILO | K90: STEFANNY AGUDELO
C91: 13274 | D91: 0.1 | E91: CALLE 42 C N° 63C - 35 AP 1101 | F91: 2750000 | G91: 0.12 | H91: =G91*F91 -> 330000 | I91: VICTOR VALENCIA | J91: VICTOR | K91: STEFANNY AGUDELO
C92: 13291 | D92: 0.08 | E92: TORRES DE AVIÑON 614 | F92: 1590000 | G92: 0.06 | H92: =G92*F92 -> 95400 | I92: PORTADA | J92: CAMILO | K92: STEFANNY AGUDELO
C93: 13299 | D93: 0.08 | E93: LAURELES DEL CASTILLO 906 | F93: 2300000 | G93: 0.1 | H93: =G93*F93 -> 230000 | I93: VICTOR VALENCIA | J93: CAMILO | K93: STEFANNY AGUDELO
C94: 13328 | D94: 0.1 | E94: AURA 101 | F94: 1200000 | G94: 0.07 | H94: =G94*F94 -> 84000 | I94: PORTADA | J94: CAMILO | K94: DIANA ESCUDERO
C95: 13339 | D95: 0.1 | E95: CALLE 79 1-155 | F95: 1000000 | G95: 0.12 | H95: =G95*F95 -> 120000 | I95: VICTOR VALENCIA | J95: CAMILO | K95: STEFANNY AGUDELO
C96: 13346 | D96: 0.1 | E96: PLAZA VICUÑA 517 | F96: 2000000 | G96: 0.07 | H96: =G96*F96 -> 140000 | I96: PORTADA | J96: CAMILO | K96: STEFANNY AGUDELO
C97: 13381 | D97: 0.1 | E97: ALTOS DEL CASTILLO 402 SUBROGACION | F97: 1100000 | G97: 0.07 | H97: =G97*F97 -> 77000 | I97: PORTADA | J97: CAMILO | K97: STEFANNY AGUDELO
C98: DESISTIDO | D98: 0.1 | E98: PORTAL DE SANTA RITA 302 -1.250.000 | I98: VICTOR VALENCIA | J98: El inquilino dice que ya necesita un casa de 4 alcobas | K98: LUISA MARIN
C99: DESISTIDO | D99: 0.1 | E99: CALLE 44B 86-12 APT 202 - 1.100.000 | J99: Toma un apartamento más economico | K99: LUISA MARIN
C100: DESISTIDO | D100: 0.1 | E100: PALMIRA 306 - 850.000 | I100: VICTOR VALENCIA | J100: Consigue un apto directo en menos presupuesto | K100: STEFANNY AGUDELO
C101: DESISTIDO | D101: 0.1 | E101: LAURELES DEL PINAR 902 - 1.300.000 | I101: PORTADA | J101: Propietario le entrega el sabado 5 y la inquilina lo necesitaba para antes | K101: STEFANNY AGUDELO | M101: TOTAL | N101: =SUM(N83:N85) -> 7100000 | O101: TOTAL | P101: =SUM(P83:P85) -> 316500
B102: TOTAL | F102: =SUM(F83:F101) -> 26440000 | G102: TOTAL | H102: =SUM(H83:H101) -> 2119900 | M102: TOTAL--------------------------------------> | P102: =H102+P101 -> 2436400
B104: ALEJANDRA RESTREPO | K104: POR CONSIGNACION
B105: CONSIGNACIONES | C105: CONTRATO | D105: % PROPIETARIO | E105: INMUEBLE | F105: CANON | G105: % | H105: COMISION | I105: CONSIGNO | J105: INVENTARIO | K105: EJECUTIVO | L105: CONTRATO | M105: INMUEBLE | N105: CANON | O105: % | P105: COMISION
B106: =CAPTACIONES!L136 -> 23 | C106: 13161 | D106: 0.1 | E106: RODEO VERDE 912 SUBROGACION | F106: 1200000 | G106: 0.05 | H106: =G106*F106 -> 60000 | I106: PORTADA | J106: CAMILO | K106: LUISA MARIN | L106: 13164 | M106: CARRERA 83A 37D - 11 APT 101 | N106: 2200000 | O106: 0.05 | P106: =O106*N106 -> 110000
C107: 13177 | D107: 0.08 | E107: CAMINO DEL PARQUE 1710 | F107: 1850000 | G107: 0.04 | H107: =G107*F107 -> 74000 | I107: VICTOR VALENCIA | J107: CAMILO | K107: LUISA MARIN
C108: 13216 | D108: 0.1 | E108: EL ALCAZAR 222 | F108: 1500000 | G108: 0.05 | H108: =G108*F108 -> 75000 | I108: CAMILO GALLEGO | J108: CAMILO | K108: LUISA MARIN
C109: 13221 | D109: 0.1 | E109: PARQUES DE LA SIERRA 104 | F109: 1400000 | G109: 0.1 | H109: =G109*F109 -> 140000 | I109: ALEJANDRA RESTREPO | J109: CAMILO | K109: STEFANNY AGUDELO
C110: 13276 | D110: 0.1 | E110: CALLE 33 74B-233 APT 201 | F110: 2250000 | G110: 0.06 | H110: =G110*F110 -> 135000 | I110: PORTADA | J110: CAMILO | K110: STEFANNY AGUDELO
C111: 13280 | D111: 0.09 | E111: ATLANTA 401 | F111: 2000000 | G111: 0.04 | H111: =G111*F111 -> 80000 | I111: VICTOR VALENCIA | J111: CAMILO | K111: STEFANNY AGUDELO
C112: 13326 | D112: 0.08 | E112: AVIVA 1444 | F112: 2700000 | G112: 0.04 | H112: =G112*F112 -> 108000 | I112: BRYAN AGUDELO | J112: CAMILO | K112: STEFANNY AGUDELO
C113: 13323 | D113: 0.1 | E113: RODEO VERDE 821 | F113: 1200000 | G113: 0.06 | H113: =G113*F113 -> 72000 | I113: PORTADA | J113: CAMILO | K113: DIANA ESCUDERO
C114: 13312 | D114: 0.1 | E114: CARRERA 88 N° 35D-40 AP 402 | F114: 700000 | G114: 0.06 | H114: =G114*F114 -> 42000 | I114: PORTADA | J114: CAMILO | K114: JESSICA ORTIZ
C115: 13365 | D115: 0.1 | E115: LAURELES DEL PARQUE 403 | F115: 2500000 | G115: 0.1 | H115: =G115*F115 -> 250000 | I115: ALEJANDRA RESTREPO | J115: CAMILO | K115: DIANA ESCUDERO
C116: 13370 | D116: 0.1 | E116: BERNALEJAS 1302 | F116: 1900000 | G116: 0.1 | H116: =G116*F116 -> 190000 | I116: ALEJANDRA RESTREPO | J116: CAMILO | K116: DIANA ESCUDERO
C117: 13384 | D117: 0.1 | E117: BALCONES DE ALAMEDA 501 | F117: 1500000 | G117: 0.06 | H117: =G117*F117 -> 90000 | I117: PORTADA | J117: CAMILO | K117: STEFANNY AGUDELO
C118: DESISTIDO | D118: 0.1 | E118: TORRES DE AVIÑON 507 - 1.500.000 | I118: KELLY GARCIA | J118: Al revisar para hace contratos, el apto tenia varios arreglos como espejos rotos, que el propietario no queria arreglar, debia servicios publicos desde marzo de 2021 y no queria brindar autorización para que la admon nos diera paz y salvo | K118: STEFANNY AGUDELO
C119: DESISTIDO | D119: 0.1 | E119: PORTON DE LA ALMERIA 1209 - 700.000 | I119: PORTADA | J119: Cliente desiste al momento de firmar contratos, no vuelve a contestar | K119: STEFANNY AGUDELO | M119: TOTAL | N119: =SUM(N106:N108) -> 2200000 | O119: TOTAL | P119: =SUM(P106:P107) -> 110000
B120: TOTAL | F120: =SUM(F106:F119) -> 20700000 | G120: TOTAL | H120: =SUM(H106:H119) -> 1316000 | M120: TOTAL--------------------------------------> | P120: =H120+P119 -> 1426000
B122: JULIAN SOLIS | K122: POR CONSIGNACION
B123: CONSIGNACIONES | C123: CONTRATO | D123: % PROPIETARIO | E123: INMUEBLE | F123: CANON | G123: % | H123: COMISION | I123: CONSIGNO | J123: INVENTARIO | K123: EJECUTIVO | L123: CONTRATO | M123: INMUEBLE | N123: CANON | O123: % | P123: COMISION
...

Sheet INFORME INTERNAS Y ADMON 2022
B2: ENERO 2022
B4: ENERO 2022 - LUISA MARIN
B5: CONTRATO | C5: PROPIETARIO | D5: OBSERVACIONES | E5: INMUEBLE | F5: CANON | G5: % | H5: LUISA | I5: EXTERNO
B6: 13117 | C6: 0.1 | D6: LUISA MARIN | E6: RODEO VERDE 725 SUBROGACION | F6: 1200000 | G6: 0.02 | H6: =G6*F6 -> 24000 | I6: JULIAN SOLIS
B7: 13110 | C7: 0.1 | D7: LUISA MARIN | E7: CALLE 42 C N° 63C - 35 AP 901 | F7: 2750000 | G7: 0.02 | H7: =G7*F7 -> 55000 | I7: VICTOR VALENCIA
B8: 13118 | C8: 0.1 | D8: LUISA MARIN | E8: RODEO VERDE 622 | F8: 1100000 | G8: 0.02 | H8: =G8*F8 -> 22000 | I8: VICTOR VALENCIA
B9: 12932 | C9: 0.1 | D9: LUISA MARIN | E9: ENTREVIENTOS 309 | F9: 900000 | G9: 0.02 | H9: =G9*F9 -> 18000 | I9: BELLO
B10: 12938 | C10: 0.1 | D10: LUISA MARIN | E10: PUERTA MADERO 408 | F10: 1000000 | G10: 0.02 | H10: =G10*F10 -> 20000 | I10: BELLO
B11: 12953 | C11: 0.1 | D11: LUISA MARIN | E11: CALLE 42B 58 - 23 301 | F11: 720000 | G11: 0.02 | H11: =G11*F11 -> 14400 | I11: BELLO
B12: 12954 | C12: 0.1 | D12: LUISA MARIN | E12: NORDICA 2709 | F12: 1700000 | G12: 0.02 | H12: =G12*F12 -> 34000 | I12: BELLO
B13: 12958 | C13: 0.1 | D13: LUISA MARIN | E13: PUERTO PARAISO 2306 | F13: 1300000 | G13: 0.02 | H13: =G13*F13 -> 26000 | I13: BELLO
B14: 12998 | C14: 0.1 | D14: LUISA MARIN | E14: PUERTO PARAISO 1207 | F14: 1150000 | G14: 0.02 | H14: =G14*F14 -> 23000 | I14: BELLO
B15: 12991 | C15: 0.1 | D15: LUISA MARIN | E15: PUERTO PARAISO 1609 | F15: 1200000 | G15: 0.02 | H15: =G15*F15 -> 24000 | I15: BELLO
B16: DESISTIDO | C16: El cliente decide seguir buscando, no estaba convencido | D16: LUISA MARIN | E16: ARBOLEDA DEL RODEO 1808 - 1.400.000 | I16: JULIAN SOLIS
B17: DESISTIDO | C17: iInquillino desiste porque dice que ya no le sirve sin parqueadero | D17: LUISA MARIN | E17: CALLE 35 80-42 - 2.200.000 | I17: JULIAN SOLIS
E18: TOTAL-----------------------------------> | F18: =SUM(F6:F17) -> 13020000 | H18: =SUM(H1:H17) -> 260400
B20: ENERO 2022 - STEFANNY AGUDELO
B21: CONTRATO | C21: PROPIETARIO | D21: OBSERVACIONES | E21: INMUEBLE | F21: CANON | G21: % | H21: STEFANNY | I21: EXTERNO
B22: 12993 | C22: 0.1 | D22: STEFANNY AGUDELO | E22: VILLA DE ABURRA 201 | F22: 1850000 | G22: 0.02 | H22: =G22*F22 -> 37000 | I22: ALEJANDRA RESTREPO
B23: 12996 | C23: 0.1 | D23: STEFANNY AGUDELO | E23: LOS CABOS 322 | F23: 2100000 | G23: 0.02 | H23: =G23*F23 -> 42000 | I23: JULIAN SOLIS
B24: 13005 | C24: 0.1 | D24: STEFANNY AGUDELO | E24: CAMINO DEL PARQUE 2512 | F24: 1700000 | G24: 0.02 | H24: =G24*F24 -> 34000 | I24: JULIAN SOLIS
B25: 13026 | C25: 0.1 | D25: STEFANNY AGUDELO | E25: LOS CABOS 9926 | F25: 1950000 | G25: 0.02 | H25: =G25*F25 -> 39000 | I25: JULIAN SOLIS
B26: 13102 | C26: 0.1 | D26: STEFANNY AGUDELO | E26: PENTAGRAMA 2216 | F26: 1500000 | G26: 0.02 | H26: =G26*F26 -> 30000 | I26: VICTOR VALENCIA
B27: 13098 | C27: 0.1 | D27: STEFANNY AGUDELO | E27: LOS CABOS 1101 SUBROGACION | F27: 1800000 | G27: 0.02 | H27: =G27*F27 -> 36000 | I27: VICTOR VALENCIA
B28: 13094 | C28: 0.08 | D28: STEFANNY AGUDELO | E28: CALLE 65C 94 - 51 AP 101 | F28: 750000 | G28: 0.01 | H28: =G28*F28 -> 7500 | I28: PORTADA
B29: DESISTIDO | C29: El inquilino actual desiste de la subrogación y continua en el inmueble | D29: STEFANNY AGUDELO | E29: CARRERA 83A 32EE-44 SUBROGACIÓN - 1.300.000 | I29: ALEJANDRA RESTREPO
B30: DESISTIDO | C30: Vendieron el carro y no les servia el sector así | D30: STEFANNY AGUDELO | E30: RODEO VERDE 912 - 1.200.000 | I30: ALEJANDRA RESTREPO
B31: DESISTIDO | C31: Propietario lo arrendo | D31: STEFANNY AGUDELO | E31: MARQUEZ DE CACERES 802 - 1.500.000 | I31: ALEJANDRA RESTREPO
B32: DESISTIDO | C32: Inquilinio desistio | D32: STEFANNY AGUDELO | E32: ARBOLEDA DEL RODEO 1808 - 1.400.000 | I32: ALEJANDRA RESTREPO
E33: TOTAL-----------------------------------> | F33: =SUM(F22:F32) -> 11650000 | H33: =SUM(H22:H32) -> 225500
B35: ENERO 2022 - AURA POSSO
B36: CONTRATO | C36: PROPIETARIO | D36: OBSERVACIONES | E36: INMUEBLE | F36: CANON | G36: % | H36: AURA | I36: EXTERNO
B38: DESISTIDO | C38: Propietario dice que no puede enviar composición accionaria de la empresa que aparece como propietaria, dice que no le queda posible. | D38: AURA POSSO | E38: ANKARA 401 - 2.300.000 | I38: JULIAN SOLIS
E39: TOTAL-----------------------------------> | F39: =SUM(F37:F38) -> 0 | H39: =SUM(H37:H38) -> 0
B41: ENERO 2022 - PORTADA
B42: CONTRATO | C42: PROPIETARIO | D42: OBSERVACIONES | E42: INMUEBLE | F42: CANON | G42: % | H42: PORTADA | I42: EXTERNO
E48: TOTAL-----------------------------------> | F48: =SUM(F43:F47) -> 0 | H48: =SUM(H43:H47) -> 0
B50: CONSOLIDADO ENERO LAURELES 2022- VERÓNICA ORTIZ
B51: CONTRATO | C51: PROPIETARIO | D51: OBSERVACIONES | E51: INMUEBLE | F51: CANON | G51: % | H51: VERÓNICA | I51: EXTERNO | J51: FACTURADO
B52: 12993 | C52: 0.1 | D52: STEFANNY AGUDELO | E52: VILLA DE ABURRA 201 | F52: 1850000 | I52: ALEJANDRA RESTREPO | J52: CATHERINE
B53: 12996 | C53: 0.1 | D53: STEFANNY AGUDELO | E53: LOS CABOS 322 | F53: 2100000 | I53: JULIAN SOLIS | J53: CATHERINE
B54: 13005 | C54: 0.1 | D54: STEFANNY AGUDELO | E54: CAMINO DEL PARQUE 2512 | F54: 1700000 | I54: JULIAN SOLIS | J54: CATHERINE
B55: 12961 | C55: 0.1 | D55: CRISTIAN | E55: LOS CABOS 630 | F55: 1700000 | I55: ALEJANDRA RESTREPO | J55: CATHERINE
B56: 12956 | C56: 0.1 | D56: CRISTIAN | E56: EDIFICIO BENIDORM 302 | F56: 1350000 | I56: ALEJANDRA RESTREPO | J56: CATHERINE
B57: 12924 | C57: 0.1 | D57: ANDREA | E57: GUADARRAMA 526 | F57: 1600000 | I57: JULIAN SOLIS | J57: CATHERINE
B58: 12970 | C58: 0.1 | D58: CRISTIAN | E58: ALPES PLAZA 1803 | F58: 1650000 | I58: JULIAN SOLIS | J58: CATHERINE
B59: 12963 | C59: 0.1 | D59: ANDREA | E59: ZAPZURRO 201 | F59: 1850000 | I59: JULIAN SOLIS | J59: CATHERINE
B60: 13026 | C60: 0.1 | D60: STEFANNY AGUDELO | E60: LOS CABOS 9926 | F60: 1950000 | G60: 0.02 | H60: =G60*F60 -> 39000 | I60: JULIAN SOLIS | J60: OK
B61: 13033 | C61: 0.1 | D61: ANDREA | E61: CARRERA 84 35-62 | F61: 1200000 | G61: 0.02 | H61: =G61*F61 -> 24000 | I61: JULIAN SOLIS | J61: OK
B62: 13102 | C62: 0.1 | D62: STEFANNY AGUDELO | E62: PENTAGRAMA 2216 | F62: 1500000 | G62: 0.02 | H62: =G62*F62 -> 30000 | I62: VICTOR VALENCIA | J62: OK
B63: 13098 | C63: 0.1 | D63: STEFANNY AGUDELO | E63: LOS CABOS 1101 SUBROGACION | F63: 1800000 | G63: 0.02 | H63: =G63*F63 -> 36000 | I63: VICTOR VALENCIA | J63: OK
B64: 13094 | C64: 0.08 | D64: STEFANNY AGUDELO | E64: CALLE 65C 94 - 51 AP 101 | F64: 750000 | G64: 0.01 | H64: =G64*F64 -> 7500 | I64: PORTADA | J64: OK
B65: 13117 | C65: 0.1 | D65: LUISA MARIN | E65: RODEO VERDE 725 SUBROGACION | F65: 1200000 | G65: 0.02 | H65: =G65*F65 -> 24000 | I65: JULIAN SOLIS | J65: OK
B66: 13110 | C66: 0.1 | D66: LUISA MARIN | E66: CALLE 42 C N° 63C - 35 AP 901 | F66: 2750000 | G66: 0.02 | H66: =G66*F66 -> 55000 | I66: VICTOR VALENCIA | J66: OK
B67: 13118 | C67: 0.1 | D67: LUISA MARIN | E67: RODEO VERDE 622 | F67: 1100000 | G67: 0.02 | H67: =G67*F67 -> 22000 | I67: VICTOR VALENCIA | J67: OK
B68: DESISTIDO | C68: Propietario lo arrendo | D68: ANDREA | E68: CAMINO DEL PARQUE 2512 | F68: 1700000 | I68: ALEJANDRA RESTREPO
B69: DESISTIDO | C69: El cliente decide seguir buscando, no estaba convencido | D69: LUISA MARIN | E69: ARBOLEDA DEL RODEO 1808 | F69: 1400000 | I69: JULIAN SOLIS
B70: DESISTIDO | C70: iInquillino desiste porque dice que ya no le sirve sin parqueadero | D70: LUISA MARIN | E70: CALLE 35 80-42 | F70: 2200000 | I70: JULIAN SOLIS
B71: DESISTIDO | C71: El inquilino actual desiste de la subrogación y continua en el inmueble | D71: STEFANNY AGUDELO | E71: CARRERA 83A 32EE-44 SUBROGACIÓN | F71: 1300000 | I71: ALEJANDRA RESTREPO
B72: DESISTIDO | C72: Vendieron el carro y no les servia el sector así | D72: STEFANNY AGUDELO | E72: RODEO VERDE 912 | F72: 1200000 | I72: ALEJANDRA RESTREPO
B73: DESISTIDO | C73: Propietario lo arrendo | D73: STEFANNY AGUDELO | E73: MARQUEZ DE CACERES 802 | F73: 1500000 | I73: ALEJANDRA RESTREPO
B74: DESISTIDO | C74: Inquilinio desistio | D74: STEFANNY AGUDELO | E74: ARBOLEDA DEL RODEO 1808 | F74: 1400000 | I74: ALEJANDRA RESTREPO
B75: DESISTIDO | C75: Propietario dice que no puede enviar composición accionaria de la empresa que aparece como propietaria, dice que no le queda posible. | D75: AURA POSSO | E75: ANKARA 401 | F75: 2300000 | I75: JULIAN SOLIS
E76: TOTAL-----------------------------------> | F76: =SUM(F52:F67) -> 26050000 | G76: TOTAL A PAGAR ----> | H76: =SUM(H52:H67) -> 237500
E79: EN ESTUDIO
E80: EN FIRMAS
E81: FIRMADO | F81: =SUM(F52:F67) -> 26050000
E82: TOTAL | F82: =F79+F80+F81 -> 26050000
E83: REUBICANDO
E84: DESISTIDO | F84: =SUM(F68:F75) -> 13000000
B86: FEBRERO 2022
B88: FEBRERO 2022 - LUISA MARIN
B89: CONTRATO | C89: PROPIETARIO | D89: OBSERVACIONES | E89: INMUEBLE | F89: CANON | G89: % | H89: LUISA | I89: EXTERNO
B90: 13158 | C90: 0.08 | D90: LUISA MARIN | E90: JARDIN DE LOS LAURELES 419 | F90: 3900000 | G90: 0.01 | H90: =G90*F90 -> 39000 | I90: PORTADA
B91: 13161 | C91: 0.1 | D91: LUISA MARIN | E91: RODEO VERDE 912 SUBROGACION | F91: 1200000 | G91: 0.02 | H91: =G91*F91 -> 24000 | I91: ALEJANDRA RESTREPO
B92: 13177 | C92: 0.08 | D92: LUISA MARIN | E92: CAMINO DEL PARQUE 1710 | F92: 1850000 | G92: 0.01 | H92: =G92*F92 -> 18500 | I92: ALEJANDRA RESTREPO
B93: 13216 | C93: 0.1 | D93: LUISA MARIN | E93: EL ALCAZAR 222 | F93: 1500000 | G93: 0.02 | H93: =G93*F93 -> 30000 | I93: ALEJANDRA RESTREPO
B94: 13269 | C94: 0.1 | D94: LUISA MARIN | E94: LA GRAN ESQUINA 707 | F94: 1500000 | G94: 0.02 | H94: =G94*F94 -> 30000 | I94: VICTOR VALENCIA
B95: 13234 | C95: 0.08 | D95: LUISA MARIN | E95: LOCAL BAHIA BLANCA | F95: 1200000 | G95: 0.01 | H95: =G95*F95 -> 12000 | I95: VICTOR VALENCIA
B96: 13238 | C96: 0.1 | D96: LUISA MARIN | E96: BALCONES DE LA CONSOLATA 602 | F96: 1000000 | G96: 0.02 | H96: =G96*F96 -> 20000 | I96: JULIAN SOLIS
B97: 13281 | C97: 0.1 | D97: LUISA MARIN | E97: CARRERA 93 35B-118 SUBROGACION | F97: 1400000 | G97: 0.02 | H97: =G97*F97 -> 28000 | I97: JULIAN SOLIS
B98: DESISTIDO | C98: El inquilino dice que ya necesita un casa de 4 alcobas | D98: LUISA MARIN | E98: PORTAL DE SANTA RITA 302 -1.250.000 | I98: VICTOR VALENCIA
B99: DESISTIDO | C99: Se decidio por este apto, dessitio, luego se le mostraron 4 apartamentos más y al final dijo que no | D99: LUISA MARIN | E99: CALLE 35 80-42 - 2.200.000 | I99: JULIAN SOLIS
B100: DESISTIDO | C100: Toma un apartamento más economico | D100: LUISA MARIN | E100: CALLE 44B 86-12 APT 202 - 1.100.000 | I100: VICTOR VALENCIA
E101: TOTAL-----------------------------------> | F101: =SUM(F90:F100) -> 13550000 | G101: SE LIQUIDA EN BELLO
B103: FEBRERO 2022 - STEFANNY AGUDELO
B104: CONTRATO | C104: PROPIETARIO | D104: OBSERVACIONES | E104: INMUEBLE | F104: CANON | G104: % | H104: STEFANNY | I104: EXTERNO
B105: 13149 | C105: 0.1 | D105: STEFANNY AGUDELO | E105: MAZIRUMA 301 | F105: 1300000 | G105: 0.05 | H105: =G105*F105 -> 65000 | I105: VICTOR VALENCIA
B106: 13160 | C106: 0.1 | D106: STEFANNY AGUDELO | E106: CARRERA 80A 36-28 | F106: 760000 | G106: 0.05 | H106: =G106*F106 -> 38000 | I106: PORTADA
B107: 13164 | C107: 0.1 | D107: STEFANNY AGUDELO | E107: CARRERA 83A 37D - 11 APT 101 | F107: 2200000 | G107: 0.05 | H107: =G107*F107 -> 110000 | I107: JULIAN SOLIS
B108: 13173 | C108: 0.1 | D108: STEFANNY AGUDELO | E108: ALPHAPARK 302 | F108: 1000000 | G108: 0.05 | H108: =G108*F108 -> 50000 | I108: JULIAN SOLIS
B109: 13171 | C109: 0.1 | D109: STEFANNY AGUDELO | E109: CALLE 38C 89-38 APT 301 | F109: 1000000 | G109: 0.05 | H109: =G109*F109 -> 50000 | I109: JULIAN SOLIS
B110: 13198 | C110: 0.1 | D110: STEFANNY AGUDELO | E110: LOS CABOS 828 | F110: 1900000 | G110: 0.05 | H110: =G110*F110 -> 95000 | I110: JULIAN SOLIS
B111: 13206 | C111: 0.08 | D111: STEFANNY AGUDELO | E111: MIRADOR DE LA ARBOLEDA 1401 | F111: 1350000 | G111: 0.04 | H111: =G111*F111 -> 54000 | I111: VICTOR VALENCIA
B112: 13221 | C112: 0.1 | D112: STEFANNY AGUDELO | E112: PARQUES DE LA SIERRA 104 | F112: 1400000 | G112: 0.05 | H112: =G112*F112 -> 70000 | I112: ALEJANDRA RESTREPO
B113: 13230 | C113: 0.1 | D113: STEFANNY AGUDELO | E113: PENTAGRAMA 707 | F113: 1400000 | G113: 0.05 | H113: =G113*F113 -> 70000 | I113: KELLY GARCIA
B114: 13245 | C114: 0.1 | D114: STEFANNY AGUDELO | E114: SAN MARTIN 201 | F114: 1650000 | G114: 0.05 | H114: =G114*F114 -> 82500 | I114: VICTOR VALENCIA
B115: 13257 | C115: 0.08 | D115: STEFANNY AGUDELO | E115: SAN PATRICIO 1001 | F115: 3700000 | G115: 0.04 | H115: =G115*F115 -> 148000 | I115: VICTOR VALENCIA
B116: 13260 | C116: 0.08 | D116: STEFANNY AGUDELO | E116: NANTES 202 | F116: 1300000 | G116: 0.04 | H116: =G116*F116 -> 52000 | I116: VICTOR VALENCIA
... B132: 13405 | C132: 0.1 | D132: STEFANNY AGUDELO | E132: CALLE 42 C N° 63C - 35 AP 201 | F132: 3250000 | G132: 0.05 | H132: =G132*F132 -> 162500 | I132: KELLY GARCIA
...

Sheet CAPTACIONES
B2: ENERO 2022
B4: VICTOR VALENCIA - ENERO 2022
B5: FECHA | C5: TIPO | D5: APTO | E5: SECTOR | F5: VALOR | G5: PORTERO O DIRECTO | H5: AVISOS | I5: FOTOS | J5: CT ARRIENDO | K5: CT VENTA | L5: ASESOR
B6: 19/1/2022 | C6: APTO | D6: BALCONES DE CONQUISTADORES 201 | E6: CONQUISTADORES | F6: 3000000 | G6: PORTERO | H6: SI | I6: SI | J6: 1 | L6: LUISA
B7: 19/1/2022 | C7: APTO | D7: BALCONES DE CONQUISTADORES 501 | E7: CONQUISTADORES | F7: 2500000 | G7: PORTERO | H7: SI | I7: SI | J7: 1 | L7: LUISA
B8: 19/1/2022 | C8: APTO | D8: BALCONES DE CONQUISTADORES 601 | E8: CONQUISTADORES | F8: 2500000 | G8: PORTERO | H8: SI | I8: SI | J8: 1 | L8: LUISA
B9: 19/1/2022 | C9: APTO | D9: BALCONES DE CONQUISTADORES 901 | E9: CONQUISTADORES | F9: 2500000 | G9: PORTERO | H9: SI | I9: SI | J9: 1 | L9: LUISA
B10: 19/1/2022 | C10: APTO | D10: BALCONES DE CONQUISTADORES 1001 | E10: CONQUISTADORES | F10: 2500000 | G10: PORTERO | H10: SI | I10: SI | J10: 1 | L10: LUISA
B11: 19/1/2022 | C11: APTO | D11: EDF ACACIAS 401 | E11: LAURELES | F11: 1750000 | G11: DIRECTO | H11: SI | I11: SI | J11: 1 | L11: LUISA
B12: 19/1/2022 | C12: APTO | D12: MASSAMAGREL 301 | E12: LA CASTELLANA | F12: 2600000 | G12: PORTERO | H12: SI | I12: SI | J12: 1 | L12: STEFANNY
B13: 19/1/2022 | C13: APTO | D13: BALCONES DE CONQUISTADORES 301 | E13: CONQUISTADORES | F13: 2500000 | G13: PORTERO | H13: SI | I13: SI | J13: 1 | L13: STEFANNY
B14: 19/1/2022 | C14: APTO | D14: BALCONES DE CONQUISTADORES 401 | E14: CONQUISTADORES | F14: 2500000 | G14: PORTERO | H14: SI | I14: SI | J14: 1 | L14: STEFANNY
B15: 19/1/2022 | C15: APTO | D15: BALCONES DE CONQUISTADORES 801 | E15: CONQUISTADORES | F15: 2500000 | G15: PORTERO | H15: SI | I15: SI | J15: 1 | L15: STEFANNY
B16: 19/1/2022 | C16: APTO | D16: BALCONES DE CONQUISTADORES 701 | E16: CONQUISTADORES | F16: 2500000 | G16: PORTERO | H16: SI | I16: SI | J16: 1 | L16: STEFANNY
B17: 19/1/2022 | C17: APTO | D17: BALCONES DE CONQUISTADORES 1101 | E17: CONQUISTADORES | F17: 2500000 | G17: PORTERO | H17: SI | I17: SI | J17: 1 | L17: STEFANNY
... B25: 25/01/2022 | C25: APARTAMENTO | D25: ANUNCIACION NIÑA MARIA 401 | E25: SIMON BOLIVAR | F25: 2700000 | G25: PORTERO | H25: SI | I25: SI | J25: 1 | L25: STEFANNY
B26: 25/01/2022 | C26: APARTAMENTO | D26: SAN FERNANDO 304 | E26: SAN FERNANDO | F26: 75000000 | G26: DIRECTO | H26: NO | I26: SI | K26: 1 | L26: VENTAS
B27: 25/01/2022 | C27: APARTAMENTO | D27: EIDIFICIO TORRECILLAS DE LAURELES 701 | E27: LAURELES | F27: 485000000 | G27: DIRECTO | H27: NO | I27: SI | K27: 1 | L27: VENTAS
B28: 25/01/2022 | C28: CASA | D28: CALLE 33AA 82-19 | E28: CASTELLANA | F28: 1700000000 | G28: DIRECTO | H28: NO | I28: SI | K28: 1 | L28: VENTAS
B29: TOTAL | J29: =SUM(J6:J27) -> 20 | K29: =SUM(K6:K28) -> 3 | L29: =J29+K29 -> 23
B31: ALEJANDRA RESTREPO - ENERO 2022
B32: FECHA | C32: TIPO | D32: APTO | E32: SECTOR | F32: VALOR | G32: PORTERO O DIRECTO | H32: AVISOS | I32: FOTOS | J32: CT ARRIENDO | K32: CT VENTA | L32: ASESOR
B33: 28/12/2021 | C33: APARTAMENTO | D33: CR 78 45 12 AP 402 | E33: VELODROMO | F33: 1350000 | G33: DIRECTO | H33: SI | I33: SI | J33: 1 | L33: CRISTIAN
B34: 28/12/2021 | C34: APARTAESTUDIO | D34: CR 78 45 12 AP 203 | E34: VELODROMO | F34: 1100000 | G34: DIRECTO | H34: SI | I34: SI | J34: 1 | L34: STEFANNY
B35: 28/12/2021 | C35: APARTAMENTO | D35: SAN MIGUEL 803 | E35: LOMA DE LOS BERNAL | F35: 1800000 | G35: PORTERO | H35: NO | I35: SI | J35: 1 | L35: STEFANNY
B36: 28/12/2021 | C36: APARTAMENTO | D36: CL 44B 86 12 AP 202 | E36: LA AMERICA | F36: 1300000 | G36: DIRECTO | H36: SI | I36: SI | J36: 1 | L36: ANDREA
B37: 44652 | C37: CASA | D37: CR 71 45B 21 | E37: FLORIDA NUEVA | F37: 2000000 | G37: DIRECTO | H37: SI | I37: SI | J37: 1 | L37: ANDREA
B38: 44652 | C38: APARTAESTUDIO | D38: MARQUES DE CASERES 802 | E38: CONQUISTADORES | F38: 1500000 | G38: PORTERO | H38: SI | I38: SI | J38: 1 | L38: CRISTIAN
B39: 44348 | C39: APARTAMENTO | D39: OASIS DE LOS BERNAL 405 | E39: LOMA DE LOS BERNAL | F39: 1500000 | G39: PORTERO | H39: SI | I39: SI | J39: 1 | L39: AURA
B40: 44348 | C40: APARTAMENTO | D40: CALLE 32C 81A 90 201 | E40: VILLA DE ABURRA | F40: 2000000 | G40: DIRECTO | H40: SI | I40: SI | J40: 1 | L40: AURA
B41: 44501 | C41: APARTAMENTO | D41: CR 79A 20A 155 201 | E41: BELEN LA GLORIA | F41: 1400000 | G41: DIRECTO | H41: SI | I41: SI | J41: 1 | L41: LUISA
B42: 44501 | C42: APARTAMENTO | D42: CR83A 37D 11 101 | E42: SIMON BOLIVAR | F42: 2300000 | G42: DIRECTO | H42: SI | I42: SI | J42: 1 | L42: STEFANNY
B43: 44501 | C43: APARTAMENTO | D43: JARDIN DE LAURELES 419 | E43: LAURELES | F43: 3800000 | G43: PORTERO | H43: SI | I43: SI | J43: 1 | L43: STEFANNY
B44: 19/1/2021 | C44: APARTAMENTO | D44: OASIS DE LOS BERNAL 919 | E44: LOMA DE LOS BERNAL | F44: 280000000 | G44: PORTERO | H44: SI | I44: SI | K44: 1 | L44: VENTAS
B45: 24/01/2021 | C45: APARTAMENTO | D45: BISSÓ 909 | E45: LOMA DE LOS BERNAL | F45: 495000000 | G45: PORTERO | H45: NO | I45: SI | K45: 1 | L45: VENTAS
B47: TOTAL | J47: =SUM(J33:J46) -> 11 | K47: =SUM(K33:K46) -> 2 | L47: =J47+K47 -> 13
B49: JULIAN SOLIS - ENERO 2022
B50: FECHA | C50: TIPO | D50: APTO | E50: SECTOR | F50: VALOR | G50: PORTERO O DIRECTO | H50: AVISOS | I50: FOTOS | J50: CT ARRIENDO | K50: CT VENTA | L50: ASESOR
B51: 30/12/2021 | C51: CASA | D51: CR 78 29 38 3 PISO | E51: BELEN PARQUE | F51: 2000000 | G51: DIRECTO | H51: SI | I51: SI | J51: 1 | L51: CRISTIAN
B52: 44682 | C52: CASA | D52: CR 65 # 1 SUR 111 | E52: MALLORCA | F52: 2000000 | G52: DIRECTO | H52: NO | I52: SI | J52: 1 | L52: CRISTIAN
B53: 44713 | C53: APTO | D53: CALLE 34C 89 38 | E53: STA MONICA | F53: 1000000 | G53: DIRECTO | H53: SI | I53: SI | J53: 1 | L53: ANDREA
B54: 44713 | C54: APTO | D54: HABITAT 70 502 | E54: FLORIDA NUEVA | F54: 2500000 | G54: DIRECTO | H54: SI | I54: SI | J54: 1 | L54: AURA
B55: 44743 | C55: CASA | D55: CR 68A 42A 15 | E55: SAN JOAQUIN | F55: 2500000 | G55: DIRECTO | H55: SI | I55: SI | J55: 1 | L55: AURA
B56: 44501 | C56: CASA | D56: CLL 35 80 42 3 PISO | E56: LAURELES | F56: 2200000 | G56: DIRECTO | H56: SI | I56: SI | J56: 1 | L56: LUISA
B57: 44531 | C57: APTO | D57: EDF DAYAN 202 | E57: LAURELES | F57: 2200000 | G57: PORTERO | H57: SI | I57: SI | J57: 1 | L57: LUISA
B58: 19/01/2022 | C58: APTO | D58: ANKARA 401 | E58: SIMON BOLIVAR | F58: 2300000 | G58: PORTERO | H58: SI | I58: SI | J58: 1 | L58: AURA
B59: 19/1/2022 | C59: APARTAESTUDIO | D59: CLL 34C 81 60 | E59: CASTELLANA | F59: 1100000 | G59: DIRECTO | H59: SI | I59: SI | J59: 1 | L59: LUISA
B60: 20/01/2021 | C60: OFICINA | D60: CARRERA 77 43 -22 | E60: LAURELES | F60: 1400000 | G60: DIRECTO | H60: SI | I60: SI | J60: 1 | L60: LUISA
B61: 44682 | C61: APTO | D61: CL 44 70 59 | E61: FLORIDA NUEVA | F61: 295000000 | G61: DIRECTO | H61: NO | I61: SI | K61: 1 | L61: VENTAS
B62: 19/1/2022 | C62: APTO | D62: ORIHUELA N"2 803 | E62: BELEN ROSALES | F62: 400000000 | G62: PORTERO | H62: SI | I62: SI | K62: 1 | L62: VENTAS
B63: 20/01/2021 | C63: APARTAMENTO | D63: EDIFICIO CAMPO REAL 202 | E63: CONQUISTADORES | F63: 415000000 | G63: PORTERO | H63: NO | I63: SI | K63: 1 | L63: VENTAS
B64: TOTAL | J64: =SUM(J51:J63) -> 10 | K64: =SUM(K51:K63) -> 3 | L64: =J64+K64 -> 13
B66: FELIPE ECHEVERRI - ENERO 2022
B67: FECHA | C67: TIPO | D67: APTO | E67: SECTOR | F67: VALOR | G67: PORTERO O DIRECTO | H67: AVISOS | I67: FOTOS | J67: CT ARRIENDO | K67: CT VENTA | L67: ASESOR
B73: TOTAL | J73: =SUM(J68:J72) -> 0 | K73: =SUM(K68:K72) -> 0 | L73: =J73+K73 -> 0
B75: PORTADA - ENERO 2022
B76: FECHA | C76: TIPO | D76: APTO | E76: SECTOR | F76: VALOR | G76: PORTERO O DIRECTO | H76: AVISOS | I76: FOTOS | J76: CT ARRIENDO | K76: CT VENTA | L76: ASESOR
B77: 24/01/2021 | C77: APARTAMENTO | D77: PENTAGRAMA 1323 | E77: RODEO ALTO | F77: 1450000 | G77: DIRECTO | H77: NO | J77: 1 | L77: AURA
B79: TOTAL | J79: =SUM(J77:J78) -> 1 | K79: =SUM(K77:K78) -> 0 | L79: =J79+K79 -> 1
B82: FEBRERO 2022
B84: VICTOR VALENCIA - FEBRERO 2022
B85: FECHA | C85: TIPO | D85: APTO | E85: SECTOR | F85: VALOR | G85: PORTERO O DIRECTO | H85: AVISOS | I85: FOTOS | J85: CT ARRIENDO | K85: CT VENTA | L85: ASESOR
B86: 44563 | C86: APARTAMENTO | D86: BALCONES DE LA CONSOLTA 501 | E86: LAURELES | F86: 1100000 | G86: PORTERO | H86: SI | I86: SI | J86: 1 | L86: STEFANNY
B87: 44563 | C87: CASA | D87: CARRERA 82 20A - 47 | E87: BELEN | F87: 1500000 | G87: DIRECTO | H87: SI | I87: SI | J87: 1 | L87: LUISA
B88: 44563 | C88: APARTAMENTO | D88: LUNA DEL CAMPO 1106 | E88: ROBLEDO | F88: 1050000 | G88: DIRECTO | H88: NO | I88: SI | J88: 1 | L88: STEFANNY
B89: 44563 | C89: APARTAMENTO | D89: MIRADOR DE ARBOLEDA 1401 | E89: RODEO ALTO | F89: 1400000 | G89: PORTERO | H89: SI | I89: SI | J89: 1 | L89: LUISA
B90: 44593 | C90: LOCAL | D90: CALLE 2 SUR 51 - 66 | E90: CRISTO REY | F90: 2800000 | G90: DIRECTO | H90: SI | I90: SI | J90: 1 | L90: STEFANNY
B91: 44563 | C91: APARTAMENTO | D91: LA GRAN ESQUINA 707 | E91: LAURELES | F91: 1500000 | G91: PORTERO | H91: SI | I91: SI | J91: 1 | L91: LUISA
B92: 44775 | C92: APARTAMENTO | D92: LAURELES DEL CASTILLO 906 | E92: LA CASTELLANA | F92: 2300000 | G92: PORTERO | H92: SI | I92: SI | J92: 1 | L92: STEFANNY
B93: 44775 | C93: APARTAMENTO | D93: EDIFICIO ATLANTA 401 | E93: LA CASTELLANA | F93: 2200000 | G93: PORTERO | H93: SI | I93: SI | J93: 1 | L93: DIANA
B94: 44775 | C94: APARTAMENTO | D94: PORTAL DE SANTA RITA 402 | E94: SIMON BOLIVAR | F94: 1200000 | G94: DIRECTO | H94: SI | I94: SI | J94: 1 | L94: KEVIN
B95: 44836 | C95: APARTAMENTO | D95: SAN PATRICIO 701 | E95: LAURELES | F95: 3800000 | G95: DIRECTO | H95: SI | I95: SI | J95: 1 | L95: KEVIN
B96: 16/02/2022 | C96: APARTAMENTO | D96: EDIFICIO PRADO REAL 203 | E96: PRADO CENTRO | F96: 750000 | G96: DIRECTO | H96: NO | I96: SI | J96: 1 | L96: DIANA
B97: 16/02/2022 | C97: APARTAMENTO | D97: BALCONES DE LA CONSOLTA 502 | E97: LAURELES | F97: 1000000 | G97: PORTERO | H97: SI | I97: SI | J97: 1 | L97: STEFANNY
B98: 16/02/2022 | C98: APARTAMENTO | D98: TORRES DEL BOSQUE 204 | E98: CRISTO REY - COPA | F98: 1100000 | G98: DIRECTO | H98: NO | I98: SI | J98: 1 | L98: DIANA
B99: 16/02/2022 | C99: APARTAMENTO | D99: EDIFICIO CHAQUIERO 601 | E99: LAURELES | F99: 3150000 | G99: DIRECTO | H99: SI | I99: SI | J99: 1 | L99: STEFANNY
B100: 19/02/2022 | C100: APARTAMENTO | D100: EDIFICIO DIANA 601 | E100: LAURELES | F100: 3000000 | G100: DIRECTO | H100: NO | I100: SI | J100: 1 | L100: JESSICA
B101: 23/02/2022 | C101: APARTAMENTO | D101: EDIFICIO GENOVA 101 | E101: CALASANZ | F101: 4500000 | G101: PORTERO | H101: NO | I101: SI | J101: 1 | L101: JESSICA
B102: 23/02/2022 | C102: APARTAMENTO | D102: EDIFICIO ANKARA 302 | E102: EL NOGAL | F102: 1700000 | G102: DIRECTO | H102: NO | I102: SI | J102: 1 | L102: JESSICA
B103: 23/02/2022 | C103: APARTAMENTO | D103: NOTAL DE BARCELONA 201 | E103: EL NOGAL | F103: 1100000 | G103: DIRECTO | H103: SI | I103: SI | J103: 1 | L103: JESSICA
B104: 23/02/2022 | C104: APARTAMENTO | D104: RAYO DE SOL 611 | E104: RODEO ALTO | F104: 1100000 | G104: PORTERO | H104: SI | I104: SI | J104: 1 | L104: JESSICA
B105: 25/02/2022 | C105: APARTAMENTO | D105: CALLE 30C 71-34 | E105: CASA | F105: 3200000 | G105: DIRECTO | H105: NO | I105: SI | J105: 1 | L105: JESSICA
B106: 44563 | C106: CASA | D106: CARRERA 82 20A - 47 | E106: BELEN | F106: 290000000 | G106: DIRECTO | H106: SI | I106: SI | K106: 1 | L106: VENTAS
B107: 44775 | C107: APARTAMENTO | D107: ARCOIRIS 1201 | E107: RODEO ALTO | F107: 22000000 | G107: DIRECTO | H107: NO | I107: SI | K107: 1 | L107: VENTAS
B108: 23/02/2022 | C108: APARTAMENTO | D108: EDIFICIO VICENZO 1101 | E108: LAURELES | F108: 1400000000 | G108: PORTERO | H108: NO | I108: SI | K108: 1 | L108: VENTAS
B109: TOTAL | J109: =SUM(J86:J107) -> 20 | K109: =SUM(K86:K108) -> 3 | L109: =J109+K109 -> 23
B111: ALEJANDRA RESTREPO - FEBRERO 2022
B112: FECHA | C112: TIPO | D112: APTO | E112: SECTOR | F112: VALOR | G112: PORTERO O DIRECTO | H112: AVISOS | I112: FOTOS | J112: CT ARRIENDO | K112: CT VENTA | L112: ASESOR
B113: 28/01/2022 | C113: APARTAMENTO | D113: PARQUES DE LA SIERRA 104 | E113: RODEO ALTO | F113: 1500000 | G113: PORTERO | H113: NO | I113: SI | J113: 1 | L113: LUISA
B114: 29/01/2021 | C114: APARTAMENTO | D114: SIEMPRE VERDE 1521 | E114: LOMA LOS BERNAL | F114: 2900000 | G114: PORTERO | H114: NO | I114: SI | J114: 1 | L114: STEFANNY
B115: 44653 | C115: CASA | D115: CARREAR 80AA 36-22 | E115: LAURELES | F115: 3000000 | G115: DIRECTO | H115: SI | I115: SI | J115: 1 | L115: STEFANNY
B116: 44318 | C116: APARTAMENTO | D116: TORRE ANGEL 2408 | E116: VILLA HERMOSA | F116: 900000 | G116: DIRECTO | H116: NO | I116: SI | J116: 1 | L116: LUISA
B117: 44775 | C117: APARTAMENTO | D117: TORRES DE VALBUENA 1706 | E117: LOMA LOS BERNAL | F117: 1400000 | G117: PORTERO | H117: NO | I117: SI | J117: 1 | L117: STEFANNY
B118: 44775 | C118: CASA | D118: CARRERA 84 33-82 APT 201 | E118: LA CASTELLANA | F118: 1400000 | G118: DIRECTO | H118: NO | I118: SI | J118: 1 | L118: DIANA
B119: 44775 | C119: APARTAMENTO | D119: CARRERA 84 33-82 APT 501 | E119: LA CASTELLANA | F119: 1500000 | G119: DIRECTO | H119: NO | I119: SI | J119: 1 | L119: STEFANNY
B120: 44775 | C120: APARTAMENTO | D120: CARRERA 79A 20A - 84 | E120: BELEN LA GLORIA | F120: 1250000 | G120: DIRECTO | H120: NO | I120: SI | J120: 1 | L120: STEFANNY
B121: 44836 | C121: APARTAMENTO | D121: CALLE 31 84A-08 | E121: BELEN LOS ALPES | F121: 1500000 | G121: DIRECTO | H121: SI | I121: SI | J121: 1 | L121: KEVIN
B122: 44836 | C122: APARTAMENTO | D122: CARRERA 86A 34-51 | E122: ALMERIA | F122: 1250000 | G122: DIRECTO | H122: NO | I122: SI | J122: 1 | L122: KEVIN
B123: 14/02/2022 | C123: APARTAMENTO | D123: BERNALEJAS 1302 | E123: LOMA LOS BERNAL | F123: 1900000 | G123: PORTERO | H123: NO | I123: SI | J123: 1 | L123: DIANA
B124: 16/02/2022 | C124: APARTAMENTO | D124: LAURELES DEL PARQUE 403 | E124: LAURELES | F124: 2500000 | G124: PORTERO | H124: SI | I124: SI | J124: 1 | L124: STEFANNY
...

Sheet PLAN CELULAR
A2: ASESOR | C2: MAYO
A3: STEFANNY AGUDELO | B3: 40500 | C3: X
A4: JESSICA ORTIZ | B4: 40500 | C4: X
A5: JOHANA PEÑA | B5: 40500 | C5: X
A6: VICTOR EDUARDO VALENICA | B6: 40500 | C6: X
A7: JULIAN SOLIS | B7: 40500 | C7: X
A8: ALEJANDRA RESTREPO | B8: 40500 | C8: X
A9: LUIS CORREA | B9: 40500 | C9: X
A10: FABER MENDEZ | B10: 40500 | C10: X
A11: TOTAL | B11: =SUM(B3:B10) -> 324000
A13: ASESOR | C13: JUNIO
A14: STEFANNY AGUDELO | B14: 40500 | C14: X
A15: JESSICA ORTIZ | B15: 40500 | C15: X
A16: JOHANA PEÑA | B16: 40500 | C16: X
A17: VICTOR EDUARDO VALENICA | B17: 40500 | C17: X
A18: JULIAN SOLIS | B18: 40500 | C18: X
A19: ALEJANDRA RESTREPO | B19: 40500 | C19: X
A20: DANIELA MONTOYA | B20: 40500 | C20: X
A21: LUIS CORREA | B21: 40500 | C21: X
A22: TOTAL | B22: =SUM(B14:B21) -> 324000
A24: ASESOR | C24: JULIO
A25: STEFANNY AGUDELO | B25: 40500 | C25: X
A26: JESSICA ORTIZ | B26: 40500 | C26: X
A27: VICTOR VALENICA | B27: 40500 | C27: X
A28: JULIAN SOLIS | B28: 40500 | C28: X
A29: ALEJANDRA RESTREPO | B29: 40500 | C29: X
A30: TOTAL | B30: =SUM(B25:B29) -> 202500
A32: ASESOR | C32: AGOSTO
A33: STEFANNY AGUDELO | B33: 40500 | C33: X
A34: JESSICA ORTIZ | B34: 40500 | C34: X
A35: VICTOR VALENICA | B35: 40500 | C35: X
A36: JULIAN SOLIS | B36: 40500 | C36: X
A37: ALEJANDRA RESTREPO | B37: VACACIONES
A38: JACKSON ARIAS | B38: 40500 | C38: X
A39: SANTIAGO HOYOS | B39: 44100 | C39: X
A40: TOTAL | B40: =SUM(B33:B39) -> 246600
A42: ASESOR | C42: SEPTIEMBRE
A43: STEFANNY AGUDELO | B43: 40500 | C43: X
A44: JESSICA ORTIZ | B44: 40500 | C44: X
A45: VICTOR VALENICA | B45: 40500 | C45: X
A46: JULIAN SOLIS | B46: 40500 | C46: X
A47: ALEJANDRA RESTREPO | B47: 81000 | C47: X | E47: DEBE EL MES DE AGOSTO
A48: JACKSON ARIAS | B48: 40500 | C48: X
A49: CATHERINE DIAZ | B49: 40500 | C49: X
A50: BRAYAN AGUDELO | B50: 44100 | C50: X
A51: SANTIAGO PINEDA | B51: 40500 | C51: X
A52: SANTIAGO HOYOS | B52: 44100 | C52: X
A53: TOTAL | B53: =SUM(B43:B52) -> 452700
A55: ASESOR | C55: OCTUBRE
A56: STEFANNY AGUDELO | B56: 40500 | C56: X
A57: JESSICA ORTIZ | B57: 40500 | C57: X
A58: VICTOR VALENICA | B58: 40500 | C58: X
A59: JULIAN SOLIS | B59: 40500 | C59: X
A60: ALEJANDRA RESTREPO | B60: 40500 | C60: X
A61: ANDRES SALDARRIAGA | B61: 40500 | C61: X
A62: ALONSO LOPEZ | B62: 40500 | C62: X
A63: JHORMAN ALVAREZ | B63: 44100 | C63: X
A64: SANTIAGO PINEDA | B64: 40500 | C64: X
A65: SANTIAGO HOYOS | B65: 44100 | C65: X
A66: TOTAL | B66: =SUM(B56:B65) -> 412200
A68: ASESOR | C68: NOVIEMBRE
A69: STEFANNY AGUDELO | B69: 40500 | C69: X
A70: JESSICA ORTIZ | B70: 40500 | C70: X
A71: VICTOR VALENICA | B71: 40500 | C71: X
A72: JULIAN SOLIS | B72: 40500
A73: ALEJANDRA RESTREPO | B73: 40500 | C73: X
A74: ANDRES SALDARRIAGA | B74: 40500 | C74: X
A75: JHORMAN ALVAREZ | B75: 44100 | C75: X
A76: SANTIAGO PINEDA | B76: 40500 | C76: X
A77: SANTIAGO HOYOS | B77: 44100 | C77: X
A78: TOTAL | B78: =SUM(B69:B77) -> 371700
A80: ASESOR | C80: DICIEMBRE
A81: RONALD MENDEZ | B81: 40500
A82: JESSICA ORTIZ | B82: 40500 | C82: OK
A83: VICTOR VALENICA | B83: 40500 | C83: OK
A84: JULIAN SOLIS | B84: 40500
A85: ALEJANDRA RESTREPO | B85: 40500
A86: ANDRES SALDARRIAGA | B86: 40500
A87: JHORMAN ALVAREZ | B87: 44100
A88: SANTIAGO PINEDA | B88: 40500
A89: SANTIAGO HOYOS | B89: 44100
A90: TOTAL | B90: =SUM(B81:B89) -> 371700

Sheet AUTORIZACIONES OTROSI - 6 MESES
B2: MAYO
B3: NEGOCIOS | C3: OTRO SI | D3: DURACION | E3: CTO FISICO | F3: OTRO | G3: MOTIVO
B4: SUBROGACION LA CASTELLANA CARRERA 83 N° 34C - 16 | C4: X | G4: NO SE RECIBE POR ARRGELOS, SE DEBE CAMBIAR FECHA DE INICIO
B5: ARCO 301 | C5: X | G5: INQUILINA VENIA DE QUIBDO POR EL PARO ARMADO NO PUDO VIAJAR, SE CAMBIA FECHA DE INICIO
B6: CARRERA 80A 40-39 | C6: X | E6: X | G6: PROPIETARIO MANIFIESTA SOLO QUERER FIRMAR FISICA YA QUE SIEMPRE TRABAJA ASI SUS CONTRATOS, QUEDO ERRADO EN EL % DE INCREMENTO, ES UN NEGOCIO COMERCIAL
B7: NANTES 401 | G7: CTO PROPIETARIO AL 8%, SE RESPETA PORCENTAJE CON EL QUE SE TRABAJA ESTE PROPIETARIO.
B8: SURBOGACION NANTES 302 | G8: CTO PROPIETARIO AL 8%, SE RESPETA PORCENTAJE CON EL QUE SE TRABAJA ESTE PROPIETARIO.
B9: FUENTE CAMPESTRE 808 | G9: CTO PROPIETARIO AL 9% SE RESPETA PORCENTAJE CON EL QUE SE TRABAJA ESTE PROPIETARIO.
B10: TORRE AVELLANA 701 | D10: 7 MESES | G10: ES UN ACUERDO ENTRE PROP E INQUILIN
B11: VITENZA 1412 | G11: COMISION AL 8% PARA QUE SE QUEDE CON PORTADA
B12: ZAMORANO 101 | C12: X | G12: CAMBIO DE COMISION Y FECHA DE PAGO AL 12% PAGOS LOS 3 - OTROSI INQUILINO POR CAMBIO DE FEHCA
B13: AMARANTA 401 | E13: X | G13: PROP SOLO QUIERE FIRMAR FISICO Y DESEA AUTENTICAR
B14: CAMINO DEL PARQUE 2304 | E14: X | G14: ES UN APTO QUE SE LE QUITO A ESCALA Y ERA DE UNICA FORMA QUE NOS LO DABA
B15: BALCONES DE LA CONSOLATA | D15: 6MESES | G15: EL INQUILINO HABIA DESISTIDO PERO LA PROPIETARIA ACEPTO CONTRATO POR ESTE TIEMPO
B17: JUNIO
B18: NEGOCIOS | C18: OTRO SI | D18: DURACION | E18: CTO FISICO | F18: OTRO | G18: MOTIVO
B19: NO SE PRESENTARO NOVEDADES
B21: JULIO
B22: NEGOCIOS | C22: OTRO SI | D22: DURACION | E22: CTO FISICO | F22: OTRO | G22: MOTIVO
B23: NO SE PRESENTARO NOVEDADES
B25: AGOSTO
B26: NEGOCIOS | C26: OTRO SI | D26: DURACION | E26: CTO FISICO | F26: OTRO | G26: MOTIVO
B27: ALCAZAR DE SAN FRANCISCO 502 | C27: X | G27: OTROSI CTO ADMON E INQUILINO POR CLAUSULA ADICIONAL
B28: CARRERA 81 # 40-72 | F28: X | G28: PAGO EL 5 DE CADA MES POR QUE EL PROP SE IBA A QUITAR POR LA FECHA DE PAGO
B29: JAIMAR 104 | C29: X | G29: CAMBIO DE FECHA DE INICIO
B30: CALLE 40 81A 44 | C30: X | G30: CAMBIO DE CANON PROP
B31: TORRE LAUREL 401 | D31: X | G31: CTO A 6 MESES POR SOLICITUD DE LA PROPIETARIA
B32: MONTELIMAR 905 | C32: X | G32: POR CAMBIO FECHA DE INICIO AUN NO ESTABA PINTADO
B33: RODEO VERDE 523 | D33: X | G33: CONTRATO 6 MESES POR SOLICITUD DEL CLIENTE PROP AUTORIZA
B36: SEPTIEMBRE
B37: NEGOCIOS | C37: OTRO SI | D37: DURACION | E37: CTO FISICO | F37: OTRO | G37: MOTIVO
