Workbook

Sheet INFORME 2019
A1: INFORME ENERO 2019 ENVIGADO
A3: ALEJANDRO BEDOYA
A4: CONSIGNACIONES | B4: CONTRATO | C4: %PROPIETARIO | D4: INMUEBLE | E4: CANON | F4: % | G4: comision | H4: ASESOR 2 | I4: EJECUTIVA | J4: OBSERVACIONES | K4: CONTRATO | L4: INMUEBLE | M4: CANON | N4: %
A5: 20+3 | B5: 7738 | C5: 0.1 | D5: NATIVO ARENA 1408 - 2.500.000 | E5: 2500000 | F5: 0.12 | G5: =E5*F5 -> 300000 | H5: ALEJANDRO BEDOYA | I5: MELBI CASTRILLON | K5: 7815 | L5: ZARZAMORA 705 | M5: 2250000 | N5: 0.05 | O5: =M5*N5 -> 112500
B6: 7749 | C6: 0.1 | D6: PUERTO LUNA 813 -SUBROGACION | E6: 1350000 | F6: 0.07 | G6: =F6*E6 -> 94500 | H6: PORTADA | I6: MELBI CASTRILLON | K6: 7816 | L6: PUERTO LUNA 604 | M6: 1500000 | N6: 0.05 | O6: =M6*N6 -> 75000
B7: 7812 | C7: 0.1 | D7: CUBIK 406 SUBROGACION | E7: 1770000 | F7: 0.07 | G7: =F7*E7 -> 123900 | H7: PORTADA | I7: RONALD MENDEZ
B8: 7782 | C8: 0.1 | D8: CHATEL 308 - 2.000.000 | E8: 2000000 | F8: 0.12 | G8: =E8*F8 -> 240000 | H8: ALEJANDRO BEDOYA | I8: RONALD MENDEZ
B9: 7789 | C9: 0.1 | D9: ENTREPARQUES 623 RECIBIMIENTO | E9: 1850000 | F9: 0.07 | G9: =E9*F9 -> 129500 | H9: PORTADA | I9: RONALD MENDEZ
B10: 7813 | C10: 0.1 | D10: NATIVO ARENA 1004 - RECIBIMIENTO | E10: 3750000 | F10: 0.07 | G10: =E10*F10 -> 262500 | H10: PORTADA | I10: MELBI CASTRILLON
B11: 7829 | C11: 0.1 | D11: TERRAZINO ZUÑIGA 902 REUBICACION | E11: 2600000 | F11: 0.12 | G11: =E11*F11 -> 312000 | H11: ALEJANDRO BEDOYA | I11: MELBI CASTRILLON
B12: 7834 | C12: 0.08 | D12: BRUJA BONITA 408 - 2.500.000 | E12: 2500000 | F12: 0.1 | G12: =E12*F12 -> 250000 | H12: ALEJANDRO BEDOYA | I12: MELBI CASTRILLON
B13: 7856 | C13: 0.1 | D13: BIOCITY GRAND 1517 | E13: 1800000 | F13: 0.07 | G13: =E13*F13 -> 126000 | H13: ANDRES MIRANDA | I13: RONALD MENDEZ
B14: DESISTIDO | C14: 0.1 | D14: PAMELA - 2.200.000 TIERRA GRATA ESMERALDAL | I14: MELBI CASTRILLON
B15: DESISTIDO | C15: 0.1 | D15: PUERTO LUNA 1606 - 1.300.000 | I15: RONALD MENDEZ
O16: =SUM(O5:O15) -> 187500
D17: TOTAL | E17: =SUM(E5:E16) -> 20120000 | F17: TOTAL | G17: =SUM(G5:G15) -> 1838400 | L17: TOTAL--------------------------------------> | O17: =G17+O16 -> 2025900
A19: JUAN DIEGO HERRERA
A20: CONSIGNACIONES | B20: CONTRATO | C20: %PROPIETARIO | D20: INMUEBLE | E20: CANON | F20: % | G20: comision | H20: ASESOR 2 | I20: EJECUTIVA | J20: OBSERVACIONES | K20: CONTRATO | L20: INMUEBLE | M20: CANON | N20: %
A21: 20+5 | B21: 7762 | C21: 0.1 | D21: BRUJAS CAMPESTRE 905 REUBICACION | E21: 1850000 | F21: 0.07 | G21: =E21*F21 -> 129500 | H21: ANDRES MIRANDA | I21: MELBI CASTRILLON | K21: 7768 | L21: BOSQUES DEL ESMERALDAL 184 | M21: 2500000 | N21: 0.05 | O21: =N21*M21 -> 125000
B22: 7785 | C22: 0.1 | D22: VILLA CRISTINA 501 RECIBIMIENTO | E22: 1800000 | F22: 0.07 | G22: =F22*E22 -> 126000 | H22: PORTADA | I22: MELBI CASTRILLON
B23: 7752 | C23: 0.1 | D23: CALIFORNIA 1907 | E23: 1450000 | F23: 0.07 | G23: =F23*E23 -> 101500 | H23: JUAN PABLO VILLA | I23: MELBI CASTRILLON
B24: 7854 | C24: 0.1 | D24: AMARELLO IN 1505 | E24: 1800000 | F24: 0.07 | G24: =E24*F24 -> 126000 | H24: PORTADA | I24: MELBI CASTRILLON
B25: DESISTIDO | C25: 0.1 | D25: PORTAL DEL CERRO 507 - 1.150.000 | G25: =E25*F25 -> 0 | I25: MELBI CASTRILLON
O26: =SUM(O21:O23) -> 125000
D27: TOTAL | E27: =SUM(E21:E26) -> 6900000 | F27: TOTAL | G27: =SUM(G21:G26) -> 483000 | L27: TOTAL--------------------------------------> | O27: =O26+G27 -> 608000
A29: JUAN PABLO VILLA
A30: CONSIGNACIONES | B30: CONTRATO | C30: %PROPIETARIO | D30: INMUEBLE | E30: CANON | F30: % | G30: comision | H30: ASESOR 2 | I30: EJECUTIVA | J30: OBSERVACIONES | K30: CONTRATO | L30: INMUEBLE | M30: CANON | N30: %
A31: 5 | B31: DESISTIDO | C31: 0.1 | D31: BIOCITY GRAN 804 - 1.600.000 | G31: =E31*F31 -> 0 | I31: MELBI CASTRILLON | K31: 7752 | L31: CALIFORNIA 1907 | M31: 1450000 | N31: 0.04 | O31: =N31*M31 -> 58000
C32: 0.1 | G32: =E32*F32 -> 0
C33: 0.1 | G33: =F33*E33 -> 0
C34: 0.1 | G34: =F34*E34 -> 0 | O34: =SUM(O31:O33) -> 58000
D35: TOTAL | E35: =SUM(E31:E34) -> 0 | F35: TOTAL | G35: =SUM(G31:G34) -> 0 | L35: TOTAL--------------------------------------> | O35: =O34+G35 -> 58000
A37: ANDRES MIRANDA
A38: CONSIGNACIONES | B38: CONTRATO | C38: %PROPIETARIO | D38: INMUEBLE | E38: CANON | F38: % | G38: comision | H38: ASESOR 2 | I38: EJECUTIVA | J38: OBSERVACIONES | K38: CONTRATO | L38: INMUEBLE | M38: CANON | N38: %
A39: 20+3 | B39: 7730 | C39: 0.1 | D39: MULTIFAMILIAR LA ABADIA 203 | E39: 1400000 | F39: 0.1 | G39: =E39*F39 -> 140000 | H39: ANDRES MIRANDA | I39: MELBI CASTRILLON | K39: 7762 | L39: BRUJAS CAMPESTRE 905 | M39: 1850000 | N39: 0.05 | O39: =N39*M39 -> 92500
B40: 7768 | C40: 0.1 | D40: BOSQUES DEL ESMERALDAL 184 | E40: 2500000 | F40: 0.05 | G40: =E40*F40 -> 125000 | H40: JUAN DIEGO HERRERA | I40: RONALD MENDEZ | K40: 7826 | L40: BIOCITY GRAND 1517 | M40: 1800000 | N40: 0.05 | O40: =N40*M40 -> 90000
B41: 7836 | C41: 0.1 | D41: MONTEPIETRA 1722 | E41: 1800000 | F41: 0.1 | G41: =E41*F41 -> 180000 | H41: ANDRES MIRANDA | I41: MELBI CASTRILLON
B42: 7816 | C42: 0.1 | D42: PUERTO LUNA 1302 | E42: 1320500 | F42: 0.1 | G42: =E42*F42 -> 132050 | H42: ANDRES MIRANDA | I42: MELBI CASTRILLON
B43: 7832 | C43: 0.1 | D43: MULTIFAMILIAR LA ABADIA 406 - 1.450.000 | E43: 1450000 | F43: 0.1 | G43: =E43*F43 -> 145000 | H43: ANDRES MIRANDA | I43: RONALD MENDEZ
B44: DESISTIDO | C44: 0.1 | D44: OCLOCK 1504 - 2700.000 | G44: =F44*E44 -> 0 | I44: MELBI CASTRILLON
B45: DESISTIDO | C45: 0.1 | D45: MONTEPINAR 705 - 1.350.000 | G45: =F45*E45 -> 0 | I45: MELBI CASTRILLON
O47: =SUM(O39:O42) -> 182500
D48: TOTAL | E48: =SUM(E39:E47) -> 8470500 | F48: TOTAL | G48: =SUM(G39:G47) -> 722050 | L48: TOTAL--------------------------------------> | O48: =O47+G48 -> 904550
A50: DANIEL GUERRA
A51: CONSIGNACIONES | B51: CONTRATO | C51: %PROPIETARIO | D51: INMUEBLE | E51: CANON | F51: % | G51: comision | H51: ASESOR 2 | I51: EJECUTIVA | J51: OBSERVACIONES | K51: CONTRATO | L51: INMUEBLE | M51: CANON | N51: %
A52: 23+3 | B52: 7781 | C52: 0.1 | D52: BONANZA 301 | E52: 1800000 | F52: 0.1 | G52: =F52*E52 -> 180000 | H52: DANIEL GUERRA | I52: MELBI CASTRILLON | K52: 7775 | L52: SAN JUAN DE PUEBLA 406 | M52: 1550000 | N52: 0.05 | O52: =N52*M52 -> 77500
B53: 7792 | C53: 0.1 | D53: SKARDALIA 401 | E53: 1200000 | F53: 0.05 | G53: =F53*E53 -> 60000 | H53: PORTADA | I53: MELBI CASTRILLON | K53: 7758 | L53: MANANTIALES DE SAN JOSE | M53: 1150000 | N53: 0.05 | O53: =N53*M53 -> 57500
B54: 7865 | C54: 0.1 | D54: PUERTO LUNA 604 | E54: 1500000 | F54: 0.05 | G54: =F54*E54 -> 75000 | H54: ALEJANDRO BEDOYA | I54: RONALD MENDEZ
B55: 7830 | C55: 0.1 | D55: JARDINAL 201 | E55: 1100000 | F55: 0.1 | G55: =F55*E55 -> 110000 | H55: DANIEL GUERRA | I55: MELBI CASTRILLON
B56: DESISTIDO | C56: 0.1 | D56: MISSISSIPPI 1107 - RECIBIMIENTO 1.200.000 | G56: =E56*F56 -> 0 | I56: RONALD MENDEZ
B57: DESISTIDO | C57: 0.1 | D57: APTO 301 - 900.000 | G57: =E57*F57 -> 0 | I57: MELBI CASTRILLON | O57: =SUM(O52:O55) -> 135000
D58: TOTAL | E58: =SUM(E52:E57) -> 5600000 | F58: TOTAL | G58: =SUM(G52:G57) -> 425000 | L58: TOTAL--------------------------------------> | O58: =O57+G58 -> 560000
A60: PORTADA
A61: CONSIGNACIONES | B61: CONTRATO | C61: %PROPIETARIO | D61: INMUEBLE | E61: CANON | F61: % | G61: comision | H61: ASESOR 2 | I61: EJECUTIVA | J61: OBSERVACIONES | K61: CONTRATO | L61: INMUEBLE | M61: CANON | N61: %
G62: =E62*F62 -> 0 | K62: 7749 | L62: PUERTO LUNA 813 SUBROGACION | M62: 1350000 | N62: 0.05 | O62: =M62*N62 -> 67500
G63: =E63*F63 -> 0 | K63: 7798 | L63: ENTREPARQUES 623 RECIBIMIENTO | M63: 1850000 | N63: 0.05 | O63: =M63*N63 -> 92500
G64: =F64*E64 -> 0 | K64: 7813 | L64: NATIVO ARENA 1004 - RECIBIMIENTO | M64: 3750000 | N64: 0.05 | O64: =M64*N64 -> 187500
G65: =F65*E65 -> 0
G66: =E66*F66 -> 0
O68: =SUM(O62:O67) -> 347500
D69: TOTAL | E69: =SUM(E62:E68) -> 0 | F69: TOTAL | G69: =SUM(G62:G68) -> 0 | L69: TOTAL--------------------------------------> | O69: =O68+G69 -> 347500
A71: TOTAL FIRMADO | D71: =E69+E58+E48+E35+E27+E17 -> 41090500
A72: TOTAL EN FIRMAS
A73: TOTAL EN ESTUDIO
A76: CAPTACIONES Y ARRIENDOS POR SECTOR
C77: ENERO | D77: FEBRERO | E77: MARZO | F77: ABRIL | G77: MAYO | H77: JUNIO | I77: JULIO | J77: AGOSTO | K77: SEPTIEMBRE | L77: OCT UBRE | M77: NOVIEMBRE | N77: DICIEMBRE | O77: TOTAL ANUAL
A78: SEÑORIAL - LA CUENCA | B78: ARRIENDO | C78: 4170500 | D78: 5550000 | E78: 6950000 | F78: 1300000 | G78: 1200000 | H78: =C616 -> 3700000 | I78: =D716 -> 7500000 | J78: =C828 -> 7150000 | K78: =C930 -> 5450000 | O78: =SUM(D78:N78) -> 38800000
B79: CAPTACIONES | C79: 9 | D79: 27 | E79: 11 | F79: 9 | G79: 4 | H79: 10 | I79: 16 | J79: 5 | O79: =SUM(C79:N79) -> 91
A80: ZUÑIGA | B80: ARRIENDO | C80: 2600000 | D80: 2900000 | E80: 1900000 | F80: 0 | G80: 4100000 | H80: =C620 -> 5450000 | K80: =C934 -> 800000 | O80: =SUM(C80:N80) -> 17750000
B81: CAPTACIONES | C81: 3 | D81: 5 | E81: 5 | F81: 1 | G81: 5 | H81: 5 | I81: 2 | O81: =SUM(C81:N81) -> 26
A82: LOMA DEL ESMERALDAL | B82: ARRIENDO | C82: 4300000 | D82: 4200000 | E82: 9248700 | F82: 4700000 | G82: 5650000 | H82: =C622 -> 3700000 | I82: =D722 -> 7230000 | J82: =C834 -> 5350000 | O82: =SUM(C82:N82) -> 44378700
B83: CAPTACIONES | C83: 6 | D83: 10 | E83: 8 | F83: 5 | G83: 4 | H83: 6 | I83: 5 | J83: 2 | O83: =SUM(C83:N83) -> 46
A84: LOMA DEL ESCOBERO | B84: ARRIENDO | C84: 1800000 | D84: 4700000 | E84: 4900000 | F84: 3000000 | G84: 1800000 | H84: =C624 -> 5400000 | I84: =D724 -> 12500000 | O84: =SUM(C84:N84) -> 34100000
B85: CAPTACIONES | C85: 7 | D85: 16 | E85: 3 | F85: 11 | G85: 17 | H85: 7 | I85: 18 | O85: =SUM(C85:N85) -> 79
A86: LOMA DEL CHOCHO | B86: ARRIENDO | C86: 8100000 | D86: 4350000 | E86: 6600000 | F86: 6000000 | H86: =C626 -> 4000000 | I86: =D726 -> 4500000 | J86: =C838 -> 4250000 | O86: =SUM(C86:N86) -> 37800000
B87: CAPTACIONES | C87: 9 | D87: 6 | E87: 15 | F87: 4 | H87: 5 | I87: 7 | O87: =SUM(C87:N87) -> 46
A88: BENEDICTINOS | B88: ARRIENDO | C88: 2000000 | D88: 0 | G88: 2500000 | H88: =C633 -> 6700000 | I88: =D733 -> 0 | O88: =SUM(C88:N88) -> 11200000
B89: CAPTACIONES | C89: 0 | D89: 1 | G89: 1 | H89: 3 | O89: =SUM(C89:N89) -> 5
A90: LOMA DE LAS BRUJAS | B90: ARRIENDO | C90: 6120000 | D90: 2700000 | E90: 4750000 | F90: 4600000 | G90: 6450000 | H90: =C635 -> 4700000 | I90: =D735 -> 2000000 | J90: =C847 -> 10150000 | O90: =SUM(C90:N90) -> 41470000
B91: CAPTACIONES | C91: 14 | D91: 8 | E91: 7 | F91: 10 | G91: 8 | H91: 5 | I91: 14 | J91: 4 | O91: =SUM(C91:N91) -> 70
A92: LA ABADIA | B92: ARRIENDO | C92: 2850000 | D92: 4000000 | G92: 1500000 | H92: =C637 -> 1800000 | I92: =D737 -> 0 | O92: =SUM(C92:N92) -> 10150000
B93: CAPTACIONES | C93: 7 | D93: 1 | G93: 4 | H93: 3 | O93: =SUM(C93:N93) -> 15
A94: CAMINO VERDE | B94: ARRIENDO | C94: 1800000 | D94: 1350000 | E94: 3900000 | F94: 1300000 | G94: 3400000 | H94: =C639 -> 3700000 | O94: =SUM(C94:N94) -> 15450000
B95: CAPTACIONES | C95: 8 | D95: 3 | E95: 11 | F95: 4 | G95: 2 | H95: 2 | O95: =SUM(C95:N95) -> 30
A96: OTRAS ZONAS (DORADO-LAPAZ-MESA-SAN MATEO - TRIANON-MANGA AZUL-ANDALUCIA) | B96: ARRIENDO | C96: 5900000 | D96: 1100000 | E96: 1600000 | G96: 5150000 | H96: =C647 -> 6850000 | I96: 6920000 | J96: =C859 -> 3950000 | O96: =SUM(C96:N96) -> 31470000
B97: CAPTACIONES | C97: 30 | D97: 22 | E97: 5 | G97: 33 | H97: 21 | O97: =SUM(C97:N97) -> 111
A98: CHINGUI | B98: ARRIENDO | C98: 1450000 | D98: 0 | E98: 0 | F98: 0 | G98: 0 | I98: =D718 -> 1400000 | K98: =C932 -> 1300000 | O98: =SUM(C98:N98) -> 4150000
B99: CAPTACIONES | C99: 2 | D99: 2 | H99: 3 | O99: =SUM(C99:N99) -> 7
A100: ANTILLAS | B100: ARRIENDO | C100: 0 | D100: 1000000 | O100: =SUM(C100:N100) -> 1000000
B101: CAPTACIONES | C101: 1 | O101: =SUM(C101:N101) -> 1
A102: OTRAPARTE | B102: ARRIENDO | C102: 0 | D102: 0 | O102: =SUM(C102:N102) -> 0
B103: CAPTACIONES | C103: 1 | D103: 3 | O103: =SUM(C103:N103) -> 4
A104: EL PORTAL | B104: ARRIENDO | C104: 0 | D104: 0 | O104: =SUM(C104:N104) -> 0
B105: CAPTACIONES | C105: 0 | D105: 1 | O105: =SUM(C105:N105) -> 1
A106: LOMA CUMBRES | B106: ARRIENDO | C106: 0 | D106: 0 | E106: 3650000 | G106: 3250000 | I106: =D738 -> 4800000 | O106: =SUM(C106:N106) -> 11700000
B107: CAPTACIONES | C107: 2 | D107: 4 | E107: 3 | H107: 3 | O107: =SUM(C107:N107) -> 12
B108: ARRIENDO | D108: 0 | O108: =SUM(C108:N108) -> 0
B109: CAPTACIONES | D109: 0 | O109: =SUM(C109:N109) -> 0
C110: =C98+C96+C94+C92+C90+C88+C86+C84+C82+C80+C78 -> 41090500 | D110: =D100+D96+D94+D92+D90+D86+D84+D82+D80+D78 -> 31850000 | E110: =E106+E96+E94+E90+E86+E84+E82+E80+E78 -> 43498700 | F110: =F78+F80+F82+F84+F86+F88+F90+F92+F94+F96+F98+F100+F102+F104+F106+F108 -> 20900000 | G110: =G106+G96+G94+G92+G90+G88+G84+G82+G80+G78 -> 35000000 | H110: =H96+H94+H92+H90+H88+H86+H84+H82+H80+H78 -> 46000000 | I110: =I106+I98+I96+I90+I86+I84+I82+I78 -> 46850000 | J110: =SUM(J78+J82+J86+J90+J96) -> 30850000 | O110: =C110+D110+F110+G110+H110+I110+J110+K110+L110+M110+++++N110 -> 252540500
C111: =C107+C103+C101+C99+C97+C95+C93+C91+C87+C85+C83+C81+C79 -> 99 | D111: =D107+D105+D103+D99+D97+D95+D93+D91+D89+D87+D85+D83+D81+D79 -> 109 | E111: =E107+E97+E95+E91+E87+E85+E83+E81+E79 -> 68
...

Sheet INFORME ASESORES INTERNOS 
A3: # CONTRATO | B3: % PROPIETARIO | C3: UNIDAD | D3: OBSERVACION PORQUE CAMBIA EL % | E3: CANON | F3: % | G3: COMISION | H3: OBSERVACIONES | I3: ASESOR
A4: 7730 | B4: 0.1 | C4: MULTIFAMILIAR LA ABADIA 203 | E4: 1400000 | F4: 0.06 | G4: =E4*F4 -> 84000
A5: 7752 | B5: 0.1 | C5: CALIFORNIA 1907 | E5: 1450000 | F5: 0.06 | G5: =E5*F5 -> 87000
A6: 7762 | B6: 0.1 | C6: BRUJA CAMPESTRE 905 | E6: 1850000 | F6: 0.06 | G6: =E6*F6 -> 111000
A7: 7749 | B7: 0.1 | C7: PUERTO LUNA 813 EMPALME | E7: 1350000 | F7: 0.06 | G7: =E7*F7 -> 81000
A8: 7738 | B8: 0.1 | C8: NATIVO ARENA 1408 | E8: 2500000 | F8: 0.06 | G8: =E8*F8 -> 150000
A9: 7785 | B9: 0.1 | C9: VILLA CRISTINA 501 | E9: 1800000 | F9: 0.06 | G9: =E9*F9 -> 108000
A10: 7781 | B10: 0.1 | C10: BONANZA 301 | E10: 1800000 | F10: 0.06 | G10: =E10*F10 -> 108000
A11: 7792 | B11: 0.1 | C11: SKADARLIA | E11: 1200000 | F11: 0.06 | G11: =E11*F11 -> 72000
A12: 7813 | B12: 0.1 | C12: NATIVO MADERA 1004 | E12: 3750000 | F12: 0.06 | G12: =E12*F12 -> 225000
A13: 7836 | B13: 0.1 | C13: MONTEPIETRA 1722 | E13: 1800000 | F13: 0.06 | G13: =E13*F13 -> 108000
A14: 7816 | B14: 0.1 | C14: PUERTO LUNA 1302 | E14: 1320500 | F14: 0.06 | G14: =E14*F14 -> 79230
A15: 7834 | B15: 0.08 | C15: BRUJA BONITA 408 | E15: 2500000 | F15: 0.05 | G15: =E15*F15 -> 125000
... A18: 7854 | B18: 0.1 | C18: AMARELLO IN 1505 | E18: 1800000 | F18: 0.06 | G18: =E18*F18 -> 108000
B19: 0.1
B20: 0.1
B21: 0.1
E23: =SUM(E4:E19) -> 28220500 | G23: =SUM(G4:G18) -> 1668230
A26: INFORME INDIVIDUAL ENERO 2019- RONALD MENDEZ
A28: # CONTRATO | B28: % PROPIETARIO | C28: UNIDAD | D28: OBSERVACION PORQUE CAMBIA EL % | E28: CANON | F28: % | G28: COMISION | H28: OBSERVACIONES | I28: ASESOR
A29: 7812 | B29: 0.1 | C29: CUBIK 406 SUBROGACION | E29: 1770000 | F29: 0.02 | G29: =F29*E29 -> 35400
A30: 7782 | B30: 0.1 | C30: CHATEL 308 | E30: 2000000 | F30: 0.02 | G30: =F30*E30 -> 40000
A31: 7789 | B31: 0.1 | C31: ENTEPARQUES 623 | E31: 1850000 | F31: 0.02 | G31: =F31*E31 -> 37000
A32: 7768 | B32: 0.1 | C32: BOSQUES DEL ESMERALDAL 184 | E32: 2500000 | F32: 0.02 | G32: =F32*E32 -> 50000
A33: 7832 | B33: 0.1 | C33: MULTIFAMILIAR LA ABADIA 406 | E33: 1450000 | F33: 0.02 | G33: =F33*E33 -> 29000
A34: 7856 | B34: 0.1 | C34: BIOCITY GRAND 1517 | E34: 1800000 | F34: 0.02 | G34: =F34*E34 -> 36000
A35: 7865 | B35: 0.1 | C35: PUERTO LUNA 604 | E35: 1500000 | F35: 0.02 | G35: =F35*E35 -> 30000
B36: 0.1 | G36: =F36*E36 -> 0
B37: 0.1 | G37: =F37*E37 -> 0
B38: 0.1 | G38: =F38*E38 -> 0
E39: =SUM(E29:E35) -> 12870000 | G39: =SUM(G29:G38) -> 257400
A42: INFORME INDIVIDUAL DE ARRIENDOS ZONA ENVIGADO ENERO 2019 BIVIANA SALAZAR
A44: # CONTRATO | B44: PORCENTAJE PROPIETARIO | C44: INMUEBLE | D44: OBSERVACION CAMBIO DE % | E44: VALOR DEL CANON | F44: % | G44: COMISION
A45: 7730 | B45: 0.1 | C45: MULTIFAMILIAR LA ABADIA 203 | E45: 1400000 | F45: 0.025 | G45: =E45*F45 -> 35000
A46: 7752 | B46: 0.1 | C46: CALIFORNIA 1907 | E46: 1450000 | F46: 0.025 | G46: =E46*F46 -> 36250
A47: 7762 | B47: 0.1 | C47: BRUJA CAMPESTRE 905 | E47: 1850000 | F47: 0.025 | G47: =E47*F47 -> 46250
A48: 7749 | B48: 0.1 | C48: PUERTO LUNA 813 EMPALME | E48: 1350000 | F48: 0.025 | G48: =E48*F48 -> 33750
A49: 7738 | B49: 0.1 | C49: NATIVO ARENA 1408 | E49: 2500000 | F49: 0.025 | G49: =E49*F49 -> 62500
A50: 7785 | B50: 0.1 | C50: VILLA CRISTINA 501 | E50: 1800000 | F50: 0.025 | G50: =E50*F50 -> 45000
A51: 7781 | B51: 0.1 | C51: BONANZA 301 | E51: 1800000 | F51: 0.025 | G51: =E51*F51 -> 45000
A52: 7792 | B52: 0.1 | C52: SKADARLIA | E52: 1200000 | F52: 0.025 | G52: =E52*F52 -> 30000
A53: 7813 | B53: 0.1 | C53: NATIVO MADERA 1004 | E53: 3750000 | F53: 0.025 | G53: =E53*F53 -> 93750
A54: 7836 | B54: 0.1 | C54: MONTEPIETRA 1722 | E54: 1800000 | F54: 0.025 | G54: =E54*F54 -> 45000
A55: 7816 | B55: 0.1 | C55: PUERTO LUNA 1302 | E55: 1320500 | F55: 0.025 | G55: =E55*F55 -> 33012.5
A56: 7834 | B56: 0.08 | C56: BRUJA BONITA 408 | E56: 2500000 | F56: 0.015 | G56: =E56*F56 -> 37500
... A66: 7865 | B66: 0.1 | C66: PUERTO LUNA 604 | E66: 1500000 | F66: 0.025 | G66: =E66*F66 -> 37500
E68: =SUM(E45:E67) -> 41090500 | G68: =SUM(G45:G67) -> 1002262.5
A72: INFORME INDIVIDUAL FEBRERO 2019 MELBI CASTRILLON
A74: # CONTRATO | B74: % PROPIETARIO | C74: UNIDAD | D74: OBSERVACION PORQUE CAMBIA EL % | E74: CANON | F74: % | G74: COMISION | H74: OBSERVACIONES | I74: ASESOR
A75: 7874 | B75: 0.1 | C75: ACANTO 806 | E75: 2400000 | F75: 0.02 | G75: =E75*F75 -> 48000 | I75: JUAN DIEGO
A76: 7881 | B76: 0.1 | C76: NATIVO FOLRA 703 | E76: 2100000 | F76: 0.02 | G76: =E76*F76 -> 42000 | I76: JUAN DIEGO
A77: 7893 | B77: 0.1 | C77: CORALES DE LA ABADIA 1908 | E77: 1600000 | F77: 0.02 | G77: =E77*F77 -> 32000 | I77: JUAN PABLO
A78: 7920 | B78: 0.1 | C78: POSITANO 801 | E78: 2400000 | F78: 0.02 | G78: =E78*F78 -> 48000 | I78: JUAN DIEGO
A79: 7936 | B79: 0.1 | C79: AMARELLO 808 | E79: 1800000 | F79: 0.02 | G79: =E79*F79 -> 36000 | I79: ANDRES
A80: 7968 | B80: 0.1 | C80: TIERRA PROMETIDA CASA 174 | E80: 2700000 | F80: 0.02 | G80: =E80*F80 -> 54000 | I80: JUAN DIEGO
A81: 7971 | B81: 0.1 | C81: LAS ANTILLAS 103 | E81: 1000000 | F81: 0.02 | G81: =E81*F81 -> 20000 | I81: ANDRES
E85: =SUM(E75:E81) -> 14000000 | G85: =SUM(G75:G82) -> 280000
A87: INFORME INDIVIDUAL FEBRERO 2019- RONALD MENDEZ
A89: # CONTRATO | B89: % PROPIETARIO | C89: UNIDAD | D89: OBSERVACION PORQUE CAMBIA EL % | E89: CANON | F89: % | G89: COMISION | H89: OBSERVACIONES | I89: ASESOR
A90: 7925 | B90: 0.1 | C90: NATIVO ARENA 1301 | E90: 2250000 | F90: 0.04 | G90: =E90*F90 -> 90000 | I90: ALEJANDRO BRDOYA
A91: 7902 | B91: 0.1 | C91: MONTEPINAR 705 | E91: 1350000 | F91: 0.04 | G91: =E91*F91 -> 54000 | I91: JUAN PABLO VILLA
A92: 7898 | B92: 0.1 | C92: MAGDALENA DE LA CUENCA 1413 | E92: 1350000 | F92: 0.04 | G92: =E92*F92 -> 54000 | I92: JUAN PABLO VILLA
A93: 7931 | B93: 0.1 | C93: OCLOCK LIVING 1705 | E93: 2900000 | F93: 0.04 | G93: =E93*F93 -> 116000 | I93: JUAN PABLO VILLA
A94: 7949 | B94: 0.1 | C94: CASTELLI 205 | E94: 1400000 | F94: 0.04 | G94: =E94*F94 -> 56000 | I94: JUAN PABLO VILLA
A95: 7962 | B95: 0.1 | C95: ORINOCO DE LA CUENCA 914 | E95: 1200000 | F95: 0.04 | G95: =E95*F95 -> 48000 | I95: JUAN PABLO VILLA
A96: 7942 | B96: 0.1 | C96: PALO SANTO 1701 | E96: 1100000 | F96: 0.04 | G96: =E96*F96 -> 44000 | I96: ANDRES MIRANDA
A97: 7965 | B97: 0.1 | C97: AMARETTO 1903 | E97: 1750000 | F97: 0.04 | G97: =E97*F97 -> 70000 | I97: ANDRES MIRANDA
A98: 7990 | B98: 0.1 | C98: CASA GASCUÑA 255 | E98: 3300000 | F98: 0.04 | G98: =E98*F98 -> 132000 | I98: ALEJANDRO BRDOYA
A99: 7930 | B99: 0.1 | C99: CUENCA MAGDALENA 1607 | E99: 1250000 | F99: 0.04 | G99: =E99*F99 -> 50000 | I99: JUAN PABLO VILLA
B100: 0.1 | G100: =F100*E100 -> 0
B101: 0.1 | G101: =F101*E101 -> 0
E102: =SUM(E90:E101) -> 17850000 | G102: =SUM(G90:G101) -> 714000
A104: INFORME INDIVIDUAL DE ARRIENDOS ZONA ENVIGADO FEBRERO 2019 BIVIANA SALAZAR
A106: # CONTRATO | B106: PORCENTAJE PROPIETARIO | C106: INMUEBLE | D106: OBSERVACION CAMBIO DE % | E106: VALOR DEL CANON | F106: % | G106: COMISION
A107: 7925 | B107: 0.1 | C107: NATIVO ARENA 1301 | E107: 2250000 | F107: 0.02 | G107: =E107*F107 -> 45000
A108: 7874 | B108: 0.1 | C108: ACANTO 806 | E108: 2400000 | F108: 0.02 | G108: =E108*F108 -> 48000
A109: 7881 | B109: 0.1 | C109: NATIVO FLORA 703 | E109: 2100000 | F109: 0.02 | G109: =E109*F109 -> 42000
A110: 7920 | B110: 0.1 | C110: POSITANO 801 | E110: 2400000 | F110: 0.02 | G110: =E110*F110 -> 48000
A111: 7968 | B111: 0.1 | C111: TIERRA PROMETIDA CASA 174 | E111: 2700000 | F111: 0.02 | G111: =E111*F111 -> 54000
A112: 7893 | B112: 0.1 | C112: CORALES DE LA ABADIA 1908 | E112: 1600000 | F112: 0.02 | G112: =E112*F112 -> 32000
A113: 7902 | B113: 0.1 | C113: MONTEPINAR 705 | E113: 1350000 | F113: 0.02 | G113: =E113*F113 -> 27000
A114: 7898 | B114: 0.1 | C114: MAGDALENA DE LA CUENCA 1413 | E114: 1350000 | F114: 0.02 | G114: =E114*F114 -> 27000
A115: 7931 | B115: 0.1 | C115: OCLOCK LIVING 1705 | E115: 2900000 | F115: 0.02 | G115: =E115*F115 -> 58000
A116: 7949 | B116: 0.1 | C116: CASTELLI 205 | E116: 1400000 | F116: 0.02 | G116: =E116*F116 -> 28000
A117: 7962 | B117: 0.1 | C117: ORINOCO DE LA CUENCA 914 | E117: 1200000 | F117: 0.02 | G117: =E117*F117 -> 24000
A118: 7942 | B118: 0.1 | C118: PALO SANTO 1701 | E118: 1100000 | F118: 0.02 | G118: =E118*F118 -> 22000
... A121: 7971 | B121: 0.1 | C121: MIRADOR DE LAS ANTILLAS 103 | E121: 1000000 | F121: 0.02 | G121: =E121*F121 -> 20000
A122: 7990. | B122: 0.1 | C122: CASA GASCUÑA 255 | E122: 3300000 | F122: 0.02 | G122: =E122*F122 -> 66000
A123: 7930 | B123: 0.1 | C123: CUENCA MAGDALENA 1607 | E123: 1250000 | F123: 0.02 | G123: =E123*F123 -> 25000
B124: 0.1 | G124: =E124*F124 -> 0
B125: 0.1 | G125: =E125*F125 -> 0
E127: =SUM(E107:E125) -> 31850000 | G127: =SUM(G107:G126) -> 637000
A130: INFORME INDIVIDUAL MARZO 2019 MARIA CAMILA OCHOA
A132: # CONTRATO | B132: % PROPIETARIO | C132: UNIDAD | D132: OBSERVACION PORQUE CAMBIA EL % | E132: CANON | F132: % | G132: COMISION | H132: OBSERVACIONES | I132: ASESOR
A133: 8043 | B133: 0.1 | C133: CASA MANGA AZUL INT 301 | E133: 800000 | F133: 0.02 | G133: =E133*F133 -> 16000 | I133: JUAN PABLO VILLA
A134: 8038 | B134: 0.1 | C134: MONTE CARLO PLAZA PH APTO 501 | E134: 800000 | F134: 0.02 | G134: =E134*F134 -> 16000 | I134: DANIEL GUERRA
A135: 8066 | B135: 0.1 | C135: MAGDALENA APTO 1204 | E135: 1350000 | F135: 0.02 | G135: =E135*F135 -> 27000 | I135: JUAN PABLO VILLA
A136: 8086 | B136: 0.1 | C136: AMARETTO 803 | E136: 1750000 | F136: 0.02 | G136: =E136*F136 -> 35000 | I136: JUAN DIEGO HERRERA
A137: 8112 | B137: 0.1 | C137: ORINOCO DE LA CUENCA 1211 | E137: $1.300.000 | F137: 0.02 | G137: 26000 | I137: JUAN DIEGO HERRERA
A138: 8113 | B138: 0.1 | C138: BIOCITY EPIC 315 | E138: $1.600.000 | F138: 0.02 | G138: 26000 | I138: JUAN DIEGO HERRERA
...

Sheet INFORME ASESORES INTERNOS 2020
A1: INFORME INDIVIDUAL ENERO 2020 RONALD MENDEZ
A3: # CONTRATO | B3: % PROPIETARIO | C3: UNIDAD | D3: OBSERVACION PORQUE CAMBIA EL % | E3: CANON | F3: % | G3: COMISION | H3: OBSERVACIONES | I3: ASESOR
A5: 9286 | B5: 0.1 | C5: NATIVO FLORA 1401 2100000 | D5: ENTREGADO | E5: 2100000 | H5: FACTURADO | I5: ALEJANDRO BEDOYA
A6: 9323 | B6: 0.1 | C6: ALTOS DEL ESCOBERO 601 1´650.000 | D6: ENTREGADO | E6: 1650000 | H6: FACTURADO | I6: JUAN ESTEBAN MANRIQUE
B7: 0.09 | C7: BIOCITY 938 2´350.000 | D7: EN FIRMAS | E7: 2350000 | H7: PENDIENTE DE FACTURAR | I7: JUAN PABLO VILLA
A8: 9339 | B8: 0.1 | C8: GUALI 910 1´700.000 | D8: ENTREGADO | E8: 1700000 | H8: FACTURADO | I8: JUAN PABLO VILLA
A9: 9350 | B9: 0.1 | C9: MULTIFAMILIAR LA ABADIA 404 1´600.000 | D9: ENTREGADO | E9: 1600000 | H9: FACTURADO | I9: ANDRES MIRANDA
B10: 0.1 | C10: SALTAMONTE 426 1´900.000 | D10: EN FIRMAS | E10: 1900000 | H10: PENDIENTE DE FACTURAR | I10: ALEJANDRO BEDOYA
A11: 9344 | B11: 0.1 | C11: LAS ANTILLAS 411 1´200.000 | D11: ENTREGADO | E11: 1200000 | H11: FACTURADO | I11: ANDRES MIRANDA
A12: 9337 | B12: 0.1 | C12: VIENNA 1301 1´500.000 | D12: ENTREGADO | E12: 1500000 | H12: FACTURADO | I12: JUAN PABLO VILLA
A13: 9390 | B13: 0.1 | C13: CUMBRES DEL BOSQUE 505 1´600.000 | D13: ENTREGADO | E13: 1600000 | H13: FACTURADO | I13: JUAN PABLO VILLA
A14: 9321 | B14: 0.1 | C14: CORAZON ENVIGADO 701 900.000$ | D14: ENTREGADO | E14: 900000 | H14: FACTURADO | I14: ANDRES MIRANDA
B15: 0.1 | C15: MUGA 410 2´300.000$ | D15: EN FIRMAS | E15: 2300000 | H15: PENDIENTE DE FACTURAR | I15: ALEJANDRO BEDOYA
B16: 0.1 | C16: ALTOS DEL ESMERALDAL 705 1´800.000$ | D16: DESISTIO | H16: PENDIENTE DE FACTURAR | I16: JUAN PABLO VILLA
E17: =SUM(E5:E16) -> 18800000
A18: INFORME INDIVIDUAL ENERO 2020 DAHIANA HOYOS
A20: # CONTRATO | B20: % PROPIETARIO | C20: UNIDAD | D20: OBSERVACION PORQUE CAMBIA EL % | E20: CANON | F20: % | G20: COMISION | H20: OBSERVACIONES | I20: ASESOR
B21: 0.1 | C21: CASA INDEPENDIENTE ANDALUCIA $ 1.600.000 | D21: APROBADO BUSCANCO INMUEBLE | I21: JUAN PABLO VILLA
A22: 9328 | B22: 0.1 | C22: TORRE GUAYACAN 903 $ 2100000 | D22: ENTREGADO | E22: 2100000 | H22: FACTURADO | I22: JUAN PABLO VILLA
A23: 9291 | B23: 0 | C23: RIO SECRETO 2204 $ 1.450.000 | D23: ENTREGADO | E23: 1450000 | H23: FACTURADO | I23: ANDRES MIRANDA
A24: 9330 | B24: 0.1 | C24: MAGDALENA DE LA CUENCA 410 $ 1.350.000 | D24: ENTREGADO | E24: 1350000 | H24: FACTURADO | I24: ALEJANDRO BEDOYA
A25: 9353 | B25: 0.1 | C25: NATIVO MADERA 1704 $ 3.800.000 | D25: ENTREGADO | E25: 3800000 | H25: FACTURADO | I25: ALEJANDRO BEDOYA
A26: 9315 | B26: 0.1 | C26: MULTIFAMILIAR LA ABADIA 412 $ 1.900.000 | D26: ENTREGADO | E26: 1900000 | H26: FACTURADO | I26: JUAN PABLO VILLA
A27: 9303 | B27: 0.1 | C27: TRENTTO 411 | D27: ENTREGADO | E27: 1700000 | H27: FACTURADO | I27: ALEJANDRO BEDOYA
A28: 9349 | B28: 0.1 | C28: ST LAURENT 801 2.300.000 | D28: ENTREGADO | E28: 2300000 | H28: FACTURADO | I28: JUAN PABLO VILLA
A29: 9347 | B29: 0.1 | C29: APTO TERCER PISO ALCALA $ 1.500.000 | D29: EN FIRMAS | E29: 1500000 | H29: FACTURADO | I29: JUAN PABLO VILLA
A30: 9352 | B30: 0.1 | C30: BIOCITY 1241$ 1.700.000 | D30: ENTREGADO | E30: 1700000 | H30: FACTURADO | I30: ANDRES MIRANDA
B31: 0.1 | C31: CASA EL OASIS $ 1.100.000 | D31: DOCUEMNTOS APROBADOS /BUSCANDO APTO | I31: JUAN PABLO VILLA
B32: 0.1 | C32: BRUJA CAMPESTRE 909 $20.050.000 | D32: ENTREGADO | E32: 2050000 | I32: ALEJANDRO BEDOYA
C33: EDIFIICIO CRISTALES 202 $ 2.500.000 | D33: EN ESTUDIO | I33: JUAN ESTEBAN MARIQUE
E34: =SUM(E22:E32) -> 19850000
A35: INFORME INDIVIDUAL ENERO 2020 BIVIANA SALAZAR
A37: # CONTRATO | B37: PORCENTAJE PROPIETARIO | C37: INMUEBLE | D37: OBSERVACION CAMBIO DE % | E37: VALOR DEL CANON | F37: % | G37: COMISION
B38: 0.1 | C38: NATIVO FLORA 1401 | F38: 0.02 | G38: 2100000
E55: =SUM(E38:E54) -> 0 | G55: =SUM(G38:G54) -> 2100000
A57: INFORME INDIVIDUAL FEBRERO 2020 RONALD MENDEZ
A59: # CONTRATO | B59: % PROPIETARIO | C59: UNIDAD | D59: OBSERVACION PORQUE CAMBIA EL % | E59: CANON | F59: % | G59: COMISION | H59: OBSERVACIONES | I59: ASESOR
A61: 9286
A62: 9323
A64: 9339
A65: 9350
A67: 9344
A68: 9337
A69: 9390
A70: 9321
E73: =SUM(E61:E72) -> 0
A74: INFORME INDIVIDUAL FEBRERO 2020 DAHIANA HOYOS
A76: # CONTRATO | B76: % PROPIETARIO | C76: UNIDAD | D76: OBSERVACION PORQUE CAMBIA EL % | E76: CANON | F76: % | G76: COMISION | H76: OBSERVACIONES | I76: ASESOR
A91: INFORME INDIVIDUAL FEBRERO 2020 BIVIANA SALAZAR
A93: # CONTRATO | B93: PORCENTAJE PROPIETARIO | C93: INMUEBLE | D93: OBSERVACION CAMBIO DE % | E93: VALOR DEL CANON | F93: % | G93: COMISION
B94: 0.1 | C94: NATIVO FLORA 1401 | F94: 0.02 | G94: 2100000
E111: =SUM(E94:E110) -> 0 | G111: =SUM(G94:G110) -> 2100000

Sheet INFORME GENERAL 2022
A1: INFORME ENERO 2022 SEDE ENVIGADO
A3: ALEJANDRO BEDOYA
A4: CAPTACIONES | B4: CONTRATO | C4: PROPIETARIO | D4: INMUEBLE | E4: CANON | F4: % | G4: comision | H4: ASESOR 2 | I4: EJECUTIVA | J4: OBSERVACIONES | K4: CONTRATO | L4: INMUEBLE | M4: CANON | N4: %
A5: 20+3 | B5: 12911 | C5: 0.1 | D5: BRUJAS CAMPESTRE 9715 2.000.000 | E5: 2000000 | F5: 0.12 | G5: =F5*E5 -> 240000 | H5: ALEJANDRO BEDOYA | I5: DARIEN CIFUENTES | K5: 13059 | L5: BALTICO 1108 | M5: 2400000 | N5: 0.05 | O5: =N5*M5 -> 120000
B6: 12921 | C6: 0.1 | D6: BIOCITY GRAND 320 2300000 | E6: 2300000 | F6: 0.12 | G6: =F6*E6 -> 276000 | H6: ALEJANDRO BEDOYA | I6: CAROLINA PARRA | K6: 13070 | L6: SENDERO FRESCO 1404 | M6: 1600000 | N6: 0.04 | O6: =N6*M6 -> 64000
B7: 12939 | C7: 0.1 | D7: ST LAURENT 602 3.900.000 | E7: 3900000 | F7: 0.12 | G7: =F7*E7 -> 468000 | H7: ALEJANDRO BEDOYA | I7: CAROLINA PARRA | K7: 13066 | L7: MUGA 1212 | M7: 2600000 | N7: 0.05 | O7: =N7*M7 -> 130000
B8: 12902 | C8: 0.1 | D8: NATIVO FLORA 1314 2.750.000 | E8: 2750000 | F8: 0.07 | G8: =F8*E8 -> 192500 | H8: PORTADA | I8: CAROLINA PARRA
B9: 12964 | C9: 0.1 | D9: FORESTA 1406 1.800.000 | E9: 1800000 | F9: 0.12 | G9: =F9*E9 -> 216000 | H9: ALEJANDRO BEDOYA | I9: CAROLINA PARRA
B10: 12835 | C10: 0.1 | D10: MUZO 1302 2.300.000 | E10: 2300000 | F10: 0.07 | G10: =F10*E10 -> 161000 | H10: MARLON RODRIGUEZ | I10: CAROLINA PARRA
B11: 13104 | C11: 0.08 | D11: AMARELLO IN 906 - 2.350.000 | E11: 2350000 | F11: 0.1 | G11: =F11*E11 -> 235000 | H11: ALEJANDRO BEDOYA | I11: CAROLINA PARRA
B12: 12965 | C12: 0.1 | D12: REGATTA 1712 - 2.600.0000 | E12: 2600000 | F12: 0.07 | G12: =F12*E12 -> 182000 | H12: JUAN DIEGO HERRERA | I12: DARIEN CIFUENTES
B13: 13093 | C13: 0.1 | D13: NATIVO ARENA 1304 - 3.300.000 | E13: 3300000 | F13: 0.07 | G13: =F13*E13 -> 231000 | H13: MARLON RODRIGUEZ | I13: CAROLINA PARRA
B14: 13080 | C14: 0.08 | D14: QUEBEC 406 - 3.800.000 | E14: 3800000 | F14: 0.1 | G14: =F14*E14 -> 380000 | H14: ALEJANDRO BEDOYA | I14: DARIEN CIFUENTES
B15: 13078 | C15: 0.1 | D15: MUGA AP 1305 - 3.100.000 | E15: 3100000 | F15: 0.12 | G15: =F15*E15 -> 372000 | H15: ALEJANDRO BEDOYA | I15: CAROLINA PARRA
B16: 12920 | C16: 0.1 | D16: FORESTA 1403 | E16: 2050000 | F16: 0.12 | G16: =F16*E16 -> 246000 | H16: ALEJANDRO BEDOYA | I16: DARIEN CIFUENTES
B19: DESISTIO | D19: TIERRA GRATA ESMERALDAL 902 - 2.500.000 | I19: CAROLINA PARRA
B20: DESISTIDO | D20: MUZO 1302 2.300.000 | I20: CAROLINA PARRA | O20: =SUM(O5:O19) -> 314000
E21: =SUM(E5:E20) -> 32250000 | G21: =SUM(G5:G20) -> 3199500 | L21: TOTAL --------------------------------------> | O21: =G21+O20 -> 3513500
A24: JUAN PABLO VILLA
A25: CAPTACIONES | B25: CONTRATO | C25: PROPIETARIO | D25: INMUEBLE | E25: CANON | F25: % | G25: comision | H25: ASESOR 2 | I25: EJECUTIVA | J25: OBSERVACIONES | K25: CONTRATO | L25: INMUEBLE | M25: CANON | N25: %
A26: 20+3
B27: 13076 | C27: 0.1 | D27: GUALI 601 1.850.000 | E27: 1850000 | F27: 0.05 | G27: =F27*E27 -> 92500 | H27: MARLON RODRIGUEZ | I27: CAROLINA PARRA
C28: 0.1 | D28: MANZANARES 1219 1.600.000 | E28: 1600000 | F28: 0.06 | G28: =F28*E28 -> 96000 | H28: PORTADA | I28: ESTEFANIA ROMERO
E31: =SUM(E27:E30) -> 3450000 | G31: =SUM(G27:G30) -> 188500 | L31: TOTAL --------------------------------------> | O31: =G31+O30 -> 188500
A33: JUAN DIEGO HERRERA
A34: CAPTACIONES | B34: CONTRATO | C34: PROPIETARIO | D34: INMUEBLE | E34: CANON | F34: % | G34: comision | H34: ASESOR 2 | I34: EJECUTIVA | J34: OBSERVACIONES | K34: CONTRATO | L34: INMUEBLE | M34: CANON | N34: %
A35: 20+3 | B35: 13015 | C35: 0.1 | D35: MANZANARES 424 1.450.000 | E35: 1450000 | F35: 0.06 | G35: =F35*E35 -> 87000 | H35: PORTADA | I35: CAROLINA PARRA | K35: 12965 | L35: REGATTA 1712 | M35: 2600000 | N35: 0.05 | O35: =N35*M35 -> 130000
B36: 13063 | C36: 0.08 | D36: CORALES DE LA ABADIA AP 1505 - 2.300.000 | E36: 2300000 | F36: 0.05 | G36: =F36*E36 -> 115000 | H36: PORTADA | I36: ESTEFANIA ROMERO | K36: 13077 | L36: REGATTA 1012 | M36: 2500000 | N36: 0.05 | O36: =N36*M36 -> 125000
B37: 13050 | C37: 0.1 | D37: EPIC 706 - 2.150.000 | E37: 2150000 | F37: 0.06 | G37: =F37*E37 -> 129000 | H37: PORTADA | I37: DARIEN CIFUENTES
B38: DESISTIO | C38: CASA BARICHARA 107 4.400.000
B39: DESISTIO | C39: NATIVO FLORA 809 3.300.000 | O39: =SUM(O35:O38) -> 255000
B40: DESISTIDO | C40: SALTAMONTE | L40: TOTAL --------------------------------------> | O40: =G41+O39 -> 586000
E41: =SUM(E35:E40) -> 5900000 | G41: =SUM(G35:G40) -> 331000
A42: MARLON RODRIGUEZ
A43: CAPTACIONES | B43: CONTRATO | C43: PROPIETARIO | D43: INMUEBLE | E43: CANON | F43: % | G43: comision | H43: ASESOR 2 | I43: EJECUTIVA | J43: OBSERVACIONES | K43: CONTRATO | L43: INMUEBLE | M43: CANON | N43: %
A44: 20+3 | B44: 12913 | C44: 0.1 | D44: ABADIA DEL CAMPO 305 1.900.000 | E44: 1900000 | F44: 0.07 | G44: =F44*E44 -> 133000 | H44: PORTADA | I44: CAROLINA PARRA | K44: 13076 | L44: GUALI 601 | M44: 1850000 | N44: 0.05 | O44: =N44*M44 -> 92500
B45: 12906 | C45: 0.1 | D45: NATIVO ARENA 1711 2.500.000 | E45: 2500000 | F45: 0.12 | G45: =F45*E45 -> 300000 | H45: MARLON RODRIGUEZ | I45: CAROLINA PARRA | K45: 13093 | L45: NATIVO ARENA 1304 | M45: 3300000 | N45: 0.05 | O45: =N45*M45 -> 165000
B46: 12929 | C46: 0.1 | D46: SAO BENTO 1404 2.250.000 | E46: 2250000 | F46: 0.07 | G46: =F46*E46 -> 157500 | H46: PORTADA | I46: CAROLINA PARRA | K46: 12835 | L46: MUZO 1302 | M46: 2300000 | N46: 0.05 | O46: =N46*M46 -> 115000
B47: 12934 | C47: 0.1 | D47: GUALI 1001 1.800.000 | E47: 1800000 | F47: 0.12 | G47: =F47*E47 -> 216000 | H47: MARLON RODRIGUEZ | I47: DARIEN CIFUENTES
B48: 12967 | C48: 0.1 | D48: GUALI 616 -1800000 | E48: 1800000 | F48: 0.12 | G48: =F48*E48 -> 216000 | H48: MARLON RODRIGUEZ | I48: DARIEN CIFUENTES
B49: 13059 | C49: 0.1 | D49: BALTICO 1108 - 2.400.000 | E49: 2400000 | F49: 0.07 | G49: =F49*E49 -> 168000 | H49: ALEJANDRO BEDOYA | I49: DARIEN CIFUENTES
B50: 13070 | C50: 0.08 | D50: SENDERO FRESCO AP 1404 - 1.600.000 | E50: 1600000 | F50: 0.06 | G50: =F50*E50 -> 96000 | H50: ALEJANDRO BEDOYA | I50: ESTEFANIA ROMERO
B51: 13077 | C51: 0.1 | D51: REGATTA 1012 - 2.500.000 | E51: 2500000 | F51: 0.07 | G51: =F51*E51 -> 175000 | H51: JUAN DIEGO HERRERA | I51: DARIEN CIFUENTES
B52: 13058 | C52: 0.1 | D52: SAN SILVESTRE AP 1301 - 1.750.000 | E52: 1750000 | F52: 0.12 | G52: =F52*E52 -> 210000 | H52: MARLON RODRIGUEZ | I52: DARIEN CIFUENTES
B53: 13012 | C53: 0.1 | D53: SONATA 304 - 1.800.000 | E53: 1800000 | F53: 0.12 | G53: =F53*E53 -> 216000 | H53: MARLON RODRIGUEZ | I53: DARIEN CIFUENTES
B54: 13074 | C54: 0.1 | D54: TRENTTO 411 - 2.100.000 | E54: 2100000 | F54: 0.07 | G54: =F54*E54 -> 147000 | H54: PORTADA | I54: DARIEN CIFUENTES
B55: 13001 | C55: 0.1 | D55: CASTELLI 202 - 2.400.000 | E55: 2400000 | F55: 0.07 | G55: =F55*E55 -> 168000 | H55: EDISON MONTOYA | I55: DARIEN CIFUENTES
B56: 13066 | C56: 0.1 | D56: MUGA 1212 - 2.600.000 | E56: 2600000 | F56: 0.07 | G56: =F56*E56 -> 182000 | H56: ALEJANDRO BEDOYA | I56: DARIEN CIFUENTES
B57: 13088 | C57: 0.1 | D57: MONTEVENTO 1212 - 2.000.000 | E57: 2000000 | F57: 0.12 | G57: =F57*E57 -> 240000 | H57: MARLON RODRIGUEZ | I57: ESTEFANIA ROMERO
E59: =SUM(E44:E58) -> 29400000 | G59: =SUM(G44:G58) -> 2624500 | O59: =SUM(O44:O58) -> 372500
L60: TOTAL --------------------------------------> | O60: =G59+O59 -> 2997000
A62: PORTADA
A63: CAPTACIONES | B63: CONTRATO | C63: PROPIETARIO | D63: INMUEBLE | E63: CANON | F63: % | G63: comision | H63: ASESOR 2 | I63: EJECUTIVA | J63: OBSERVACIONES | K63: CONTRATO | L63: INMUEBLE | M63: CANON | N63: %
A71: TOTAL FIRMADO | D71: =E59+E41+E31+E21 -> 71000000
A72: TOTAL EN FIRMAS
A73: TOTAL EN ESTUDIO
A77: INFORME ASESORA INTERNA ENERO 2022 CAROLINA PARRA
A79: # CONTRATO | B79: % PROPIETARIO | C79: UNIDAD | D79: OBSERVACION PORQUE CAMBIA EL % | E79: CANON | F79: % | G79: COMISION | H79: OBSERVACIONES | I79: ASESOR
A80: 12913 | B80: 0.1 | C80: ABADIA DEL CAMPO 305 1.900.000 | D80: facturado | E80: 1900000 | F80: 0.05 | G80: =E80*F80 -> 95000 | I80: MARLON RODRIGUEZ
A81: 12906 | B81: 0.1 | C81: NATIVO ARENA 1711 2.500.000 | D81: facturado | E81: 2500000 | F81: 0.05 | G81: =E81*F81 -> 125000 | I81: MARLON RODRIGUEZ
A82: 12921 | B82: 0.1 | C82: BIOCITY GRAND 320 2.300.000 | D82: facturado | E82: 2300000 | F82: 0.05 | G82: =E82*F82 -> 115000 | I82: ALEJANDRO BEDOYA
A83: 12939 | B83: 0.1 | C83: ST LAURENT 602 3.900.000 | D83: facturado | E83: 3900000 | F83: 0.05 | G83: =E83*F83 -> 195000 | I83: ALEJANDRO BEDOYA
A84: 12902 | B84: 0.1 | C84: NATIVO FLORA 1314 2.750.000 | D84: facturado | E84: 2750000 | F84: 0.02 | G84: =E84*F84 -> 55000 | H84: cliente por portero | I84: ALEJANDRO BEDOYA
A85: 12929 | B85: 0.1 | C85: SAO BENTO 1404 2.250.000 | D85: facturado | E85: 2250000 | F85: 0.02 | G85: =E85*F85 -> 45000 | H85: cliente por portero | I85: MARLON RODRIGUEZ
A86: 12964 | B86: 0.1 | C86: FORESTA 1406 1.800.000 | D86: facturado | E86: 1800000 | F86: 0.05 | G86: =E86*F86 -> 90000 | I86: ALEJANDRO BEDOYA
A87: 13015 | B87: 0.1 | C87: MANZANARES 424 1.450.000 | D87: facturado | E87: 1450000 | F87: 0.05 | G87: =E87*F87 -> 72500 | I87: JUAN DIEGO HERRERA
A88: 12835 | B88: 0.1 | C88: MUZO 1302 2.300.000 | D88: facturado | E88: 2300000 | F88: 0.05 | G88: =E88*F88 -> 115000 | I88: ALEJANDRO BEDOYA
A89: 13076 | B89: 0.1 | C89: GUALI 601 1.850.000 | D89: facturado | E89: 1850000 | F89: 0.05 | G89: =E89*F89 -> 92500 | I89: JUAN PABLO VILLA
A90: 13093 | B90: 0.1 | C90: NATIVO ARENA 1304 3.300.000 | E90: 3300000 | F90: 0.05 | G90: =E90*F90 -> 165000 | I90: ALEJANDRO BEDOYA
A91: 13104 | B91: 0.08 | C91: AMARELLO 906 2.350.000 | E91: 2350000 | F91: 0.04 | G91: =E91*F91 -> 94000 | I91: ALEJANDRO BEDOYA
A92: 13078 | B92: 0.1 | C92: MUGA 1305 3.100.000 | D92: facturado | E92: 3100000 | F92: 0.05 | G92: =E92*F92 -> 155000 | I92: ALEJANDRO BEDOYA
A95: DESISTIO | C95: MANZANARES 1219 1.600.000 | D95: SOLICITUD NEGADA
A96: DESISTIO | C96: CASA GUARNE 4.000.000 | D96: NO tiene deudor
E97: =SUM(E80:E96) -> 31750000 | G97: =SUM(G80:G96) -> 1414000
A102: INFORME ASESOR INTERNO ENERO 2022 DARIEN CIFUENTES
A104: # CONTRATO | B104: % PROPIETARIO | C104: UNIDAD | D104: OBSERVACION PORQUE CAMBIA EL % | E104: CANON | F104: % | G104: COMISION | H104: OBSERVACIONES | I104: ASESOR
A105: 12911 | B105: 0.1 | C105: BRUJAS CAMPESTRE 9715 | D105: FACTURADO | E105: 2000000 | F105: 0.05 | G105: =E105*F105 -> 100000 | H105: 10031739 - 3801 | I105: ALEJANDRO BEDOYA
A106: 12934 | B106: 0.1 | C106: GUALI 1001 | D106: FACTURADO | E106: 1800000 | F106: 0.05 | G106: =E106*F106 -> 90000 | H106: 10032914 - 4391 | I106: MARLON RODRIGUEZ
A107: 12920 | B107: 0.1 | C107: FORESTA 1403 | D107: FACTURADO | E107: 2050000 | F107: 0.05 | G107: =E107*F107 -> 102500 | H107: 10033234 - 7560 | I107: ALEJANDRO BEDOYA
A108: 13077 | B108: 0.1 | C108: REGATTA 1012 | D108: FACTURADO | E108: 2500000 | F108: 0.05 | G108: =E108*F108 -> 125000 | H108: 7367176 - 6428 | I108: MARLON RODRIGUEZ
A109: 12965 | B109: 0.1 | C109: REGATTA 1712 | D109: FACTURADO | E109: 2600000 | F109: 0.05 | G109: =E109*F109 -> 130000 | H109: 10036323 - 6008 | I109: ALEJANDRO BEDOYA
A110: 13001 | B110: 0.1 | C110: CASTELLI 202 | D110: FACTURADO | E110: 2400000 | F110: 0.05 | G110: =E110*F110 -> 120000 | H110: 10036471 - 5532 | I110: MARLON RODRIGUEZ
A111: 12967 | B111: 0.1 | C111: GUALI 616 | D111: FACTURADO | E111: 1800000 | F111: 0.05 | G111: =E111*F111 -> 90000 | H111: 10022929 - 2021 | I111: MARLON RODRIGUEZ
A112: 13059 | B112: 0.1 | C112: BALTICO 1108 | D112: FACTURADO | E112: 2400000 | F112: 0.05 | G112: =E112*F112 -> 120000 | H112: 10038667 - 9111 | I112: MARLON RODRIGUEZ
A113: 13080 | B113: 0.08 | C113: QUEBEC 406 | D113: FACTURADO | E113: 3800000 | F113: 0.04 | G113: =E113*F113 -> 152000 | H113: 10039781 - 9136 | I113: ALEJANDRO BEDOYA
A114: 13058 | B114: 0.1 | C114: SAN SILVESTRE 1301 | D114: FACTURADO | E114: 1750000 | F114: 0.05 | G114: =E114*F114 -> 87500 | H114: 7369036 - 5695 | I114: MARLON RODRIGUEZ
A115: 13050 | B115: 0.1 | C115: EPIC 706 | D115: FACTURADO | E115: 2150000 | F115: 0.05 | G115: =E115*F115 -> 107500 | H115: 10037374 - 1577 | I115: JUAN DEIGO HERRERA
A116: 13066 | B116: 0.1 | C116: MUGA 1212 | D116: FACTURADO | E116: 2600000 | F116: 0.05 | G116: =E116*F116 -> 130000 | H116: 10043534 - 1945 | I116: MARLON RODRIGUEZ
... A118: 13074 | B118: 0.1 | C118: TRENTTO 411 | D118: FACTURADO | E118: 2100000 | F118: 0.05 | G118: =E118*F118 -> 105000 | H118: 10044424 - 4515 | I118: MARLON RODRIGUEZ
E121: =SUM(E105:E303) -> 31750000 | G121: =SUM(G105:G303) -> 1549500
A127: INFORME ASESORA INTERNA ENERO 2022 ESTEFANIA ROMERO
A129: # CONTRATO | B129: % PROPIETARIO | C129: UNIDAD | D129: OBSERVACION PORQUE CAMBIA EL % | E129: CANON | F129: % | G129: COMISION | H129: OBSERVACIONES | I129: ASESOR
A130: 13109 | B130: 0.1 | C130: MANZANARES 1219 | D130: EN FIRMAS | E130: 1600000 | F130: 0.02 | G130: =F130*E130 -> 32000 | H130: 10050862-2143 | I130: JUAN PABLO VILLA
A131: 13063 | B131: 0.08 | C131: CORALES DE LA ABADIA 1505 | D131: FACTURADO | E131: 2300000 | F131: 0.01 | G131: =F131*E131 -> 23000 | I131: JUAN DIEGO HERRERA
A132: 13088 | B132: 0.1 | C132: MONTEVENTO 1212 | D132: FACTURAR | E132: 2000000 | F132: 0.02 | G132: =F132*E132 -> 40000 | I132: MARLON RODRIGUEZ
A133: 13070 | B133: 0.08 | C133: SENDERO FRESCO 1404 | D133: FACTURAR | E133: 1600000 | F133: 0.01 | G133: =F133*E133 -> 16000 | I133: MARLON RODRIGUEZ
E136: =SUM(E127:E135) -> 7500000 | G136: =SUM(G130:G135) -> 111000
A139: INFORME GENERAL ENERO 2022 BIVIANA SALAZAR
A141: N. CONTRATO | B141: PORCENTAJE | C141: INMUEBLE | D141: OBSERVACION PORQUE CAMBIA EL % | E141: CANON
A142: 12911 | B142: 0.1 | C142: BRUJAS CAMPESTRE 9715 2.000.000 | E142: 2000000 | F142: 0.03 | G142: =E142*F142 -> 60000
...

Sheet INFORME GLOBAL
A1: INFORME ANUAL ASESORES EXTERNOS 2022
B3: JUAN PABLO VILLA | C3: ALEJANDRO BEDOYA | D3: JUAN DIEGO HERRERA | E3: MARLON RODRIGUEZ | F3: CARLOS VALLEJO | G3: SERGIO CARMONA
A5: ENERO | B5: ='INFORME GENERAL 2022'!E31 -> 3450000 | C5: ='INFORME GENERAL 2022'!E21 -> 32250000 | D5: ='INFORME GENERAL 2022'!E41 -> 5900000 | E5: ='INFORME GENERAL 2022'!E59 -> 29400000 | G5: 0
A6: FEBRERO | B6: ='INFORME GENERAL 2022'!E225 -> 28220000 | C6: ='INFORME GENERAL 2022'!E198 -> 20150000 | D6: ='INFORME GENERAL 2022'!E238 -> 13400000 | E6: ='INFORME GENERAL 2022'!E255 -> 17300000 | G6: 0
A7: MARZO | B7: ='INFORME GENERAL 2022'!E422 -> 20004000 | C7: ='INFORME GENERAL 2022'!E402 -> 14650000 | D7: ='INFORME GENERAL 2022'!E436 -> 7580000 | E7: ='INFORME GENERAL 2022'!E460 -> 29450000 | G7: 0
A8: ABRIL | B8: ='INFORME GENERAL 2022'!E608 -> 15750000 | C8: ='INFORME GENERAL 2022'!E595 -> 6600000 | D8: ='INFORME GENERAL 2022'!E614 -> 0 | E8: ='INFORME GENERAL 2022'!E628 -> 13050000 | G8: 0
A9: MAYO | B9: ='INFORME GENERAL 2022'!E736 -> 18220000 | C9: ='INFORME GENERAL 2022'!E721 -> 23450000 | D9: ='INFORME GENERAL 2022'!E744 -> 2300000 | E9: ='INFORME GENERAL 2022'!E760 -> 21794300 | G9: 0
A10: JUNIO | B10: 16100000 | C10: 29800000 | D10: 4650000 | E10: 4200000 | G10: 0
A11: JULIO | B11: 26850000 | C11: 23800000 | D11: 0 | E11: 0 | F11: 11400000 | G11: 8500000
A12: AGOSTO | B12: 20000000 | C12: 13850000 | D12: 0 | E12: 0 | F12: 5300000 | G12: 0
A13: SEPTIEMBRE | B13: 23600000 | C13: 28350000 | D13: 0 | E13: 0 | F13: 22200000 | G13: 0
A14: OCTUBRE | B14: 20550000 | C14: 17900000 | D14: 0 | E14: 0 | F14: 24100000 | G14: 0
A15: NOVIEMBRE | B15: 20700000 | C15: 18800000 | F15: 13800000 | G15: 8400000
A16: DICIEMBRE
A18: TOTAL | B18: =SUM(B5:B17) -> 213444000 | C18: =SUM(C5:C17) -> 229600000 | D18: =SUM(D5:D17) -> 33830000 | E18: =SUM(E5:E17) -> 115194300 | F18: =SUM(F5:F17) -> 76800000 | G18: =SUM(G5:G17) -> 16900000
A19: META | B19: 192000000 | C19: 192000000 | D19: 156000000 | E19: 192000000 | F19: 192000000 | G19: 156000000
A20: DIFERENCIA | B20: =B18-B19 -> 21444000 | C20: =C18-C19 -> 37600000 | D20: =D18-D19 -> -122170000 | E20: =E18-E19 -> -76805700 | F20: =F18-F19 -> -115200000 | G20: =G18-G19 -> -139100000
A22: INFORME ANUAL ASESORES INTERNOS 2022
B24: CAROLINA PARRA | C24: ESTEFANIA ROMERO | D24: ANDREA ARISTIZABAL | E24: ESTEFHANIA VANEGAS
A26: ENERO | B26: ='INFORME GENERAL 2022'!E97 -> 31750000 | C26: ='INFORME GENERAL 2022'!E136 -> 7500000 | D26: 12000000
A27: FEBRERO | B27: ='INFORME GENERAL 2022'!E297 -> 27100000 | C27: ='INFORME GENERAL 2022'!E340 -> 25220000 | D27: 17100000
A28: MARZO | B28: ='INFORME GENERAL 2022'!E501 -> 20334000 | C28: ='INFORME GENERAL 2022'!E525 -> 25513175 | D28: 11550000
A29: ABRIL | B29: =0 -> 0 | C29: ='INFORME GENERAL 2022'!E677 -> 20800000 | D29: 13350000
A30: MAYO | B30: ='INFORME GENERAL 2022'!E796 -> 23450000 | C30: ='INFORME GENERAL 2022'!E816 -> 25220000 | D30: ='INFORME GENERAL 2022'!E835 -> 19044300
A31: JUNIO | B31: 24600000 | C31: 20600000 | D31: 13950000
A32: JULIO | B32: 27900000 | C32: 29850000 | D32: 14300000
A33: AGOSTO | B33: 23300000 | C33: 20400000 | D33: 0 | E33: 2300000
A34: SEPTIEMBRE | B34: 35000000 | C34: 37900000 | D34: 0 | E34: 12875000
A35: OCTUBRE | B35: 30450000 | C35: 30100000 | D35: 0 | E35: 6300000
A36: NOVIEMBRE | B36: 30500000 | C36: 32500000 | E36: 2300000
A37: DICIEMBRE
A39: TOTAL | B39: =SUM(B26:B37) -> 274384000 | C39: =SUM(C26:C37) -> 275603175 | D39: =SUM(D25:D38) -> 101294300 | E39: =SUM(E25:E38) -> 23775000
A40: META | B40: 216000000 | C40: 216000000 | D40: 216000000 | E40: 216000000
A41: DIFERENCIA | B41: =B39-B40 -> 58384000 | C41: =C39-C40 -> 59603175 | D41: =D39-D40 -> -114705700 | E41: =E39-E40 -> -192225000
A43: INFORME ANUAL SEDE 2022
A46: ENERO | B46: ='INFORME GENERAL 2022'!E173 -> 71000000
A47: FEBRERO | B47: ='INFORME GENERAL 2022'!E381 -> 80680000
A48: MARZO | B48: ='INFORME GENERAL 2022'!E580 -> 75247175
A49: ABRIL | B49: ='INFORME GENERAL 2022'!E698 -> 37600000
A50: MAYO | B50: ='INFORME GENERAL 2022'!E867 -> 65764300
A51: JUNIO | B51: 60800000
A52: JULIO | B52: 76850000
A53: AGOSTO | B53: 46300000
A54: SEPTIEMBRE | B54: 85470000
A55: OCTUBRE | B55: 66050000
A56: NOVIEMBRE | B56: 62300000
A57: DICIEMBRE
A59: TOTAL | B59: =SUM(B46:B57) -> 728061475
A60: META | B60: 720000000
A61: DIFERENCIA | B61: =B59-B60 -> 8061475

Sheet CAPTACIONES 2021
A2: JUAN DIEGO HERRERA ENERO 2019
A3: FECHA | B3: TIPO | C3: UNIDAD O DIRECCION | D3: BARRIO | E3: SECTOR | F3: VALOR | G3: PORTERO O DIRECTO | H3: AVISOS | I3: FOTOS | J3: ·# | K3: EJECUTIVA
B4: APTO | C4: COLORS APTO 615 | D4: LA MINA | E4: ENVIGADO | F4: 1200000 | G4: DIRECTO | H4: SI | I4: SI | J4: 1 | K4: RONALD
B5: APTO | C5: BIOCITY 1708 | D5: ESCOBERO | E5: ENVIGADO | F5: 2700000 | G5: JHOAN | H5: SI | I5: SI | J5: 1 | K5: RONALD
B6: CASA COMERC | C6: CASA SEGUNDO PISO 34 SUR 50 | D6: ANDALUCIA | E6: ENVIGADO | F6: 2500000 | G6: DIRECTO | H6: SI | I6: SI | J6: 1 | K6: MELBI
B7: APTO | C7: NATIVO ARENA 1405 | D7: EL CHOCHO | E7: ENVIGADO | F7: 2000000 | G7: SERGIO | H7: SI | I7: SI | J7: 1 | K7: RONALD
B8: APTO | C8: BOSQUE ADENTRO 622 | D8: EL CHOCHO | E8: ENVIGADO | F8: 2400000 | G8: DIRECTO | H8: SI | I8: SI | J8: 1 | K8: RONALD
B9: APTO | C9: TURMALINA 2004 | D9: COLORES | E9: COLORES | F9: 1550000 | G9: DIRECTO | H9: SI | I9: SI | J9: 1 | K9: PORTADA
B10: APTO | C10: ATALAYA DE SAN JORGE 501 | D10: LAS BRUJAS | E10: ENVIGADO | F10: 2000000 | G10: DIRECTO | H10: NO | I10: SI | J10: 1 | K10: MELBI
B11: APTO | C11: ENTREPINOS 1906 | D11: LAS BRUJAS | E11: ENVIGADO | F11: 5500000 | G11: ADARRIAGA | H11: NO | I11: SI | J11: 1 | K11: MELBI
B12: APTO | C12: SAN JUAN DE PUEBLA 408 | D12: CUMBRES | E12: ENVIGADO | F12: 1500000 | G12: REINALDO | H12: NO | I12: SI | J12: 1 | K12: MELBI
B13: APTO | C13: SAO BENTO 1206 | D13: ESMERALDAL | E13: ENVIGADO | F13: 2400000 | G13: OSCAR | H13: NO | I13: SI | J13: 1 | K13: MELBI
B14: APTO | C14: SAO BENTO 1010 | D14: ESMERALDAL | E14: ENVIGADO | F14: 2300000 | G14: OSCAR TAPASCO | H14: NO | I14: SI | J14: 1 | K14: MELBI
B15: LOCAL | C15: LOCAL 34-30 | D15: LAURELES | E15: LAURELES | F15: 6000000 | G15: DIRECTO | H15: NO | I15: SI | J15: 1 | K15: RONALD
... B23: APTO | C23: CALIFORNIA 89 | D23: CHINGUI | E23: ENVIGADO | F23: 1500000 | G23: FAUSTO | H23: SI | I23: SI | J23: 1 | K23: MELBI
B24: APTO | C24: BIOCITY 1708 | E24: ENVIGADO | F24: 535000000 | G24: JHOAN | K24: VENTAS
B25: BODEGA | C25: BODEGA LA ALDEA | E25: GUAYABAJL | F25: 10500000000 | G25: DIRECTO | K25: VENTAS
B26: CASA | C26: JARDINES DE LA COLINA 113 | E26: ENVIGADO | F26: 1200000000 | G26: DIRECTO | K26: VENTAS
B27: APTO | C27: RESERVA DE LA MARIA 805 | E27: ENVIGADO | F27: 850000000 | G27: DIRECTO | K27: VENTAS
B28: APTO | C28: ALAMEDA 604 | E28: SABANETA | F28: 410000000 | G28: DIRECTO | K28: VENTAS
J29: =SUM(J4:J23) -> 20
A30: ALEJANDRO BEDOYA ENERO 2019
A31: FECHA | B31: TIPO | C31: UNIDAD O DIRECCION | E31: SECTOR | F31: VALOR | G31: PORTERO O DIRECTO | H31: AVISOS | I31: FOTOS | J31: ·# | K31: EJECUTIVA
B32: APTO | C32: BRUJA BONITA 1205 | D32: LAS BRUJAS | E32: ENVIGADO | F32: 2600000 | G32: RODOLFO | H32: SI | I32: SI | J32: 1 | K32: RONALD
B33: APTO | C33: BALTICO 1002 | E33: ENVIGADO | F33: 2100000 | G33: TOBINSON | H33: SI | I33: SI | J33: 1 | K33: PORTADA
B34: APTO | C34: TORRE GUAYACAN 1803 | E34: ENVIGADO | F34: 2200000 | G34: LEONARDO | H34: SI | I34: SI | J34: 1 | K34: PORTADA
B35: APTO | C35: ENTREPARQUES 1010 | E35: ENVIGADO | F35: 2050000 | G35: RAFAEL | H35: SI | I35: SI | J35: 1 | K35: PORTADA
B36: APTO | C36: MUGA 606 | E36: ENVIGADO | F36: 3000000 | G36: RAFAEL | H36: SI | I36: SI | J36: 1 | K36: PORTADA
B37: APTO | C37: HACIENDA SAN JOSE 131 | E37: ENVIGADO | F37: 4050000 | G37: DIRECTO | H37: SI | I37: SI | J37: 1 | K37: RONALD
B38: APTO | C38: CONDOMINO CUMBRES 1108 | E38: ENVIGADO | F38: 2200000 | G38: DIRECTO | H38: SI | I38: SI | J38: 1 | K38: RONALD
B39: APTO | C39: AVILA 134 | E39: ENVIGADO | F39: 8500000 | G39: DIRECTO | H39: SI | I39: SI | J39: 1 | K39: RONALD
B40: APTO | C40: BRUJAS CAMPESTRE 9716 | E40: ENVIGADO | F40: 1800000 | G40: FLOREZ | H40: SI | I40: SI | J40: 1 | K40: RONALD
B41: APTO | C41: ZURICH 1004 | E41: ENVIGADO | F41: 2250000 | G41: WEIMAR | H41: SI | I41: SI | J41: 1 | K41: MELBI
B42: APTO | C42: MUGA 902 | E42: ENVIGADO | F42: 3100000 | G42: FREDY | H42: SI | I42: SI | J42: 1 | K42: MELBI
B43: APTO | C43: BALTICO 301 | E43: ENVIGADO | F43: 1800000 | G43: TOBINSON | H43: SI | I43: SI | J43: 1 | K43: MELBI
B44: APTO | C44: PUERTO LUNA 604 | E44: ENVIGADO | F44: 1500000 | G44: JAVIER | H44: SI | I44: SI | J44: 1 | K44: MELBI
... B51: APTO | C51: PUERTO LUNA 604 | E51: ENVIGADO | F51: 1350000 | G51: JAVIER | H51: SI | I51: SI | J51: 1 | K51: PORTADA
B52: CASA | C52: AVILA 134 | E52: ENVIGADO | F52: 1350000000 | G52: DIRECTO | K52: VENTAS
B53: APTO | C53: FELISA 1001 | E53: ENVIGADO | F53: 490000000 | G53: DIRECTO | K53: VENTAS
B54: APTO | C54: MUGA 606 | E54: ENVIGADO | F54: 565000000 | G54: RAFAEL | K54: VENTAS
J55: =SUM(J32:J51) -> 20
A56: JUAN PABLO VILLA ENERO 2019
A57: FECHA | B57: TIPO | C57: UNIDAD O DIRECCION | E57: SECTOR | F57: VALOR | G57: PORTERO O DIRECTO | H57: AVISOS | I57: FOTOS | J57: ·# | K57: EJECUTIVA
B58: LOCAL | C58: LOS NARANJOS 35 SUR 27 | E58: ENVIGADO | F58: 1600000 | G58: DIRECTO | H58: NO | I58: SI | J58: 1 | K58: MELBI
B59: APTO | C59: CAMINO DE LAS BRUJAS 524 | E59: ENVIGADO | F59: 1900000 | G59: DIRECTO | H59: SI | I59: SI | J59: 1 | K59: MELBI
B60: APTO | C60: BIOCITY GRAND 1204 | E60: ENVIGADO | F60: 1800000 | G60: JADER | H60: SI | I60: SI | J60: 1 | K60: RONALD
B61: APTO | C61: CUENCA MAGDALENA | E61: ENVIGADO | F61: 1300000 | G61: DIRECTO | H61: SI | I61: SI | J61: 1 | K61: MELBI
B62: APTO | C62: VITENZA 1107 | E62: ENVIGADO | F62: 1900000 | G62: FRAI | H62: NO | I62: SI | J62: 1 | K62: RONALD
A67: DANIEL GUERRA ENERO 2019
A68: FECHA | B68: TIPO | C68: UNIDAD O DIRECCION | E68: SECTOR | F68: VALOR | G68: PORTERO O DIRECTO | H68: AVISOS | I68: FOTOS | J68: ·# | K68: EJECUTIVA
B69: APTO | C69: ABADIA DEL CAMPO 304 | E69: ENVIGADO | F69: 1800000 | G69: JUAN | H69: NO | I69: SI | J69: 1 | K69: RONALD
B70: APTO | C70: AIRES DEL BOSQUE 305 | E70: ENVIGADO | F70: 1300000 | G70: DIRECTO | H70: NO | I70: SI | J70: 1 | K70: MELBI
B71: APTO | C71: ALTOS DE CLARAVAL CASA 133 | E71: ENVIGADO | F71: 4500000 | G71: DIRECTO | H71: SI | I71: SI | J71: 1 | K71: RONALD
B72: APTO | C72: ANTILLAS 611 | E72: ENVIGADO | F72: 1200000 | G72: DIRECTO | H72: NO | I72: SI | J72: 1 | K72: MELBI
B73: APTO | C73: APARTAESTUDIO 600 | E73: ENVIGADO | F73: 600000 | G73: DIRECTO | H73: NO | I73: SI | J73: 1 | K73: MELBI
B74: APTO | C74: APTO TRIANON 201 | E74: ENVIGADO | F74: 1300000 | G74: DIRECTO | H74: NO | I74: SI | J74: 1 | K74: MELBI
B75: APTO | C75: BALCONES DE LA HOLANDA 2003 | E75: ENVIGADO | F75: 1100000 | G75: JORGE | H75: NO | I75: SI | J75: 1 | K75: MELBI
B76: APTO | C76: BILBAO 202 | E76: ENVIGADO | F76: 950000 | G76: DIRECTO | H76: NO | I76: SI | J76: 1 | K76: MELBI
B77: APTO | C77: BIOCITY EPIC 315 | E77: ENVIGADO | F77: 1800000 | G77: DIRECTO | H77: NO | I77: SI | J77: 1 | K77: MELBI
B78: APTO | C78: CASA BARRIO MESA 101 | E78: ENVIGADO | F78: 1400000 | G78: DIRECTO | H78: NO | I78: SI | J78: 1 | K78: MELBI
B79: APTO | C79: EDIFICIO ZUÑIGA 302 | E79: ENVIGADO | F79: 1100000 | G79: DIRECTO | H79: SI | I79: SI | J79: 1 | K79: PORTADA
B80: APTO | C80: EDIFICIO JARDINAL 201 | E80: ENVIGADO | F80: 1100000 | G80: DIRECTO | H80: NO | I80: SI | J80: 1 | K80: PORTADA
... B91: APTO | C91: VOLGA DE LA CUENCA 507 | E91: ENVIGADO | F91: 1200000 | G91: YEFERSON | H91: NO | I91: SI | J91: 1 | K91: RONALD
B92: APTO | C92: VOLGA DE LA CUENCA 1008 | E92: ENVIGADO | F92: 240000000 | G92: DIRECTO | H92: NO | I92: SI | K92: VENTAS
B93: APTO | C93: CALIFORNIA 1105 | E93: ENVIGADO | F93: 330000000 | G93: DIRECTO | H93: NO | I93: SI | K93: VENTAS
B94: APTO | C94: LAS COMETAS 504 | E94: ENVIGADO | F94: 160000000 | G94: DIRECTO | H94: NO | I94: SO | K94: VENTAS
J95: =SUM(J69:J91) -> 23
A96: ANDRES MIRANDA ENERO 2019
A97: FECHA | B97: TIPO | C97: UNIDAD O DIRECCION | E97: SECTOR | F97: VALOR | G97: PORTERO O DIRECTO | H97: AVISOS | I97: FOTOS | J97: ·# | K97: EJECUTIVA
B98: APTO | C98: ACANTO 310 | E98: ENVIGADO | F98: 2500000 | G98: JHON | H98: SI | I98: SI | J98: 1 | K98: MELBI
B99: APTO | C99: ARBOLEDA DEL CAMPO 1808 | E99: NIQUIA | F99: 750000 | G99: DIRECTO | H99: si | I99: SI | J99: 1 | K99: RONALD
B100: APTO | C100: ARBOLEDA DEL ESMERALDAL 816 | E100: ENVIGADO | F100: 1600000 | G100: MUÑOZ | H100: SI | I100: SI | J100: 1 | K100: RONALD
B101: APTO | C101: ARRECIFES DE LA ABADIA 1505 | E101: ENVIGADO | F101: 1800000 | G101: HUGO | H101: NO | I101: SI | J101: 1 | K101: RONALD
B102: APTO | C102: BOSQUEADENTRO 219 | E102: ENVIGADO | F102: 2600000 | G102: DIRECTO | H102: SI | I102: SI | J102: 1 | K102: PORTADA
B103: CASA | C103: CASA CONDOMINIO ALTOS DEL ESCOBERO | E103: ENVIGADO | F103: 6000000 | G103: DIRECTO | H103: NO | I103: SI | J103: 1 | K103: RONALD
B104: CASA | C104: CASA EL POBLADO MANILA | E104: POBLADO | F104: 8000000 | G104: DIRECTO | H104: SI | I104: SI | J104: 1 | K104: MELBI
B105: APTO | C105: CIUDADELA SAN PABLO 604 | E105: ENVIGADO | F105: 1300000 | G105: EDWIN | H105: NO | I105: SI | J105: 1 | K105: PORTADA
B106: APTO | C106: CUMBRES DEL BOSQUE 201 | E106: ENVIGADO | F106: 1500000 | G106: OQUENDO | H106: NO | I106: SI | J106: 1 | K106: RONALD
B107: APTO | C107: ENTREPARQUES 808 | E107: ENVIGADO | F107: 2350000 | G107: ZAPATA | H107: SI | I107: SI | J107: 1 | K107: PORTADA
B108: APTO | C108: FIJI 1101 | E108: ENVIGADO | F108: 3000000 | G108: PALACIO | H108: NO | I108: SI | J108: 1 | K108: RONALD
B109: APTO | C109: FIJI 901 | E109: ENVIGADO | F109: 3200000 | G109: FRANKLIN | H109: NO | I109: SI | J109: 1 | K109: RONALD
... B117: APTO | C117: PUERTO LUNA 1302 | E117: ENVIGADO | F117: 1350000 | G117: PORTERO | H117: NO | I117: SI | J117: 1 | K117: MELBI
B118: APTO | C118: ESSENCE 1103 | E118: ENVIGADO | F118: 645000000 | G118: DIRECTO | H118: NO | K118: VENTAS
B119: APTO | C119: MONTEPIETRA 1422 | E119: ENVIGADO | F119: 380000000 | G119: DIRECTO | H119: NO | K119: VENTAS
B120: APTO | C120: PALMERAS 1108 | E120: ENVIGADO | F120: 155000000 | G120: DIRECTO | H120: NO | K120: VENTAS
J121: =SUM(J98:J120) -> 20
A122: PORTADA ENERO 2019
A123: FECHA | B123: TIPO | C123: UNIDAD O DIRECCION | E123: SECTOR | F123: VALOR | G123: PORTERO O DIRECTO | H123: AVISOS | I123: FOTOS | J123: ·# | K123: EJECUTIVA
B124: APTO | C124: MONTEPINAR 705 | E124: ENVIGADO | F124: 1400000 | G124: DIRECTO | H124: NO | I124: SI | J124: 1 | K124: MELBI
B125: APTO | C125: BRUJAS CAMPESTRE 707 | E125: ENVIGADO | F125: 1800000 | G125: RECIBIMIENTO | H125: SI | I125: SI | J125: 1 | K125: PORTADA
B126: APTO | C126: EDIFICIO ALEJANDRIA 303 | E126: ENVIGADO | F126: 1600000 | G126: RECIBIMIENTO | H126: SI | I126: SI | J126: 1 | K126: PORTADA
B127: APTO | C127: ALTO BONITO CASA 174 | E127: ENVIGADO | F127: 3000000 | G127: RECIBIMIENTO | H127: SI | I127: SI | J127: 1 | K127: PORTADA
B128: APTO | C128: CORALES DE LA ABADIA 1908 | E128: ENVIGADO | F128: 1650000 | G128: RECIBIMIENTO | H128: SI | I128: SI | J128: 1 | K128: PORTADA
B129: APTO | C129: CASAS DEL CAMINO 110 | E129: ENVIGADO | F129: 4000000 | G129: RECIBIMIENTO | H129: SI | I129: SI | J129: 1 | K129: PORTADA
A140: INFORME DE CAPTACIONES 2019 SEDE ENVIGADO
A141: JUAN DIEGO HERRERA FEBRERO 2019
A143: FECHA | B143: TIPO | C143: UNIDAD O DIRECCION | E143: SECTOR | F143: VALOR | G143: PORTERO O DIRECTO | H143: AVISOS | I143: FOTOS | J143: ·# | K143: EJECUTIVA
A144: 43500 | B144: APTO | C144: BOSQUES DEL ESMERALDAL 152 | D144: ESMERALDAL | E144: ENVIGADO | F144: 3500000 | G144: MAURO | H144: NO | I144: SI | J144: 1 | K144: MELBI
A145: 43498 | B145: APTO | C145: NATIVO ARENA 1301 | D145: EL CHOCHO | E145: ENVIGADO | F145: 2400000 | G145: SERGIO | H145: NO | I145: SI | J145: 1 | K145: MELBI
A146: 43498 | B146: APTO | C146: BIOCITY GRAND 409 | D146: ESCOBERO | E146: ENVIGADO | F146: 2600000 | G146: JOHAN | H146: SI | I146: SI | J146: 1 | K146: RONALD
...

Sheet SEGUIMIENTO CLIENTES
A1: INFORME CLIENTES MES DE FEBRERO 2022
A3: JUAN PABLO VILLA | B3: CLIENTE Y QUIEN ASIGNA PORDE DONDE SALE EL CLIENTE | C3: JUAN DIEGO HERRERA | D3: CLIENTE Y QUIEN ASIGNA PORDE DONDE SALE EL CLIENTE | E3: MARLON RODRIGUEZ | F3: CLIENTE Y QUIEN ASIGNA PORDE DONDE SALE EL CLIENTE | G3: ALEJANDRO BEDOYA | H3: CLIENTE Y QUIEN ASIGNA PORDE DONDE SALE EL CLIENTE
A4: FECHA 2 DE AGOSTO DE 2021 | B4: Jorge Andres Angel Uribe - 3188884468 pregunto por casa en el esmeraldal a traves de ciencuadras B.S - El asesor sigue en seguimiento y me muestra que el cliente no define cita queda de comunicarse luego | C4: FECHA 2 DE AGOSTO DE 2021 | D4: Laura González 3003985210 - pregunto por inmueble en camino verde a traves de ciencuadras B.S indica el asesor que busca para noviembre | E4: FECHA 2 DE AGOSTO DE 2021 | F4: Nombre: luz Stella Alzate Email: luz.alzate59@gmail.com Celular: +57 3042539330 B.S | G4: FECHA 2DE AGOSTO DE 2021 | H4: consuelo bolivar p Email: fcbolivarp@gmail.com Celular: +57 3206996471 pregunta por camelot a traves de ciencuadras B.S
A5: FECHA 2 DE AGOSTO DE 2021 | B5: Hector 3006206953 pregunto por este inmueble que no esta disponible de fincaraiz | C5: FECHA 2 DE AGOSTO DE 2021 | D5: Apartamento en Arriendo - Envigado OASIS con número de referencia 6548588 en Fincaraíz.com.co y con Cod. Inmueble: 679-37917, 3227468449 en la ciudad de Manizales indica el asesor que busca para noviembre B.S | E5: FECHA 2 DE AGOSTO DE 2021 | F5: NANCY GIRALDO Email: nanchilin1228@hotmail.com Celular: +57 3213040496 pregunta por casa bosques del esmeraldal a traves de ciencuadras B.S Tambien pregunto por el otra casa de 4.000.000 | G5: FECHA 2 DE AGOSTO DE 2021 | H5: Nombre: derly castro Email: dlcastrogenetista@gmail.com Celular: +57 3204405689
A6: FECHA 2 DE AGOSTO DE 2021 | B6: MARGARITA 5817830 en Fincaraíz.com.co y con Cod. Inmueble: 679-32111,interesado en su inmueble 3156482753 Pregunto por un inmueble en zuñiga que no esta disponible | C6: FECHA 3 DE AGOSTO DE 2021 | D6: Apartaestudio en Arriendo 5843569 en Fincaraíz.com.co y con Cod. Inmueble: 679-32308, estos son los datos del cliente interesado: nombre Luisa Valentina 3127752488 LA CLIENTE PREGUNTO apto de 1.850.000 B.S | E6: FECHA 2 DE AGOSTO DE 2021 | F6: Ana Maria Picón Cabarcas Telefono : 3015034646 Correo : ana_picon20@hotmail.com pregunta por kobalto que no esta disponible B.S | G6: FECHA 2 DE AGOSTO DE 2021 | H6: Liliana Patricia Galeano Guerra Email: lipa2976@gmail.com Celular: +57 3105290272 ESTA CLEINTE YA LA VENIA ATENDIENDO ALEJANDRO Y LE HABIA MOSTRADO OPCIONES
A7: FECHA 3 DE AGOSTO DE 2021 | B7: 321 7718906 LUZ DARY CLIENTE CITA CAMINO VERDE DE LOS NARANJOS | C7: FECHA 5 DE AGOSTO 2021 | D7: CLIENTE POR LLAMADA ANGIE 3207724185 se le muestra varias opciones pero no se decide aun se le esta haciendo seguimiento CP | E7: FECHA 4 DE AGOSTO DE 2021 | F7: 3148969156- GLADYS CLIENTE VLORE Y QUEBEC, SE LE ENVIAN LAS OPCIONES, PENDIENTE DE CITA. DC | G7: FECHA 3 DE AGOSTO DE 2021 | H7: 321 4425457 VICENTE CLIENTE QUE PREGUNTA POR ZU 41 21
A8: FECHA 6 DE AGOSTO DE 2021 | B8: - Envigado CUMBRES con número de referencia 6462607 en Fincaraíz.com.co y con Cod. Inmueble: 679-37164, Ana Bero Teléfono y ciudad LLame al cliente interesado en su inmueble +5521982312610 B.S | C8: FECHA 4 DE AGOSTO DEL 2021 | D8: CLIENTE POR CORREO ANGIE 3207724185 Se le muestran varias opciones esta en seguimiento aun no se decide CP | E8: FECHA | F8: CLIENTE ISABEL 3017877109 se le muestran opciones el dia de mañana se le hace seguimiento CP | G8: FECHA 5 DE AGOSTO DEL 2021 | H8: CLIENTE POR LLAMADA ROBERTO 3014133044 se le envian opciones y se le muestra hoy aptos CP
A9: FECHA 4 DE AGOSTO 2021 | B9: cliente por correo finca raiz se le muestran varias opciones hoy YOLANDA PARRA 3008085411 C.P | C9: FECHA 6 DE AGOSTO DEL 2021 | D9: CLIENTE ANA MARIA JUVINAO LLAMADA se le va mostrar una opcion hoy segumiento CP | E9: FECHA | F9: CLIENTE FINCA RAIZ PAOLA 3007473658 Se le hace seguimiento | G9: FECHA 10 DE AGOSTO DE 2021 | H9: 3012038666 - LAURA CLIENTE ALEJANDRO MOSTRAR IBERICA VITAL CLIENTE A.B
A10: FECHA 10 DE AGOSTO DE 2021 | B10: 313 6970965 ESTEBAN CLIENTE PREGITNA POR INMUEBLE DE FINCARAIZ COLORS QUE NO ESTA DISPONIBLE SE LE BRINDA INFORMACION AL ASESOR PARA SEGUIMIENTO. BS | C10: FECHA 9 DE AGOSTO DE 2021 | D10: Cliente ximena pregunta por codigo de fincaraiz 6462374 - 3115977376 | E10: FECHA 10 DE AGOSTO EDE 2021 | F10: través de fincaraíz.com.co, un nuevo cliente se ha interesado en su inmueble Apartamento en Arriendo - Envigado LOMA BENEDICTINOS con número de referencia 5695067 en Fincaraíz.com.co y con Cod. Inmueble: 679-31254, estos son los datos del cliente interesado: nombre Mauricio vasco Teléfono y ciudad LLame al cliente interesado en su inmueble 3006184028 en la ciudad de Envigado B.S | G10: FECHA 10 DE AGOSTO DE 2021 | H10: 3154624093 - LUZ ADRIANA CLIENTE D.C MOSTRAR ESSENCE Y BRUJA BONITA
A11: FECHA 11 DE AGOSTO DE 2021 | B11: CLIENTE PREGUNTA POR CASA DE SIENA +1 (786) 260-4900 se pasa la informacion al asesor para el seguimiento. B.S | C11: FECHA 9 DE AGOSTO DE 2021 | D11: Javier Cruz [Haz click sobre el correo o el teléfono para marcar o enviar mail] +57310309721 pregunto por zarzamora, pero no esta disponible se le asigna al asesor para sweguimiento B.S | E11: FECHA 23 DE AGOSTO DE 2021 | F11: LUZ MARINA MEJIA - 3016258396 - La cliente busca apartamento en un presupuesto de 1.400.000 | G11: FECHA 11 DE AGOSTO DE 2021 | H11: 3147975098 - DIEGO CLIENTE D.C BUSCA APARTAMENTO HASTA 2.800.00 2 ALCOBAS, PEDIENTE DEL SEGUIMIENTO DEL ASESOR
A12: FECHA 11 DE AGOSTO DE 2021 | B12: 3145291513 - IMBIRA JIMENEZ CLIENTE CON PAPELES APROBADO POR 2.700.000 CLIENTE D.C "necesita $2'700.000 2'500.000 en las brujas" | C12: FECHA 12 DE AGOSTO DE 2021 | D12: Nombre: Camila avila Email: camilaavila_9702@hotmail.com Celular: 3012333799 | E12: FECHA 23 DE AGOSTO DE 2021 | F12: EVELYN RINCON . 3223206434 - Le gusto sauces de la concha, aun no se agenda visita al apto | G12: FECHA 23 DE AGOSTO DE 2021 | H12: LUIS FERNANDO RESTREPO - 3146798546 - el cliente busca apartamento amplio en un presupesto de 2.300.000, el asesor le envía opciones
A13: FECHA | B13: Nombre: paula vasquez Email: vpaula_alejandra@hotmail.com Celular: +57 3005999373 cliente de Ciencuadras B.S | C13: FECHA 13 DE AGOSTO DE 2021 | D13: ANDREA MONTOYA - 3192540331 MOSTRAR LA CUENCA, CLIENTE D.C | E13: FECHA 24 DE AGOSTO DE 2021 | F13: HUMAR - 3057538309 - el cliente tiene un presupuesto de 1.500.000 busca apartamento de 3 alcobas | G13: FECHA 23 DE AGOSTO DE 2021 | H13: GIRBERTO - 3127797137 - al señor le gusto tramontana, aun no se agenda la cita, el asesor le envía las opciones disponibles
A14: FECHA 23 DE AGOSTO DE 2021 | B14: Jesica - 3207148868 La cliente pregunto por Kobalto, tiene un presupuesto de 1.600.000, el asesor aun no ha agendado cita. 27/08/2021 Se le enviaron opciones y no respondío, reviso el chat y no informó para programar cita | C14: FECHA 18 DE AGOSTO DE 2021 | D14: A través de fincaraíz.com.co, un nuevo cliente se ha interesado en su inmueble Apartamento en Arriendo - Envigado EL PORTAL con número de referencia 6509996 en Fincaraíz.com.co y con Cod. Inmueble: 679-29569, estos son los datos del cliente interesado: nombre Karen Teléfono y ciudad LLame al cliente interesado en su inmueble 3016516503 en la ciudad de Medellin | E14: FECHA 24 DE AGOSTO DE 2021 | F14: RAUL BARRIOS - 3106181525 - El señor busca apartamento de dos alcobas, en el sector de la forntera | G14: FECHA 23 DE AGOSTO DE 2021 | H14: LAURA ALZATE - 3136249399 - La cliente buasca un apartamento de 3 alcobas con un presupuesto de 3 millones, el asesor le envía opciones.
... A16: FECHA 23 DE AGOSTO DE 2021 | B16: GUSTAVO RENDON - 3104443584 - Se agenda cita para el miercoles a las 12 en el Porton Del Dorado, Le gusto el apartamento, lo quiere volver a ver el dia sabado 28 de agosto. | C16: FECHA 18 DE AGOSTO DE 2021 | D16: inmueble de 1.650.000 pero no esta disponible William Pabon +573116055941 | E16: FECHA 24 DE AGOSTO DE 2021 | F16: 3013784768 alexander se le hace seguimiento busca hasta 1.500 | G16: FECHA 26 DE AGOSTO DEL 2021 | H16: laura 301 3198532 quiere apto de 3 alcobas le gusta oclock se le hace seguimiento
A17: FECHA 23 DE AGOSTO DE 2021 | B17: LINA MOLINA - 3183890875 - la cliente es una reubicación, esta pendiente a entregar un apartamento que tiene con nosotros, 27/08/2021 se le enviara la opcion de Milan, ya que busca apartamento en parte baja, busca una unidad más nueva, el presupuesto es de 1.600.000 | C17: FECHA 18 DE AGOSTO DE 2021 | D17: Apartamento en Arriendo - Envigado LOMA DE LAS BRUJAS con número de referencia 6513438 en Fincaraíz.com.co y con Cod. Inmueble: 679-37576, estos son los datos del cliente interesado: nombre Diana Jiménez Teléfono y ciudad LLame al cliente interesado en su inmueble +573006629228 en la ciudad de Medellín | E17: FECHA | G17: FECHA 6 DE SEPTIEMBRE | H17: 313 6216006 maria gomez CLIENTE INTERNA busca casa hasta 4 millones se le hace seguimiento CP
A18: FECHA 23 DE AGOSTO DE 2021 | B18: MARGARITA ARIAS - 3127889553 - La cliente busca apartamnto amplio, en un presupuesto de 4.500.000. 27/08/2021 la señora busca apartamento en Poblado, se le paso el dato a un compañero de la sede. | C18: FECHA 23 DE AGOSTO DE 2021 | D18: KEREN - 3046361235 - La cliente agendo una cita para ver Manzanares, estamos pendientes de enviarle mas opciones. | E18: FECHA | G18: FECHA
A19: FECHA 24 DE AGOSTO DE 2021 | B19: JUAN DIEGO RAMIREZ - 3212416874 - Se le asigna cita para el 25, en la tarde el cliente confirma que no puede acomodar el horario con el horario en que lo muestra la propietaria. 20/08/2021 pendiente de cita el sabado 28 en bruja bonita. | C19: FECHA 23 DE AGOSTO DE 2021 | D19: LUIS ESTEBAN - 3183587999 - busca apartamento de 70 mts, de tres alcobas en 1.500.000 se le envían opciones. | E19: FECHA | G19: FECHA
A20: FECHA 24 DE AGOSTO DE 2021 | B20: YULIETH VIEIRA - 3505997398 - La cliente busca apartamento amplio en un presupuesto de 3.700.000, el asesor le brinda la información. 27/082021 se le envío todo lo que había disponible, no le gusto ninguna. | C20: FECHA 23 DE AGOSTO DE 2021 | D20: VALLERY - 3187122168 - busca apartamento de tres alcobas en un presupuesto de 1.700 el asesor se encarga de enviarle las opciones. | E20: FECHA | G20: FECHA
A21: FECHA 24 DE AGOSTO DE 2021 | B21: NATASCHA 3006742424 VA TOMAR EL APTO DE ZEBRANO SE LE MOSTRO AYER CP | C21: FECHA 24 DE AGOSTO DE 2021 | D21: ANA - 3046534146 - Busca opciones en el sector de la cuenca o cumbres, el asesor le envía opciones " le mostré manzanares 718 pero q no le sirven de ese metraje por q tiene sala muy grande le ofrecí Zurich y q ya lo había visto, tiene maximo 2.000.000" | E21: FECHA | G21: FECHA
A22: FECHA 10 DE AGOSTO DE 2021 | B22: OLGA 319 3771281 se le muestra en el sector de la cuenca se le hace seguimineto | C22: FECHA 24 DE AGOSTO DE 2021 | D22: DUNELLA MAYA - 3147077247 - busca apartamento de tres alcobas con 3 baños - 26/08/2021 la cliente quiero si o si en Ceylan 34 en poblado. | E22: FECHA | G22: FECHA
A23: FECHA | C23: FECHA 24 DE AGOSTO DE 2021 | D23: ANDREA PEREZ - 3105103665 - Busca apartamento en el sector de la paz - 26/08/2021 ya le mostré la cuenca pero no le gusto la vista de manzanares por el ruido y le mandé Zurich. | E23: FECHA | G23: FECHA
A24: FECHA | C24: FECHA 23 DE AGOSTO DE 2021 | D24: GLORIA DURAN - 3044532188 - busca apartamento en cumbres. Se le envio refugio verde, pendiente de agendar visita. | E24: FECHA | G24: FECHA
A25: FECHA | C25: FECHA 25 DE AGOSTO DE 2021 | D25: DIANA ROMERO - 3207642007 - Se agenda cita para el 26, mostrar el 1207 de Zurich "le gustó Zurich pero q quiere ver más opciones por allá ya le dije q papelería debe presentar" | E25: FECHA | G25: FECHA
A26: FECHA | C26: FECHA 25 DE AGOSTO DE 2021 | D26: carlos 317 8746139 se le muestra opciones esta en segumiento | E26: FECHA | G26: FECHA
A27: FECHA | C27: FECHA 26 DE AGOSTO DE 2021 | D27: Juan Felipe Velasquez - 301 2011090 - el cliente pregunto por Tramontana, el asesor le envia mas opciones - " estoy mirando q ofrecer tiene varios pedidos pero q no tiene afán q puede esperar hasta 4 meses pero ya le estoy buscando tiene máximo 1800 cerca a la frontera" | E27: FECHA
C28: FECHA 15 DE AGOSTO DEL 2021 | D28: andrea escobar 3136145850 cliente se le envian varias opciones pero no se sube de presupuesto CP | E28: FECHA
C29: FECHA 20 DE AGOSTO DEL 2021 | D29: ANA MARIA 3188218156 se le muestran opciones pero no concreto aun se le hace seguimiento porque no se a ubicado CP
C30: FECHA 10 DE AGOSTO DEL 2021 | D30: ANGIE 3207724185 cliente pendiente se le han mostrado opcones sigue en seguimiento CP
C31: FECHA 19 DE AGOSTO DEL 2021 | D31: DIANA 300 2546460 se le envian opciones pendiente de que indique ue quiere ver se lehace seguimiento CP
A33: INFORME CLIENTES MES DE SEPTIEMBRE 2021
A35: JUAN PABLO VILLA | B35: CLIENTE Y QUIEN ASIGNA PORDE DONDE SALE EL CLIENTE | C35: JUAN DIEGO HERRERA | D35: CLIENTE Y QUIEN ASIGNA PORDE DONDE SALE EL CLIENTE | E35: MARLON RODRIGUEZ | F35: CLIENTE Y QUIEN ASIGNA PORDE DONDE SALE EL CLIENTE | G35: ALEJANDRO BEDOYA | H35: CLIENTE Y QUIEN ASIGNA PORDE DONDE SALE EL CLIENTE
A36: 27 DE AGOSTO DEL 2021 | B36: NATASCHA 3006742424 CLIENTE SE LE OFRECE ZEBRANO Y LO VA TOMAR | C36: 30 DE AGOSTO DEL 2O21 | D36: ANA MARIA NUMERO EXTRANJERO SE LE HACE SEGUIMIENTO CLIENTE ASIGNO INTERNA | E36: 29 DE AGOSTO DEL 2021 | F36: LUZ 3127907139 CLIENTE hasta 1.800 se le ofrece una opcion pero no le gusta se le hace seguimiento cliente ASESOR INTERNO | G36: FECHA:30 AGOSTO | H36: CLIENTE POR CHAT SEÑORA JANET, PREGUNTO POR APTO EN QUEBEC 3002010948 - B.S
A37: FECHA: 30 AGOSTO | B37: JUAN DIEGO 3118695628 CLIENTE ASESOR, se programa para mostrar foretti 1402 y 1402, cancela la cita, pendiente volver a programar, X | C37: 31 DE AGOSTO DEL 2021 | D37: yolanda 3113415063 ella busca 2 a 3 alcobas hasta 2.500 se le hace seguimiento cliente ASESOR INTERNO CP | E37: FECHA: 30 AGOSTO | F37: DIANA 3054641532 CLIENTE LLEGO A LA OFICINA, se le muestra sonata 506, sao bento 312, faro del esmeraldal 712, trento 308, CLIENTE PASA DOCUMENTOS PARA SONATA SI | G37: FECHA:30 AGOSTO | H37: SEBASTIAN 319 7285493, CLIENTE ASESOR, se le va a mostrar Cubik APROBADO PARA ARRIENDO FECHA INICIO 24/09/21 X
A38: FECHA: 31 AGOSTO | B38: LINA JIMENEZ 3174009696 CLIENTE INTERNA, se le ofrece epic 502, sonata 506, santorini 704, 4 SEP le va a mostrar epic, klaus y sao bento, AUN NO DEFINE, SE PASA DOCUMENTOS POR TIERRA GRATA ESMERALDAL 912 SI | C38: FECHA: 2 DE SEPTIEMBRE | D38: LAURA 3134770606 CLIENTE ASESOR, mostrar Verdum X | E38: FECHA: 30 AGOSTO | F38: JULIANA RESTREPO 3234815169, CLIENTE ASESOR se le muestra faro del esmeraldal X | G38: FECHA: 30 AGOSTO | H38: JUAN PABLO JIMENEZ 3206998148 CLIENTE ASESOR, se le va a mostrar nativo arena 1616 PASA DOCUMENTOS PARA RADICAR 01/09/21. DOCUMENTOS APROBADOS SE ENTREGA A INQUILINA 07 SEPTIEMBRE SI
A39: FECHA: 31 AGOSTO | B39: ALEXANDRA GARCIA 3017817099, CLIENTE ASESOR, se le va a mostrar zurich 1207, cancela la cita pendiente volver a confirmar, SE PROGRAMA PARA EL 2 SEP MOSTRAR CASTELLI Y ZURICH, PASA DOCUMENTOS PARA RADICAR 6 SEP, DOCUMENTOS APLZADOS SI | C39: FECHA 3 DE SEPTIEMBRE DEL 2021 | D39: FRANCISCO 301 4975728 CLIENTE INTERNA se le informa de dos opciones se le hace seguimiento | E39: FECHA: 31 AGOSTO DEL 2021 | F39: CAMILO 3146547302 ASESOR INTERNA se le hace seguimiento pendiente de enviar oociones | G39: FECHA : 30 AGOSTO 2021 | H39: yanet 3002010948 busca apto hasta 3.200 se le hace segumiento cliente ASESOR INTERNA CP
A40: FECHA: 31 AGOSTO | B40: CAMILA 3233828709 cliente ASESOR INTERNA se le hace seguimiento busca de 3 alcobas | C40: 3 DE SEPTIEMBRE DEL 2021 | D40: ASRTID 301 5061758 CLIENTE INTERNA se le ofrece trentto tiene cita mañana 10 am CP | E40: FECHA: 31 AGOSTO | F40: GLADYS 316832599 CLIENTE ASESOR, mostrar casa cumbres, cliente se ubico con otra inmobiliaria X | G40: FECHA: 31 AGOSTO | H40: JOSHUA 3012147726 CLIENTE INTERNA, se le va a mostrar quebec 1209 Y Firenzze 805, 2 sep inquilino se acomodo con otra inmobiliaria X
A41: FECHA: 01 SEPTIEMBRE | B41: NATALIA 3206728110 CLIENTE ASESOR, mostrar manzanares de la cuenca 418 X | C41: FECHA: 6 DE SEPTIEMBRE | D41: CAROL BEJARANO 319 3450124, CLIENTE INTERNA, mostrar locales de los naranjos y santorino, no le gustaron X | E41: FECHA 3 SEPTIEMBRE | F41: 311 3700078 JUAN CLIENTE ASESOR INTERNA SE LE HACE SEGUIMIENTO CP | G41: FECHA: 31 AGOSTO | H41: JORGE ALIRIO 3216432351 CLIENTE ASESOR, mostrar edificio la matina, SE PIDE TRASLADO EL 02 SEPT APROBADOS SI
A42: FECHA: 02 SEPTIEMBRE | B42: GERMAN SANTACOLOMA 3118413834, CLIENTE INTERNA, mostrar venetto 303 y muratto X | C42: FECHA: 7 DE SEPTIEMBRE | D42: JOSE 316 8314374 CLIENTE INTERNA, mostrar trentto 308, PASA DOCUMENTOS POR CDT SI | E42: FECHA: 7 DE SEPTIEMBRE | F42: JHOANA 319 4745223 CLIENTE INTERNA, mostrar casa 146 de villa real, no se ha decidido X | G42: FECHA: 31 AGOSTO DEL 2021 | H42: VALENTINA SOTO 301 3198532 CLIENTE ASESORA INTERNA se le envia opciones y va ver nativo arena se le hace seguimiento CP
A43: FECHA 2 DE SEPTIEMBRE | B43: sandeep 311 3507305 le mando epic 502 y busca hasta 2 millones CLIENTE INTERNA | C43: FECHA 9 DE SEPTIEMBRE | D43: 3126341681 dario barrera SE LE HACE SEGUIMIENTO CLIENTE INTERNA CP | E43: FECHA 8 DE SEPTIEMBRE | F43: martha serrano 3014553364 CLIENTE INTERNA se le hace seguimiento busca apto hasta 3 millones CP | G43: FECHA 2 SEPTIEMBRE | H43: SANDRA 310 8410833 CLIENTE INTERNA se le muesta nogales pero pide rebaja se le hace seguimiento
A44: FECHA: 4 SEPTIEMBRE | B44: ANGELA 3148898222 CLIENTE ASESOR, le va a mostrar epic 502 y 507, y trentto APROBADOS PARA EPIC 507 X | C44: FECHA 20 SEPTIEMBRE | D44: MAURICIO CLIENTE INTERNA, MOSTRAR CUBIK 910. ESTA RADICANDO SI | E44: FECHA: 11 DE SEPTIEMBRE | F44: CRISTIAN 3008025559 CLIENTE ASESOR, mostrar casa 146 villa real, pasa propuesta por 2.100 X | G44: FECHA 6 DE SEPTIEMBRE DEL 2021 | H44: 313 6216006 maria gomez CLIENTE INTERNA busca casa hasta 4 millones se le hace seguimiento CP
A45: FECHA 8 SEPTIEMBRE | B45: CAROLINA | C45: FECHA: 20 SEPTIEMBRE | D45: MOSTRAR EPIC 507 CLIENTE ASESOR, ESTA RADICANDO SI | E45: FECHA 9 DE SEPTIEMBRE | F45: ricardo 3053565788 CLIENTE INTERNA se le hace seguimiento busca hasta 3 millones de 3 alcobas CP
A46: FECHA: 9 SEPTIEMBBRE | B46: ANDERSON 302 2266096 CLIENTE INTERNA, mostrar casa de los naranjos X | E46: FECHA: 16 DE SEPTIEMBRE | F46: MANUELA MONTOYA CLIENTE INTERNA 313 6499327 Mostrar altos del escobero 408 y villa real X
A47: FECHA: 9 SEPTIEMBBRE | B47: diana lopez 319 3888925 cliente INTERNA se le hace seguimiento CP | E47: FECHA: 15 DE SEPTIEMBRE | F47: MARIA ISABEL OLARTE 310 3762210 CLIENTE ASESOR, mostrar casa ginebra house X
A48: FECHA: 27 SEPTIEMBRE | B48: LUCIA PALLARES CLIENTE INTERNA, mostrar mississippi 1111 | E48: FECHA: 16 DE SEPTIEMBRE | F48: SUSANA 318 8272179 CLIENTE ASESOR, mostrar casa ginebra house, siena y quintas de la serrania. X
A49: FECHA: 27 SEPTIEMBRE | B49: WILSON CLIENTE INTERNA Mostrar ginebra house | E49: FECHA: 16 SEPTIEMBRE | F49: ALBERTO 312 2950941 CLIENTE INTERNA mostrar casa villa real, NO LE GUSTO LA UBICACION X
E50: FECHA: 17 DE SEPTIEMBRE | F50: JOHANA 316 5302542 CLIENTE ASESOR mostrar tierra grata 1012, se reprograma para el lunes RADICA PARA BIOCITY GRAND 1535 SI PARA OCTUBRE
E51: FECHA: 17 SEPTIEMBRE | F51: SIMON 3045923418 CLIENTE ASESOR Mostrar tierra grata 1012 SI
E52: FECHA: 20 SEPTIEMBRE | F52: ELETISE 313 4126385 CLIENTE INTERNA, mostrar Quebec 802 Se queda con Nativo 1403 SI
E53: FECHA: 25 SEPTIEMBRE | F53: ANDREA CLIENTE ASESOR mostrar casa villa real. RADICA DOCUMENTOS
A54: INFORME CLIENTES MES DE NOVIEMBRE 2021
A55: JUAN PABLO VILLA | B55: CLIENTE Y QUIEN ASIGNA PORDE DONDE SALE EL CLIENTE | C55: JUAN DIEGO HERRERA | D55: DE DONDE SALE EL CLIENTE | E55: MARLON RODRIGUEZ | F55: CLIENTE Y QUIEN ASIGNA PORDE DONDE SALE EL CLIENTE | G55: ALEJANDRO BEDOYA | H55: CLIENTE Y QUIEN ASIGNA PORDE DONDE SALE EL CLIENTE
A56: 44563 | B56: Claudia Maria Ramirez Cliente 3202111749 ER | C56: 28 DE ENERO | D56: 3246797295 NANCY MALDONADO CLIENTE CIENCUADRAS | E56: 44563 | F56: Juan Camilo Cliente 3004648653 ER | G56: 44563 | H56: Manuela Trujillo 3116422074 - D.C
A57: 44563 | B57: Dayana cliente La Cuenca 3146629319 - D.C | C57: 31 DE ENERO D | E57: 44563 | F57: Jose Aurelio Matamala 3106995407 - D.C | G57: 44563 | H57: Adriana Mejia 3103787000 - D.C
A58: 44563 | B58: Karina cliente La Cuenca 3128104077 - D.C | C58: 44563 | D58: Juliana Castellon 3183723991 - D.C | E58: 44563 | F58: XXX cliente La Abadia 3104390413 - D.C | G58: 44563 | H58: Maria Isabel Perez 3108425281 - D.C
A59: 44563 | B59: Monica Ines cliente La Cuenca 3177735229 - D.C | C59: 44563 | D59: Laura Cardona 3187305165 - D.C | E59: 44563 | F59: Wendy Salcedo 3106056257 - D.C | G59: 44563 | H59: Alejandro 3003729911 - D.C
A60: 44563 | B60: Juan Castaño 3013463385 - D.C | C60: 44653 | D60: Lina Uribe cliente ER 3158614901 | E60: 44563 | F60: Laura Natalia Portillo 3185250236 - D.C | G60: 44594 | H60: ANDRES ZAPATA 3104400627 CP
A61: 44563 | B61: Liliana Gaviria 3188340499 - D.C | C61: 44744 | D61: Paula Andrea Alvares cliente 3116197636 ER | E61: 44563 | F61: Juliana Gomez 3235831744 - M.R | G61: 44653 | H61: ABDUL +1 (832) 240-6962
A62: 44563 | B62: Mariana Gomez 3213121070 - D.C | C62: 44775 | D62: Veronica Cristancho cliente 3052220530 ER | E62: 44563 | F62: Luisa Fernanda Castro 3007941612 - D.C | G62: 44867 | H62: Sebastian 316 4195375 ER
A63: 44563 | B63: Natalia 3013782843 - D.C | E63: 44563 | F63: Leonardo Medina 3002460160 - D.C | G63: 15/02/2022 | H63: paula moncada 3128038957 CP
A64: 44563 | B64: Mauricio 3187759006 - D.C | E64: 44563 | F64: Andres Mendez 3025878374 - D.C
A65: 44563 | B65: Laura Cardona 3187305165 - D.C | E65: 44563 | F65: Gloria Mercedes Mora 3017224144 - D.C
A66: 44594 | B66: Jorge Orozco Cliente 311 7603631 ER | E66: 44563 | F66: Daniela 3503335173 - M.R
A67: 44622 | B67: Jorge Cardona 3227633737 ER | E67: 44563 | F67: Eliana Giraldo 3174412603 - D.C
A68: 44775 | B68: Daniela Hincapie Barco 3043409035 ER | E68: 44594 | F68: SILVANA 3002093295 CP
A69: 44775 | B69: Paola Salazar Cliente 3024307350 ER | E69: 44594 | F69: Alejandra cliente 3014403345 ER
A70: 44836 | B70: Cristina Cliente 3007901879 ER | E70: 44594 | F70: Cesar Cliente 3017223531 ER
E71: 44744 | F71: Leonardo Cliente 3045717055 ER
A72: 18 de abril se entrega cliente que ya fue agregado por darien, pero juan pablo ya lo venia atendiendo sra manuela | B72: Finca Raiz | C72: 18 de abril se entrega leinte de finca que pregunto por casa alcala captada por alexander del poblado señor Conrado vargas | D72: Finca Raiz | E72: 19 de abril de 2022 se entrega cliente de finca raiz pregunta por casa no disponible. 3006171886 | F72: Finca Raiz | I72: eliana cliente interesada en inmueble 2 alcobas 2.000.000 - 3007472144
A73: 20 de abril se envia solicitud que la señora daniela pregunta por una pto de prado alto ya venia siendo atendida por darien y estefania, pero quien inicialmente agendo la cita fue estefania. la sra daniela esposa del señor martin 3183852656 | B73: Finca Raiz | C73: 18 de abril se entrega cliente finca pregunta por nubenzza Esteban Escobar | D73: Finca Raiz | E73: 21 de abril se entrega cleinte a marlon ya se encontraba en sistema registrado hace un año, pero nunca se asigno una cita ana maria | F73: Finca Raiz
C74: 18 de abril se entrega cleinte a juan diego pregunta pro nubenzza y otro inmueble en la cuenca jorge luis | D74: Finca Raiz
C75: 19 de abril se entrega cleirnte de finca pregunto por zarzamora que no esta disponible para ofrecer otras opcioens, tambien pregunta por punta del parque de la zona Oscar ( este cleinte ya lo estaba atendiendo Juan diego desde el dia anterior, pero tambien el aesor Alejandro quien concreot cita con el señor en st laurent | D75: Finca Raiz

Sheet INFORME GENERAL 2021
A1: INFORME ENERO 2021 SEDE ENVIGADO | P1: 45
A3: ALEJANDRO BEDOYA
A4: CONSIGNACIONES | B4: CONTRATO | C4: PROPIETARIO | D4: INMUEBLE | E4: CANON | F4: % | G4: comision | H4: ASESOR 2 | I4: EJECUTIVA | J4: OBSERVACIONES | K4: CONTRATO | L4: INMUEBLE | M4: CANON | N4: %
B5: 10465 | C5: 0.1 | D5: IBERICA 701 $ 1.700.000 | E5: 1700000 | F5: 0.07 | G5: =E5*F5 -> 119000 | H5: PORTADA | I5: CAROLINA PARRA
B6: 10493 | C6: 0.1 | D6: EPIC 706 - 1.950.000 | E6: 1950000 | F6: 0.12 | G6: =E6*F6 -> 234000 | H6: ALEJANDRO BEDOYA | I6: CAROLINA PARRA
A7: 20+10 | B7: 10489 | C7: 0.1 | D7: NATIVO FLORA 616 2.400.000 | E7: 2400000 | F7: 0.12 | G7: =E7*F7 -> 288000 | H7: ALEJANDRO BEDOYA | I7: CAROLINA PARRA
B8: 10508 | C8: 0.1 | D8: LA RESERVA 701 2.800.000 | E8: 2800000 | F8: 0.07 | G8: =E8*F8 -> 196000 | H8: PORTADA | I8: BIVIANA SALAZAR
B9: 10576 | C9: 0.1 | D9: BIOCITY GRAND 804 - 1.700.000 | E9: 1700000 | F9: 0.07 | G9: =E9*F9 -> 119000 | H9: PORTADA | I9: CAROLINA PARRA
B10: FIRMAS | D10: LYON 2.200.000 | I10: LUISA MARIN
B11: DESISTIDO | D11: LUZ VIRGINIA PEREZ ALZATE 63278353 $ 1.500.000 | I11: DAHIANA HOYOS
B12: DESISTIDO | D12: SAN JUAN DE LAS ORQUIDEAS 704 $ 2550000 | I12: DAHIANA HOYOS
D13: BENEDICTINE GARDEN 1603 $ 4.800.000 | I13: DAHIANA HOYOS
B14: DESISTIDO | D14: REGATTA 708 - 2-300.000 | I14: CAROLINA PARRA
B15: DESISTIDO | D15: QUEBEC 1102 2.400.000 | I15: CAROLINA PARRA
B16: DESISTIDO | D16: CUBIK 910 SUBROGACION 2.300.000 | I16: BIVIANA SALAZAR | O16: =SUM(O9:O15) -> 0
D17: TOTAL | E17: =SUM(E5:E16) -> 10550000 | F17: TOTAL | G17: =SUM(G5:G16) -> 956000 | L17: TOTAL--------------------------------------> | O17: =O16+G17 -> 956000
A19: JUAN PABLO VILLA
A20: CONSIGNACIONES | B20: CONTRATO | C20: PROPIETARIO | D20: INMUEBLE | E20: CANON | F20: % | G20: comision | H20: ASESOR 2 | I20: EJECUTIVA | J20: OBSERVACIONES | K20: CONTRATO | L20: INMUEBLE | M20: CANON | N20: %
A21: 26+10 | B21: 10496 | C21: 0.1 | D21: PUERTO LUNA 510 | E21: 1450000 | F21: 0.12 | G21: =E21*F21 -> 174000 | H21: JUAN PABLO VILLA | I21: DAHIANA HOYOS
B22: 10515 | C22: 0.1 | D22: PUERTO LUNA 1502 | E22: 1500000 | F22: 0.12 | G22: =E22*F22 -> 180000 | H22: JUAN PABLO VILLA | I22: CAROLINA PARRA
B23: 10579 | C23: 0.1 | D23: MISSISSIPPI DE LA CUENCA 1310 | E23: 1400000 | F23: 0.12 | G23: =E23*F23 -> 168000 | H23: JUAN PABLO VILLA | I23: CAROLINA PARRA
B24: 10517 | C24: 0.1 | D24: GUADALCANAL 150 $ 2.200.000 | E24: 2200000 | F24: 0.12 | G24: =E24*F24 -> 264000 | H24: JUAN PABLO VILLA | I24: DAHIANA HOYOS
B25: 10542 | C25: 0.1 | D25: CASTELLI 1109 - 1750000 | E25: 1750000 | F25: 0.07 | G25: =E25*F25 -> 122500 | H25: SEBASTIAN MONTOYA | I25: DAHIANA HOYOS
B26: 10509 | C26: 0.08 | D26: NUEVA ORQUIDEA 504 | E26: 2200000 | F26: 0.1 | G26: =E26*F26 -> 220000 | H26: JUAN PABLO VILLA | I26: DAHIANA HOYOS
B27: 10490 | C27: 0.1 | D27: PUNTA DEL PARQUE 601 | E27: 3200000 | F27: 0.12 | G27: =E27*F27 -> 384000 | H27: JUAN PABLO VILLA | I27: DAHIANA HOYOS
B28: 10564 | C28: 0.1 | D28: ATALAYA DE SAN JORGE 1101 - 2.000.000 | E28: 2000000 | F28: 0.07 | G28: =E28*F28 -> 140000 | H28: PORTADA | I28: LUISA MARIN
B29: 10563 | C29: 0.1 | D29: ATALAYA DE SAN JORGE 1308 - 2.000.000 | E29: 2000000 | F29: 0.07 | G29: =E29*F29 -> 140000 | H29: PORTADA | I29: CAROLINA PARRA
B30: DESISTIDO | D30: ZURICH 406 $ 1550.000 EN BUSCA DE APTO | I30: DAHIANA HOYOS
B31: DESISTIDO | D31: CORALES DE LA ABADIA 501 - 1.800.000 | I31: DAHIANA HOYOS
B32: DESISTIDO | D32: BIOCITY 804 1.700.000 | I32: CAROLINA PARRA
B33: PENDIENTES | D33: RECINTOS DE LA ABADIA 1504 -EN ESTUDIO LIBERTADOR | I33: DAHIANA HOYOS
D34: MISSISSIPPI 1310 1.400.000 | I34: CAROLINA PARRA
B35: DESISTIDO | D35: CASA LAS BRUJAS 3.000.000 | I35: DAHIANA HOYOS
O38: =SUM(O21:O27) -> 0
D39: TOTAL | E39: =SUM(E21:E37) -> 17700000 | F39: TOTAL | G39: =SUM(G21:G38) -> 1792500 | L39: TOTAL--------------------------------------> | O39: =O38+G39 -> 1792500
A42: SEBASTIAN MONTOYA
A43: CONSIGNACIONES | B43: CONTRATO | C43: PROPIETARIO | D43: INMUEBLE | E43: CANON | F43: % | G43: comision | H43: ASESOR 2 | I43: EJECUTIVA | J43: OBSERVACIONES | K43: CONTRATO | L43: INMUEBLE | M43: CANON | N43: %
A44: 11+1 | L44: CASTELLI 1109 - 1750000 | M44: 1750000 | N44: 0.04 | O44: =M44*N44 -> 70000
B45: 10536 | D45: SANTA TERESITA 302 1.300.000 | E45: 1300000 | F45: 0.08 | G45: =E45*F45 -> 104000 | H45: SEBASTIAN MONTOYA | I45: CAROLINA PARRA
B46: 10532 | D46: BIOCITY GRAN 1142 - 2.200.000 | E46: 2200000 | F46: 0.04 | G46: =E46*F46 -> 88000 | H46: ALEJANDRO OCAMPO | I46: LUISA MARIN
D47: APTO PENDIENTE CDT - 1.600.000 | I47: CAROLINA PARRA
D48: CASTELLI 1109 - 1.750.000 | I48: LUISA MARIN
D49: PORTAL DEL CAMINO 601 $ 1.750.000 | I49: CAROLINA PARRA
D50: PORTAL DEL CAMINO 601 $ 1.750.000 | I50: DAHIANA HOYOS
D51: BALTICO 1211 - 2.800.000 | I51: LUISA MARIN | O51: =SUM(O44:O50) -> 70000
D52: TOTAL | E52: =SUM(E45:E51) -> 3500000 | F52: TOTAL | G52: =SUM(G45:G51) -> 192000 | L52: TOTAL--------------------------------------> | O52: =O51+G52 -> 262000
A54: PORTADA
A55: CONSIGNACIONES | B55: CONTRATO | C55: PROPIETARIO | D55: INMUEBLE | E55: CANON | F55: % | G55: comision | H55: ASESOR 2 | I55: EJECUTIVA | J55: OBSERVACIONES | K55: CONTRATO | L55: INMUEBLE | M55: CANON | N55: %
O63: =SUM(O56:O62) -> 0
D64: TOTAL | E64: =SUM(E56:E63) -> 0 | F64: TOTAL | G64: =SUM(G56:G63) -> 0 | L64: TOTAL--------------------------------------> | O64: =O63+G64 -> 0
A66: TOTAL FIRMADO | D66: =E52+E39+E17 -> 31750000
A67: TOTAL EN FIRMAS
A68: TOTAL EN ESTUDIO
A71: INFORME ASESORA INTERNA ENERO 2021 CAROLINA PARRA
A73: # CONTRATO | B73: % PROPIETARIO | C73: UNIDAD | D73: OBSERVACION PORQUE CAMBIA EL % | E73: CANON | F73: % | G73: COMISION | H73: OBSERVACIONES | I73: ASESOR
A74: 10465 | B74: 0.1 | C74: IBERICA 701 1.700.000 | E74: 1700000 | F74: 0.02 | G74: =E74*F74 -> 34000 | H74: FACTURADO | I74: ALEJANDRO BEDOYA
A75: 10493 | B75: 0.1 | C75: BIOCITY EPIC 706 1.950.000 | E75: 1950000 | F75: 0.02 | G75: =E75*F75 -> 39000 | I75: ALEJANDRO BEDOYA
A76: 10489 | B76: 0.1 | C76: NATIVO FLORA 616 2.400.000 | E76: 2400000 | F76: 0.02 | G76: =E76*F76 -> 48000 | I76: ALEJANDRO BEDOYA
A77: 10536 | B77: 0.1 | C77: CARRERA 34 N° 38 SUR 50 AP 302 1.300.000 | E77: 1300000 | F77: 0.02 | G77: =E77*F77 -> 26000 | I77: SEBASTIAN MONTOYA
A78: 10515 | B78: 0.1 | C78: PUERTO LUNA 1502 1.500.000 | E78: 1500000 | F78: 0.02 | G78: =E78*F78 -> 30000 | I78: JUAN PABLO VILLA
A79: 10563 | B79: 0.1 | C79: ATALAYA DE SAN JORGE 1308 2.000.000 | E79: 2000000 | F79: 0.02 | G79: =E79*F79 -> 40000 | I79: JUAN PABLO VILLA
A80: 10579 | B80: 0.1 | C80: MISSISSIPPI 1310 1.400.000 | E80: 1400000 | F80: 0.02 | G80: =E80*F80 -> 28000 | I80: JUAN PABLO VILLA
A81: 10576 | B81: 0.1 | C81: BIOCITY 804 1.700.000 | E81: 1700000 | F81: 0.02 | G81: =E81*F81 -> 34000 | I81: ALEJANDRO BEDOYA
B82: DESISTIDO | C82: APTO PENDIENTE | D82: SOLICITUD POR CDT SE UBICO CON OTRA INMOBILIARIA | I82: SEBASTIAN MONTOYA
B83: DESISTIDO | C83: PORTAL DEL CAMINO 601 $ 1.750.000 | D83: DESISTIO | I83: SEBASTIAN MONTOYA
B84: DESISTIDO | C84: BIOCITY 804 1.700.000 | D84: DESISTIO PROBLEMA PERSONAL | I84: JUAN PABLO VILLA
E85: =SUM(E74:E84) -> 13950000 | G85: =SUM(G74:G84) -> 279000
A87: INFORME ASESORA INTERNA ENERO 2021 DAHIANA HOYOS
A89: # CONTRATO | B89: % PROPIETARIO | C89: UNIDAD | D89: OBSERVACION PORQUE CAMBIA EL % | E89: CANON | F89: % | G89: COMISION | H89: OBSERVACIONES | I89: ASESOR
A90: 10517 | B90: 0.1 | C90: GUADALCANAL 150 | E90: 2200000 | F90: 0.01 | G90: =E90*F90 -> 22000 | I90: JUAN PABLO VILLA
A91: 10490 | B91: 0.1 | C91: PUNTA DEL PARQUE 601 | E91: 3200000 | F91: 0.01 | G91: =E91*F91 -> 32000 | I91: ALEJANDRO BEDOYA
A92: 10496 | B92: 0.1 | C92: PUERTO LUNA 510 | E92: 1450000 | F92: 0.01 | G92: =E92*F92 -> 14500 | I92: JUAN PABLO VILLA
A93: 10509 | B93: 0.08 | C93: NUEVA ORQUIDEA 504 | E93: 2200000 | F93: 0.01 | G93: =E93*F93 -> 22000 | I93: JUAN PABLO VILLA
A94: 10542 | B94: 0.1 | C94: CASTELLI 1109 | E94: 1750000 | F94: 0.01 | G94: =E94*F94 -> 17500 | I94: JUAN PABLO VILLA
A95: DESISTIDO | C95: RECINTOS DE LA ABADIA 1504 $ 1.850.000
A96: DESISTIDO | C96: SAN JUAN DE LAS ORQUIDEAS 804 $ 2.550.000
A97: DESISTIDO | C97: BENEDICTINE GARDENS 1603 $ 4.800.000
A98: DESISTIDO | C98: ZURICH 406 $ 1550000
A99: DESISTIDO | C99: PORTAL DEL CAMINO 601 $ 1.750.000
A100: DESISTIDO | C100: BALTICO 1211 $ 2.800.000
A101: DESISTIDO | C101: CORALES DE LA ABADIA 501 $ 1.800.000
A102: DESISTIDO | C102: SOLICITUD DE ESTUDIO LUZ VIRGINIA PEREZ ALZATE 63278353 $ 1.500.000 | E102: =SUM(E90:E101) -> 10800000 | G102: =SUM(G90:G101) -> 108000
A103: DESISTIDO | C103: CASA VERDEDA EL SILENCIO $ 3.100.000
A105: INFORME ASESORA INTERNA ENERO 2021 BIVIANA SALAZAR
A107: 10508 | B107: 0.1 | C107: LA RESERVA 701 | E107: 2800000 | F107: 0.02 | G107: =E107*F107 -> 56000
A112: INFORME GENERAL ENERO 2021 BIVIANA SALAZAR
A114: 10465 | B114: 0.1 | C114: IBERICA 701 1.700.000 | E114: 1700000 | F114: 0.02 | G114: =E114*F114 -> 34000
A115: 10493 | B115: 0.1 | C115: EPIC 706 1.950.000 | E115: 1950000 | F115: 0.02 | G115: =E115*F115 -> 39000
A116: 10489 | B116: 0.1 | C116: NATIVO FLORA 616 2.400.000 | E116: 2400000 | F116: 0.02 | G116: =E116*F116 -> 48000
A117: 10536 | B117: 0.1 | C117: CARRERA 34 N° 38 SUR 50 AP 302 1.300.000 | E117: 1300000 | F117: 0.02 | G117: =E117*F117 -> 26000
A118: 10515 | B118: 0.1 | C118: PUERTO LUNA 1502 1.500.000 | E118: 1500000 | F118: 0.02 | G118: =E118*F118 -> 30000
A119: 10563 | B119: 0.1 | C119: ATALAYA DE SAN JORGE 1308 2.000.000 | E119: 2000000 | F119: 0.02 | G119: =E119*F119 -> 40000
A120: 10579 | B120: 0.1 | C120: MISSISSIPPI 1310 1.400.000 | E120: 1400000 | F120: 0.02 | G120: =E120*F120 -> 28000
A121: 10576 | B121: 0.1 | C121: BIOCITY 804 1.700.000 | E121: 1700000 | F121: 0.02 | G121: =E121*F121 -> 34000
A122: 10517 | B122: 0.1 | C122: GUADALCANAL 150 | E122: 2200000 | F122: 0.02 | G122: =E122*F122 -> 44000
A123: 10490 | B123: 0.1 | C123: PUNTA DEL PARQUE 601 | E123: 3200000 | F123: 0.02 | G123: =E123*F123 -> 64000
A124: 10496 | B124: 0.1 | C124: PUERTO LUNA 510 | E124: 1450000 | F124: 0.02 | G124: =E124*F124 -> 29000
A125: 10509 | B125: 0.08 | C125: NUEVA ORQUIDEA 504 | E125: 2200000 | F125: 0.01 | G125: =E125*F125 -> 22000
... A129: 10564 | B129: 0.1 | C129: ATALAYA DE SAN JORGE 1101 - 2.000.000 | E129: 2000000 | F129: 0.02 | G129: =E129*F129 -> 40000
E130: =SUM(E114:E129) -> 31750000 | G130: =SUM(G114:G129) -> 613000
...

Sheet LLAVES 
A1: INVENTARIO LLEVES SEDE
A2: NUMERO | B2: NOMBRE DE LA UNIDAD | C2: INMUEBLE | D2: OBSERVACIONES
A3: 1
A4: 2
A5: 3
A6: 4
A7: 5
A8: 6
A9: 7
A10: 8 | B10: LOCAL TRIANON 39 B 04
A11: 9
A12: 10
A13: 11
A14: 12 | B14: VILLANUEVA DE LA AYURA | C14: 1105
A15: 13
A16: 14
A17: 15
A18: 16 | B18: CORALES DE LA ABADIA | C18: 1105
A19: 17
A20: 18
A21: 19 | B21: PORTON DEL DORADO | C21: 103
A22: 20
A23: 21
A24: 22 | B24: PALMERAS | C24: 708
A25: 23
A26: 24
A27: 25 | B27: REGATTA AP 613
A28: 26 | B28: VERGEL SEÑIOR CLUB | C28: 336
A29: 27
A30: 28
A31: 29 | B31: LOCAL MESA 38 SUR 36 | C31: 401
A32: 30 | B32: LOCAL PORTAL DEL CERRO | C32: 161 | D32: 1350000
A33: 31 | B33: LOCAL SAN MARCOS 32 B 27
A34: 32 | B34: LOCAL ANDA LUCIA | D34: 1200000
A35: 33
A36: 34
A37: 35
A38: 36 | B38: MISSISSIPPI 1111
A39: 37 | B39: CASTELLI 1210 | C39: 1210 | D39: 1900000
A40: 38 | B40: BIOCITY GRAND | C40: 435 | D40: 2400000
A41: 39 | B41: ZUÑIGA REAL | C41: 505
A42: 40 | B42: QUEBEC | C42: 708 | D42: 3700000
A43: 41 | B43: C. EMPRESARIAL CIUDAD DEL RIO | C43: 733
A44: 42 | B44: MISSISSIPPI | C44: 414
A45: 43 | B45: GOSY | C45: 1117 | D45: 5500000
A46: 44
A47: 45
A48: 46
A49: 47
A50: 48
A51: 49
A52: 50
A53: 51
A54: 52
A55: 53
A56: 54
A57: 55
... A59: 57
A60: 58 | B60: LOCAL ALCALA 47 A 22
A61: 59
A62: 60
A63: 61 | B63: LOCAL MARCELIANO 43-25
A64: 62
A65: 63
A66: 64 | B66: EL VERGEL | C66: 401
A67: 65
A68: 66
A69: 67
A70: 68
A71: 69
A72: 70
A73: 71
A74: 72
A75: 73 | B75: LOCAL CENTRO 35 SUR 47
A76: 74
A77: 75
A78: 76
A79: 77
A80: 78
A81: 79
A82: 80
A83: 81
A84: 82 | B84: LOCAL COA
A85: 83
A86: 84 | B86: PANORAMA AUSTRAL
A87: 85
A88: 86
A89: 87
A90: 88
A91: 89
A92: 90
A93: 91
A94: 92
A95: 93
A96: 94
A97: 95
A98: 96
... A100: 98

Sheet PORTERIAS ENVIGADO
A2: SECTOR | B2: UNIDAD | C2: PORTERO | D2: NUMERO | E2: DIRECCION | F2: NUMERO DE ADMINISTRACION | G2: HORARIO DE TRATEOS Y DEPOSITOS
A3: ABADIA | B3: ABADIA DEL CAMPO | C3: EVER HIGUITA | D3: 3211126 | E3: Calle 25 Sur 41-35 | G3: Lunes a Viernes de 8 - 12 y 2-5 Sábado (pendiente) - Deposito$ 150.000
A4: FRONTERA ZÚÑIGA | B4: ACANTO | C4: JORGE LEON LOPEZ | D4: 3136419 - 3117976586 | E4: Carrera 41A#22 Sur 87 | G4: Lunes a viernes de 8 -12 2-5 100.000
A5: SEÑORIAL | B5: AGUA DULCE | C5: CARLOS OLIVEROS-ARLEY | D5: 5963927 - 3122624757 | E5: Calle 46D Sur 42D-80 | G5: Lunes a Viernes de 8:30 a 5:00 pm Sábado 8:30 a 2:00 - Deposito $150.000
A6: SEÑORIAL | B6: AIRE DEL BOSQUE | C6: ALBERTO GIRALDO | D6: 3348418 | E6: CALLE 48 C SUR 42A-80 | G6: Lunes a Viernes de 8:00 a 5:00 pm Sábado 9:00 a 5:00 - No tiene deposito
A7: LA COLA DEL ZORRO | B7: ALCARAVAN | C7: HUMBERTO NAVARRO | D7: 3116121 | E7: Carrera 25A#10-75
B8: ALMENDROS DE ZUÑIGA | C8: RUBEN TUBERQUIA | D8: 5781764 | E8: CALLE 20 SUR 45 - 107
A9: SEÑORIAL | B9: ALTOS DE LOS ALMENDROS | C9: ANDRES | D9: 3504731400 - 2092936 | G9: LUNES A VIERNES DE 8 AM - 5 PM SABADO DE 8 AM - 1 PM NO DEPOSITO
A10: LAS FLORES | B10: ALTOS DE MAYORCA | D10: 5962197 | E10: CALLE 52 SUR 43 A - 57
A11: SEBASTIANA | B11: ALTOS DEL CLARAVAL | C11: CESAR GALLO | D11: 3360217 | E11: CALLE 36 SUR 25 - 153
A12: ESCOBERO | B12: ALTOS DEL ESCOBERO | D12: 3362471 | E12: Carrera 27A#37 Sur 07 | F12: 3362471 DIANA | G12: LUNES A VIERNES 8AM- 5PM Y SABADO DE 8AM - 2PM DEPOSITO $300.000
A13: INTERMEDIA | B13: AQUAMONTE | C13: CARLOS RODRIGUEZ | D13: 3344810 | E13: CALLE 36 AA SUR 26 A - 30 | G13: Lunes a Viernes de 8:00 a 4:00 pm Sábado 8:00 a 12:00 - No tiene deposito
A14: LA MINA | B14: COLORS | C14: JAVIER CASTILLO | D14: 5577709 | E14: CARRERA 24 DDNo. 41 SUR 190 | F14: BEATRIZ - 3176710977 | G14: Lunes a Viernes de 8:30 a 5:00pm sabados de 9:00 am a 3:00 pm no deposito
A15: LOMA DE LAS BRUJAS | B15: CUBIK | C15: CARLOS MARTINEZ | D15: 3144372301 | E15: CALLE 37 B SUR 27 D - 84 | F15: ADMON 4442420- 5788010 | G15: LUNES A VIERNES 8:00 A 4:00 PM SABADOS 8:00 A 12:00 DEPOSITO 200.000
B17: ALTO DEL ESMERALDAL | C17: MAURICIO | D17: 3662572 | E17: Calle 27 Sur 27-80
A18: LA FRONTERA | B18: B | E18: Carrera 15#9A-23
A19: LAS BRUJAS | B19: ATALAYA DE SAN JORGE | C19: luis garaby | D19: 5707547 | E19: CALLE 37 B SUR 27 B - 81 | G19: LUNES A VIERNES 8:30 5:00 SABADOS 8:00 A 2:00 PM DEPOSITO 150000
A20: EL ESMERALDAL | B20: AMARELLO IN | D20: 3566116 | E20: A | F20: ADMON 3135679 - 5804034 | G20: Lunes a Viernes 8am-5pm jornada continua y sabados 8:30am-1:30pm, deposito 200000
A21: ANTILLAS | B21: ANTILLAS 1 | C21: LUIS VALENCIA | D21: 3348156 | E21: CARRERA 36D 43 SUR-100
A22: ANTILLAS | B22: ANTILLAS 3 | C22: HAMILSON MONTOYA | E22: CARRERA 36 D 42 SUR - 50
A23: INTERMEDIA | B23: AQUAMONTE | C23: CARLOS RODRIGUEZ | D23: 3344810 | E23: CALLE 36AA SUR 26A 30
B24: ARBOLEDA DE CUMBRES | C24: LUIS CARLOS GOMEZ | D24: 3363891 | E24: CARRERA 27B 27D SUR 81
A25: CAMINO VERDE | B25: ARBOLEDA DE LAS BRUJAS | C25: JORGE URREGO-CARLOS | E25: CARRERA 29 A 39 SUR - 34 | F25: 3187641071 - magdalena guzman 5406350 opc 1 | G25: lunes a viernes de 8: 400 pm sabados 8:00 a 12:00
B26: ARBOLEDA DEL ESMERALDAL | C26: EDGAR MURIEL | D26: 5795374 | E26: CALLE 27 SUR 27 D - 79 | G26: lunes a viernes de 8: 400 pm sabados 8:00 a 12:00 DEPOSITO $ 100.000
B27: AREKA | C27: ELKIN TABORDA | D27: 5994433 - 3162062530 | E27: CALLE 27 SUR 27B-87 | G27: LUNES A VIERNES DE 8 AM - 4 PM Y SÁBADO DE 8 AM - 2 PM DEPOSITO $ 300.000
B28: AMARETTO
A29: ABADIA | B29: ARRECIFES DE LA ABADIA | C29: PORTERIA | D29: 3232205779 Y 5454161 | E29: Calle 27D Sur 28-50
B30: ROCIO DE LA MAÑANA | C30: RAUL ESCOBAR | D30: 3212575 | E30: Calle 27 Sur 28 | F30: L-V 8 AM - 3 PM SABADO 8 1 PM
B31: AUSTRAL | D31: 5776700 | E31: CALLE 36 SUR 27 A - 24
B32: BALCONES DE LA RAZA | C32: REINALDO | D32: 5978576 - 3106360409 | E32: CALLE 48C SUR 39A 165
B33: BALCONES DE TIERRA LINDA | C33: NICOLAS BEDOYAS | D33: 5776762 | E33: CARRERA 27A 36 D SUR 201
B34: BIOCITY EPIC | D34: 5577426 | E34: 3127814349 administracion | G34: LUNES A VIERNES DE 8AM A 5 PM - SABADOS DE 8AM A 2PM
D35: 4797922 | E35: Administración 3103891390 gloria bedoya | F35: 3019546 -5783987 KATERINE FACTURACIN ADMON | G35: lunes a viernes 8 am - 5 pm y sabado 10 am a 2 pm deposito 100.000 apartar la mudanza 1dia antes
B36: BALCONES DEL SUR | C36: JUAN SERNA | D36: 5978152 | E36: CALLE 49D SUR 40A 469
B37: BALTICO | C37: ANDRES RAMOS | D37: 5577514 | E37: Carrera 27#36 Sur 159 | G37: lunes viernes 8-12 y 2 - 6 sabados 8 - 2 deposito 250000
B38: BARICHARA | C38: FABER MUÑOZ | D38: 3669387 | E38: CARRERA 20 25 SUR 81 | G38: 0
A39: BENEDICTINOS | B39: BENEDICTINE PARK | C39: ODIVER RESTREPO | D39: 3005163773 | E39: Calle 24 Sur 38-40
C40: FERNEY HIGUITA | D40: 5796570 | E40: CALLE 24 SUR Nº 38 - 40 | F40: 4484173 | G40: Lunes a Viernes: 8 a 12 y 2 - 5, Sabado 8 - 12 DEPOSITO $300.000
B41: BONIVENTO CASAS | D41: 3342216 | E41: Cra. 38, calle 40 b sur 98, Envigado, Antioquia | G41: Lunes a Viernes: 8 a 5, Sabado 8 - 5 DEPOSITO
A42: EL CHOCHO | B42: BOSQUE ADENTRO | C42: ROBINSON NAVAS | D42: 3363400 - 3146868123 | E42: CARRERA 27 A 36 SUR - 150 | F42: 3148204043 | G42: Lunes a Viernes de 8:30 a 5:00 pm - Sábado de 9 :00 a 12 deposito 250.000
A43: BRUJAS | B43: CAMINO DE BRUJAS | D43: 2710426 - 3104378652 | E43: Calle 37B Sur 27A-71 | G43: lunes a viernes de 8 am - 5 pm sabado 8am - 3 pm deposito 1.500.000
A44: LAS COMETAS | B44: CAMINO DE LA COLINA | C44: JULIO VELEZ | D44: 3343517 | E44: Trasversal 35 Sur 27F-51
A45: CAMINO VERDE | B45: CAMINO VERDE DE LAS COMETAS | C45: FRANCISCO CORREA | D45: 3332820 | E45: Calle 39A Sur 28-06
A46: LOMA DE CUMBRES | B46: CUMBRES DEL BOSQUE | D46: 3875745 | E46: calle 27d sur 27 c - 15 | F46: 4443219 ADMON | G46: Lunes a Viernes: 8am-12pm 2PM a 5PM sabados 8AM A 2PM, deposito 100.000
B47: CAMINO DE CUMBRES | D47: 3005897 | E47: CALLE27DSUR#27B-101 ADMON | F47: MARTA MOSQUERA - 3053767915 | G47: Lunes a Viernes: 8am-5:00pm jornada continua sabados 9-1:00pm, deposito 160000
A48: CAMINO VERDE | B48: CAMINO VERDE DEL BOSQUE | C48: FABIO JIMENEZ | D48: 3344884 | E48: CALLE 39 SUR 27 - 55
A49: CAMINO VERDE | B49: CAMINO VERDE DEL PARQUE | C49: ALEJANDRA MARIA | D49: 3348081 | E49: CARRERA 27 D 39 SUR - 15
A50: LA FRONTERA | B50: CAMPO MORO | C50: JORGE MARIO | D50: 3135577 | E50: CRR 39 A-NO 18B SUR-154
A51: ZUÑIGA | B51: CAMELOT | C51: JOSE | D51: 3216148796 | F51: 4126085 | G51: Lunes a Viernes de 8 am a 5 pm y sábado de 8 am a 1 pm - deposito de $300.000
B52: CORTIJO DE SAN JORGE | C52: NELSON ARIAS | D52: 3012041 | E52: NUMERO NO ESTA EN USO
B53: CANTO DE LUNA | C53: WILSON MARQUEZ | D53: 3344067 | E53: CALLE 36 AA SUR 25 B - 150
B54: CANTO DE LUNA 1 | D54: 2528273 3146292598 | E54: FIJO NO ESTA EN USO
B55: CASAS DE AVIGNON | C55: ELIO SOLAR | D55: 3212597 | E55: CALLE 23 SUR 25 B 69
B56: CEREZAL | C56: ALEX ATENCIO | D56: 5781456 | E56: CAlle 23 sur 15 - 175
B57: CERROS DE GUADALCANAL | C57: EFRAIN SALAZAR | D57: 2760579 - 3117047204 | E57: CALLE 36 D 27 D - 29
B58: CIUDADELA DEL VALLE | C58: JARAMILLO | D58: 4187658 | E58: CARRERA 59 70 -349
A59: SAN LUCAS | B59: CIUDADELA REAL | C59: GILDARDO | D59: 3345580 | E59: CALLE 48C SUR 43A 50
B60: HACIENDA SAN JORGE | C60: JHONNY | D60: PORTERIA 3137604
B61: CIUDADELA SAN LUCAS | C61: JORGE MEDINA | D61: 2706485 | E61: CALLE 27A SUR 47 55
B62: HACIENDA SAN JOSE | C62: RODRIGO LOPEZ | D62: 3171531 | E62: CARRERA 20 22 SUR 30
B63: CORAZON DE ENVIGADO | C63: YEISON | D63: 3228225162 - 5985796 | E63: CALLE 52G SUR # 39E-37 | F63: 3043585207 - WILSON CASTAÑO PORTERIAS / 3166427718 ANA LUCIA HERNANDEZ 4444812 - 105 PARA SOLICITAR PAZ Y SALVO /PORTERIAS TORRES 1-2-3
B64: AVILA | C64: GUILLERMO PULGARIN | D64: 3213852 | E64: CARRERA 20 23 SUR - 140
B65: CASAS DE SAN FERNANDO | C65: ELDER ZAPATA | D65: 3173416 | E65: CARRERA 20 23 SUR - 25
B66: CEIBA DE LA CALLEJA | C66: CARLOS PETRO | D66: 2976905 -2976905 | E66: CALLE 26 SUR 23 A 11 | F66: ADMON 3218660 PROGRAMAR Y LLENAR FORMULARIOS UN 1 ANTES
B67: ARANDANO DE LA CALLEJA | C67: DIANA | D67: 5779408 | E67: CARRERA 23 A 26 C SUR 02
B68: OLIVO DE LA CALLEJA | C68: FERNANDO BERMUDEZ | D68: 5793912 | E68: CALLE 26 SUR 23 A 04
B69: CASA DE PATIO | C69: ALONSO TORO | D69: 4880287 | E69: CALLE 25 SUR 20 - 17
B70: BURDEOS CASAS CAMPESTRES | C70: DIEGO PARRA | D70: 5702656 | E70: CALLE 25 SUR 20 - 110
B71: CASAS DE BARILOCHE | C71: JEREMIAS REYES | D71: 5978422 | E71: NUMERO NO COINCIDE
B73: CIUDADELA SAN PABLO | C73: JOHAN PEREZ | D73: 3025467 3004369534 | E73: CALLE 40 AA SUR 36 - 30
B74: CIUDADELA SANTA MONICA | D74: 3344718 | E74: CALLE 28 SUR 43 A - 60
B75: COLINA DEL BOSQUE | C75: STALING | D75: 3345522 3147974675
A76: LA FRONTERA | B76: CONDOMINIO ACANTO | C76: JORGE LOPEZ | D76: 3136419 | E76: Carrera 41A#22 Sur 87
B77: CONDOMNINIO CUMBRES | C77: DARIO LEDESMA | D77: 2846295 3206577075 | E77: CARRERA 27 B 27 D - 225
B78: CONTEMPORA | C78: JUAN MUÑOZ | D78: 3212478 | E78: CALLE 18 B SUR 38 - 164 | F78: admonvelasquez@une.net.co
A79: ZUÑIGA | B79: CRISTALES DE ZUÑIGA | C79: JULIO CORREA | D79: 3342520 | G79: lunea a Viernes 8 a 4 Sábado 8 a 4, déposito $200.000// caminiones muy grandes no permiten ingresar.
A80: CAMINO VERDE | B80: CUBICK | C80: CARLOS MARTINEZ | D80: 5788010 | E80: Calle 37B Sur 27D-84 | F80: ADMON 4442420 | G80: Lunea a Viernes 8 a 4 Sábado 8 a 12, déposito $200.000
B81: EDIFICIO SAN GERMAN | D81: 3332628 | E81: CARRERA 44 23 SUR 30
A82: CAMINO VERDE | B82: EL EMBRUJO | C82: FABIO REYES | D82: 2701297 | E82: CARRERA 29 B SUR 39 - 02
B83: EL PORTAL DE LOS YARUMOS | C83: CARLOS GALLO | D83: 313 81 67 | E83: Calle 20 Sur 38-40
A84: LA SEBASTIANA | B84: ENTREPARQUES | C84: GILBERTO VALENCIA | D84: 3102017624 - 5794547 | E84: CALLE 36 SUR 27 - 10 | F84: JUAN ESTEBAN CORRALES 3157664622- JCORRALES@ABELARDOYEPES.COM | G84: Lunes a Viernes de 8am-12m y 2pm-5pm sabados 8am-2pm deposito 200000
A85: LOMA DE LA BRUJAS | B85: ENTREPINOS | C85: FAVER | D85: 5393776 | E85: 4798127- | F85: ADMINISTRACION 3145863964 - MELBA GARCIA | G85: lunes a viernes 8 am a 5 pm sabados de 8 a 2 deposito $ 245.000 se debe llamara a solicitar la MUDANZA 2 dias antes
A86: CAMINO VERDE | B86: ESCARLATA | C86: WILMAR VILLADA | D86: 3346696 3133097871 | E86: CARRERA 27 38 B SUR - 10
A87: ESMERALDAL | B87: FARO DEL ESMERALDAL | C87: ALEX PARRA | D87: 498 7115-5969634 | E87: Calle 27 Sur 27D-100-3217315958 | F87: ADMON GLORIA ZULUAGA FARODELESMERALDAL@GMAIL.COM | G87: Lunes a Sabado de 8:00 am-11:30 y 2:00pm-5:30pm - deposito 150000
A88: ESCOBERO | B88: FIORE | C88: FELIPE MEJIA | D88: 5701058
B89: FLORES DE LA COLINA 1 | C89: DIEGO USUGA | D89: 2701792 3207831476 | E89: CARRERA 32 B 40 F SUR - 25
B90: flores de mayorca | D90: 5986327 | E90: CALLE 49 D SUR 40 A - 508
B91: FUENTE CAMINO VERD | D91: 2763598 | E91: CALLE 39 B SUR 28 - 85
B92: GASCUÑA | C92: GUILLERMO ARREDONDO | D92: 3343291 | E92: Calle 36#27D-166 | G92: LUNES A SABDO 8 A 5 PM
A93: LA SEBASTIANA | B93: GINEBRA HOUSES | C93: ANDRES ACEVEDO | D93: 5793914 | E93: Carrera 24#27 Sur 191 ,
B94: GUADALCANAL | D94: 2760760 - 3007919532 Yina | E94: CALLE 36 D SUR 27 D - 39 | G94: lunes a sábado después de las 8am hasta antes de las 6pm- depósito de 150.000
B95: GUADUALES DE LA ABADIA | D95: 3347086 | E95: CARRERA 28 27 SUR - 042
B96: GUALI | D96: 2718083 | E96: CARRERA 27 G 35 SUR - 150 | G96: LUNES A VIERNES DE 8 A 4.30 SABADOS 8 A 1 DEPOSITO $ 140.0000
B97: ISLA FUERTE | D97: 3360045
B98: IRIS | D98: 4174014 - 3188278762 | E98: CALLE 45 39 B - 22 | G98: Lunes a Viernes de 9 a 4 y sábado de 9 a 1- deposito $100.000
B99: JARDINDES DE CLARAVAL | C99: LUIS GERARDO | D99: 3361749 | E99: CARRERA 26 D 36 A SUR - 80
A100: ZUÑIGA | B100: JARDINES DE LA MARIA | C100: RAFAEL ACOSTA | D100: 3340804 3117637277 - 4174014 | E100: CALLE 22 SUR 44 - 50 | G100: LUNES A VIERNES DE 8 AM 12 PM 2 PM A 5 PM - SABADO 8AM -2 PM DEPOSITO 2500.000
B101: a | E101: CALLE 22 SUR 44 - 80
B102: KLAUS | D102: 3669626 | E102: CARRERA 27 B SUR 27 D 60
B103: LA RESERVA | C103: EDWAR TORRES - ABAL | D103: 2066662 3147641083 | E103: CALLE 37 B SUR 27 B - 125 | G103: De lunes a viernes de 8:00 a 5:00 y Sábados de 8 a 3 pm // Deposito $215.000
...

Sheet PORTEROS SEDE ENVIGADO 
A1: PORTERIAS ENVIGADO
A2: NOMBRE | B2: UNIDAD | C2: N° CONTACTO | D2: ASESOR
A3: NELSON RAMIRO | B3: ST LAURENT | C3: 3128715910 | D3: JUAN PABLO VILLA | E3: 1
A4: YOHAN ESTEBAN PEREZ | B4: MISSISSIPPI DE LA CUENCA | C4: 3206234752 | D4: JUAN PABLO VILLA | E4: 2
A5: DIEGO ALEJANDRO ROJAS | B5: MAGDALENA DE LA CUENCA | C5: 3122469708 | D5: JUAN PABLO VILLA | E5: 3
A6: MILENA | B6: MAGDALENA DE LA CUENCA | C6: 3235842624 | D6: JUAN PABLO VILLA | E6: 4
A7: RAFAEL ANTONIO SANCHEZ | B7: PUERTO LUNA | C7: 3134976831 | D7: JUAN PABLO VILLA | E7: 5
A8: IVAN | B8: DOS VELAS | C8: 3192820006 | D8: JUAN PABLO VILLA | E8: 6
A9: FREIS ALBERTO MACEA | B9: O´CLOCK | C9: 3022997993 | D9: JUAN PABLO VILLA | E9: 7
A10: JORGE | B10: FORETTI | C10: 3015314482 | D10: JUAN PABLO VILLA | E10: 8
A11: JUAN ESTEBAN OCAMPO | B11: PUNTA DEL PARQUE | C11: 3206608677 | D11: JUAN PABLO VILLA | E11: 9
A12: GERLEN MENECES BEDOYA | B12: JACARANDAS | C12: 3107230505 | D12: JUAN PABLO VILLA | E12: 10
A13: GUILLERMO ORTEGA | B13: ATALAYA DE SAN JORGE | C13: 3005796328 | D13: JUAN PABLO VILLA | E13: 11
A14: DAVID ORTEGA | B14: JACARANDAS | C14: 3024648869 | D14: JUAN PABLO VILLA | E14: 12
... A111: JUAN DAVID | B111: CUBIK | C111: 3217095754 | D111: ALEJANDRO BEDOYA | E111: 109

Sheet INFORME DE RADICADOS
A1: CONTROL RADICADOS EL LIBERTADOR
A2: FECHA DE RADICADO | B2: HORA RADICADO | C2: RESPUESTA DE CONFIRMACION DE RECIBIDO | D2: HORA FECHA DE RESPUESTA | E2: RADICADO | F2: TIEMPO DE RESPUESTA FINAL
A3: 43587 | B3: 12:40 PM | C3: 13:17PM | D3: 2:44pm aplazado | E3: 6535448
A4: 43587 | B4: 15:14PM | C4: 15:20PM | D4: 17:22pm no asegurado | E4: 6537867
A5: 43587 | B5: 17:22PM | C5: 15:27PM | D5: LA PRIMERA RESPUESTA FUE EL DIA 03 DE MAYO 16:09 | E5: 6535486 | F5: EL 6 DE MAYO A LAS 8:35AM SE CONFIRMA COMO RECIBIDO EL ANEXO, RESULTADO FINALD PORQUE ESTABA PENDIENTE DE SEGUNDA HOJA DE LOS FORMULARIOS
A6: 43529 | B6: 16:54PM | C6: 11:40AM | D6: EL 6 MAYO A LAS 11:40AM ENVIARON EL RADICADO Y LA PRIMERA RESPUESTA RESPUESTA | E6: 6506028 | F6: APROBADO EL DIA 07 DE MAYO, PERO PORQUE SE ENCONTRABA EN VALIDACION TELEFONICA
A7: 43651 | B7: 3:31PM | C7: 0.64652778 | D7: 8 DE MAYO 9:56AM | E7: 6535549 | F7: 5 HORAS
A8: 43682 | B8: 2:48PM | C8: PENDIENTE | D8: PENDIENTE | E8: PENDIENTE | F8: PENDIENTE
A11: INFORME CIEN CUADRAS
A12: FECHA | B12: RADICADO | C12: CLIENTE | D12: N. TELEFONICO | E12: OBSERVACION

Sheet INFORME CLIENTES FINCA
A1: INFORME FINCA RAIZ - OLX- LONJANET 2019
A5: FECHA | B5: CODIGOS | C5: NOMBRE CLIENTE | D5: CONTACTO | E5: EJECUTIVO QUE ASIGNA | F5: ASESOR ASIGNADO | G5: OBSERVACIONES
A6: 43508 | B6: 67919072 | C6: lauchik07 | E6: MELBI CASTRILLON | F6: SEDE LAURELES | G6: EL CLIENTE SOLO BUSCA APTO POR CRISTO REY. POE ENDE SE REENVIS CORREO ALA SEDE ENCARGADA
A7: 43508 | B7: 67920860 | C7: JUAN JOSE | E7: MELBI CASTRILLON | F7: ANDRES MIRANDA | G7: SE LLAMA AL CIENTE SE LE OFRECE LAS OPCIONES DEL SECTOR Y SE LE ASIGNA EL ASESOR
A8: 43508 | C8: Ana Elisa Alvarez | E8: MELBI CASTRILLON | F8: SEDE POBLADO | G8: CLIENTE MUESTRA SU INTERES EN UN APTO DE POBALDO Y SE ENVIA CORREO A ALA SEDE ENCARGADA
A9: 43508 | B9: 67918202 | C9: JHOANA | E9: MELBI CASTRILLON | F9: JUAN DIEGO HERRERA | G9: SE LE INFORMA A LA CLIENTE QUE LA CASA YA NO ESTA DIPONIBLE PERO SE LE OFRECEN OTRAS OPCIONES
A10: 43508 | B10: 679-17222 | C10: JULIO CESAR ROJAS | E10: MELBI CASTRILLON | F10: ALEJANDRO BEDOYA | G10: CLIENTE SOLO QUIERE EN LA UNIDAD DE NATIVO FLORA SE LE ASIGAN CLIOENTE AL ASESOR Y SOLO SE PUEDE HABALAR POR EL WS
A11: 43143 | B11: 679-679-19005 | C11: DIANA PALACIO | E11: MELBI CASTRILLON | F11: JUAN PABLO VILLA | G11: LA CLIENTE TIENE PRESUPUESTO HASTA 3 MIILONES DE PESO SE LO ENVIAN LOS LINK DE LO QUE ESTA DISPONIBLE Y SE INFORMA DEL ASESORQUE SE COMUNICARA CON ELLA PARA AGENDAR CITA
A12: 43508 | B12: 4299367 | C12: adriana calle | E12: MELBI CASTRILLON | F12: ALEJANDRO BEDOYA | G12: LACLIENTE ENVIA UN CODIGO ELCUAL YA NO ESTA DISPONIBLE.SE LE OFECEN MAS OPCIONES Y SE LE ASIGA EL ASESOR -PERO NECESITA LA CASA PARA EL MES DE MARZO
A13: 43509 | B13: 4212814 | C13: Ruby | E13: PORTADA | F13: JUAN PABLO VILLA | G13: INMUEBLE NO SE ENCUENTRA DISPONIBLE
A14: 43509 | B14: 13660 | E14: PORTADA | G14: INMUEBLE NO SE ENCUENTRA DISPONIBLE
A15: 43509 | B15: 679-20727 | C15: Andres Quintero | E15: PORTADA | F15: ANDRES MIRANDA | G15: INMUEBLE NO SE ENCUENTRA DISPONIBLE
A16: 43510 | B16: 4222122 | C16: Yunbal | E16: PORTADA | G16: INMUEBLE NO SE ENCUENTRA DISPONIBLE - SE ESTAN ENVIADO OPCIONES AL WHATSSAP
A17: 43510 | B17: 4221800 | C17: Luis Fernando restrepo | E17: PORTADA | G17: BUSCA INMUEBLES HASTA 1.100.000 SE CONTACTA Y SE ENVIA INFORMACION AL WHATSSAP
A18: 43510 | B18: 67918190 | C18: cliente olx | E18: PORTADA | G18: BUSCA APARTAESTUDIO 750.000
A19: 43510 | B19: 4221897 | C19: Sirley | E19: PORTADA | G19: INMUEBLE NO DISPONIBLE BUSCA HASTA 1.350.000 CASA SE CONTACTA A WHATSSAP
A20: 43510 | B20: 679-19336 | C20: WILMAR | D20: 3003207037 | E20: PORTADA | G20: BUSCA LOCAL HASTA 1.200.000 SE CONTACTA POR WHATSSAP
A21: 43510 | B21: 679-18190 | C21: OLX | E21: PORTADA | G21: EL INMUEBLE NO SE ENCUENTRA DISPONIBLE, BUSCA HASTA 750.000
A22: 43510 | B22: 679-16388 | C22: OLX | D22: 3046579524 | E22: PORTADA | G22: INTERESADA EN EL APARTAESTUDIO DE ORQUIDEAS
A23: 43510 | B23: 1766330 | C23: VICTORIA CORREA | D23: 3105140211 | E23: PORTADA | G23: INTERESADA CASA DE CLARAVAL 112 SE ENVIA INFORMACION AL WHATSSAP
A24: 43510 | B24: 6796323 | C24: cliente olx | D24: 3204476625 | E24: PORTADA | G24: INTERESADA ARBOLEDA DEL ESMERALDAL - SE ENVIA INFORMACION POR WHATSSAP
A25: 43510 | B25: 4205542 | C25: Josais Montoya | E25: PORTADA | G25: INTERESADA EN APTO 1.100.000 SE ENVIA INFORMACION POR WHATSSAP
A26: 43514 | B26: 4345302 | C26: Zulima | D26: 3145764951 | E26: PORTADA | F26: JUAN DIEGO HERRERA | G26: INTERESADO EN CASA DE JARDINES SE ENVIA CONTACTO DEL CLIENTE AL ASESOR
A27: 43514 | B27: 679-17892/ | C27: Sara | D27: 317 7190727 | E27: PORTADA | F27: JUAN PABLO VILLA | G27: INTERESADA APTO de 1.200.000, SE ENVIAN OPCIONES AL WHATSSAP - JUAN PABLO YA A ESTADO CONVERSANDO CON LA SRA BUSCA HASTA 1.200.000
A28: 43514 | B28: 679-19210 | C28: Cliente olx | D28: 3168199959 | E28: PORTADA | F28: ALEJANDRO BEDOYA | G28: INTERESADA EN OFICINA EN TORRE MEDICA
A29: 43514 | B29: 679-2072 | C29: Guillermo | D29: 3155326670 | E29: PORTADA | G29: INTERESADO EN APTO EN LA FRONTERA
A30: 43514 | B30: 761117 | C30: Johana Gafaro | D30: 3005274792 | E30: PORTADA | G30: INTERESADA EN EL APARTAESTUDIO DE DEBORA ARANGO
A31: 43514 | B31: 679-21770 | C31: Dahiana Goes | D31: 3014378526 | E31: PORTADA | F31: JUAN DIEGO HERRERA | G31: INTERESADA EN CASA TRIANON
A32: 43514 | B32: 679-21535 | C32: Santiago Barrera | D32: 3016436598 | E32: PORTADA | F32: JUAN PABLO VILLA | G32: INTERESADA EN AMARETTO SE ENVIA INFORMACION AL ASESOR
A33: 43514 | B33: 67921802 | C33: Cliente olx | D33: 3136485834 | E33: PORTADA | F33: ANDRES MIRANDA | G33: CLIENTE INTERESADO EN PALMERAS SE ENVIA INFORMACION AL ASESOR
A34: 43515 | B34: 679-19475 | C34: Finca Raiz - Mauricio | D34: 3112477094 | E34: PORTADA | G34: CLIENTE FINCA INTERESADO EN APTO LAS ANTILLAS
A35: 43515 | B35: 679-21793 | C35: Judith Leon | D35: 3002056764 | E35: PORTADA | F35: DANIEL GUERRA | G35: CLIENTE INTERESADO EN APTO EN MISSISSIPPI 1501
A36: 43515 | B36: 679-20898 | C36: FINCA Raiz | D36: 3142429514 | E36: PORTADA | F36: JUAN DIEGO HERRERA | G36: CLIENTE INTERESADO EN CASA EL EMBRUJO
A37: 43515 | B37: 679-17892 | C37: castrillon | D37: 3147248245 | E37: PORTADA | F37: JUAN PABLO VILLA | G37: CLIENTE INTERESADO EN AMBAR
A38: 43515 | C38: Sirley quintero | D38: 3117600718 | E38: PORTADA | F38: JUAN PABLO VILLA | G38: CLIENTE INTERESADO EN LA CASA AZUL 201
A39: 43515 | B39: 67921802 | C39: cliente finca | D39: 3122811263 | E39: PORTADA | F39: ANDRES MIRANDA | G39: CLIENTE PREGUNTA POR APTO EN PALMERAS
A40: 43515 | B40: 4345302 | C40: cliente finca nataly | D40: 3147154306 | E40: CAMILA OCHOA | G40: CLIENTE PREGUNTA POR CASA EN JARDINES
A41: 43516 | B41: 679-20850 | C41: Cliente finca raiz alejandra | E41: CAMILA OCHOA | G41: INMUEBLE NO SE ENCUENTRA DISPONIBLE
A42: 43516 | B42: 679-5945 | C42: Santiago Barrera finca raiz | D42: 301 6436598 | E42: CAMILA OCHOA | G42: INMUEBLE NO SE ENCUENTRA DISPONIBLE
A43: 43516 | B43: 42846 | C43: Claudia Badel | D43: 3006649387 | E43: CAMILA OCHOA | F43: JUAN PABLO VILLA | G43: CLIENTE PREGUNTA POR APTOESTUDIO EN ANDALUCIA
A44: 43516 | B44: 679-16388 | C44: Cliente olx | D44: 3046579524 | E44: CAMILA OCHOA | G44: INMUEBLE NO DISPONIBLE BUSCA APTOESTUDIO MAX 850000
A45: 43516 | B45: 42846 | C45: luz maryory castrillon | D45: 3005872920 | E45: CAMILA OCHOA | F45: JUAN DIEGO HERRERA | G45: APTOESTUDIO 42845 ANDALUCIA
A46: 43516 | B46: 42873 | C46: Cliente finca raiz apt abril | D46: 3135078080 | E46: CAMILA OCHOA | G46: APTO TIERRA GRATA ESMERALDAL 1204
A47: 43517 | B47: 679-21872 | C47: Cliente olx | D47: 3017567523 | E47: CAMILA OCHOA | G47: CLIENTE PREGUNTA POR APTOESTUDIO ANDALUCIA
A48: 43517 | B48: 679-21784 | C48: Cliente finca raiz | D48: 312 2253373 | E48: CAMILA OCHOA | G48: CLIENTE INTERESADO POR CASA EN JARDINES
A49: 43517 | B49: 679-21802 | C49: cliente finca raiz | D49: 3045593014 | E49: CAMILA OCHOA | G49: CLIENTE INTERESADO PALMERAS 3 931
A50: 43517 | B50: 679-21260 | C50: cliente finca raiz | D50: 3163777953 | E50: CAMILA OCHOA | G50: CLIENTE INTERESADO EN LOCAL LOS NARANJOS
A51: 43517 | B51: 4221897 | C51: Cliente finca raiz | D51: 3122253373 | E51: CAMILA OCHOA | G51: INMUEBLE NO SE ENCUENTRA DISPONIBLE
A52: 43517 | B52: 679-20590 | C52: cliente finca raiz | D52: 3122253373 | E52: CAMILA OCHOA | G52: INMUEBLE NO SE ENCUENTRA DISPONIBLE
A53: 43517 | B53: 4299367 | C53: cliente finca | D53: 3162577274 | E53: CAMILA OCHOA | G53: INMUEBLE NO DISPONIBLE CASA LOMA ESCOBERO SE LE ESTAN ENVIANDO OPCCIONES AL WPP
A54: 43517 | B54: 679-21872 | C54: Cliente olx | E54: CAMILA OCHOA | G54: CLIENTE INTERESADO EN APTOESTUDIO DE ANDALUCIA
A55: 43517 | B55: 679-13710 | C55: Milena giraldo | D55: 322854476 | E55: CAMILA OCHOA | F55: DANIEL GUERRA | G55: CLIENTE INTERESADA EN CASA MANGA AZUL SE LE ASIGNA ASESOR
A56: 43518 | B56: 679-21872 | C56: cliente olx | D56: 3163909380 | E56: CAMILA OCHOA | G56: CLIENTE INTERESADO EN APTOESTUDIO DE ANDALUCIA
A57: 43518 | B57: 4345302 | C57: cliente finca raiz | D57: 3127968184 | E57: CAMILA OCHOA | G57: CLIENTE INTERESADA EN CASA JARDINES 301
A58: 43518 | B58: 679-19769 | C58: cliente olx | D58: 3013182018 | E58: CAMILA OCHOA | G58: INMUEBLE EN LA MAGNOLIA NO DISPONIBLE
A59: 43518 | B59: 4315148 | C59: Cliente finca raiz | D59: 3156276200 | E59: CAMILA OCHOA | G59: INTERESADO EN ORINOCO DE LA CUENCA 415
A60: 43518 | B60: 679-21266 | C60: Cliente finca raiz | D60: 3183638472 | E60: CAMILA OCHOA | G60: CLIENTE INTERESADO EN PIETRAROSA 702
A61: 43518 | B61: 679-21316 | C61: Cliente olx | D61: 3003237724 | E61: CAMILA OCHOA | G61: CLIENTE INTERESADO APTO CAMINO VERDE 41804
A62: 43518 | B62: 679-21872 | C62: Cliente olx | D62: 3117118884 | E62: CAMILA OCHOA | G62: CLIENTE INTERESADO APTOESTUDIO
A63: 43518 | B63: 679-21930 | C63: cliente olx mauricio | D63: 3112477094 | E63: CAMILA OCHOA | G63: CLIENTE INTERESADO EN MAGDALENA DE LA CUENCA 1204
A64: 43518 | B64: 679-21770 | C64: cliente olx | D64: 3106447380 | E64: CAMILA OCHOA | F64: no contesta | G64: INTERESADO CASA TRIANON
A65: 43521 | B65: 679-20590 | D65: se le respondio por correro | E65: CAMILA OCHOA | G65: CLIENTE INTERESADO EN CASA INDEPENDIENTE MANGA AZUL 301
A66: 43521 | B66: 679-7741 | C66: cliente finca | D66: 3113411874 | E66: CAMILA OCHOA | G66: INMUEBLE NO DISPONIBLE
A67: 43521 | B67: 1492633 | C67: cliente finca | D67: 3103987591 | E67: CAMILA OCHOA
A68: 43521 | B68: 679-20791 | C68: cliente finca | E68: CAMILA OCHOA | G68: INMUEBLE NO DISPONIBLE
A69: 43521 | B69: 679-20945 | C69: cliente finca | D69: 3115285797 | E69: CAMILA OCHOA | G69: INMUEBLE DISPONIBLE
A70: 43522 | B70: 679-21355 | C70: cliente olx | E70: CAMILA OCHOA | G70: SEDE LAURELES
A71: 43522 | B71: 4354472 | C71: cliente finca raiz | D71: 3194910969 | E71: CAMILA OCHOA | G71: MI MORADA 401 NO DISPONIBLE
A72: 43522 | B72: 679-20840 | C72: Cliente finca | D72: 3046175042 | E72: CAMILA OCHOA | G72: CASA ALCALA INMUEBLE NO DISPONIBLE
A73: 43522 | B73: 679-21872 | C73: cliente finca | D73: 3152200809 | E73: CAMILA OCHOA | G73: APTOESTUDIO ANDALUCIA SE LE HABLO AL WPP
A74: 43522 | B74: 679-20727 | C74: Cliente finca | D74: 3144630945 | E74: CAMILA OCHOA | G74: NO DISPONIBLE
A75: 43522 | B75: 679-21314 | C75: Ccliente olx | D75: 3209896416 | E75: CAMILA OCHOA | G75: REFUGIO DE VILLA VERDE 203
A76: 43522 | B76: 679-17908 | C76: cliente ol | E76: CAMILA OCHOA | G76: INMUEBLE NO DISPONIBLE
A77: 43522 | B77: 679-17444 | C77: Cliente olx | D77: 3042490628 | E77: CAMILA OCHOA | G77: LOCAL INDENPENDIENTE SAN MATEO
A78: 43523 | B78: 679-20235 | C78: cliente olx | D78: 3147766971 | E78: CAMILA OCHOA | G78: CLIENTE INTERESADO EN APTOESTUDIO ANDALUCIA
A79: 43523 | B79: 4380136 | C79: cliente finca raiz | D79: 3148624256 | E79: CAMILA OCHOA | G79: CLIENTE INTERESADO EN TRENTTO 1103
A80: 43523 | B80: 679-20590 | D80: 3204476625 | E80: CAMILA OCHOA | G80: CLIENTE INTERESADO EN CASA MANGA AZUL
A81: 43524 | B81: 679-16165 | C81: cliente finca raiz | D81: 3008981868 | E81: RONALD MENDEZ | F81: PENDIENTE DE ASIGNAR | G81: CLIENTE INTERESADO EN CORAZON DE ENVIGADO, SE LE INDICA QUE EL INMUEBLE NO SE ENCUENTRA DISPONIBLE Y SE LE OFRECEN MAS OPCIONES
A82: 43524 | B82: 679-20683 | C82: cliente finca raiz | D82: 3175050599 | E82: RONALD MENDEZ | F82: PENDIENTE DE ASIGNAR | G82: CLIENTE INTERESADO EN CASA LA MAGNOLIA, EL INMUEBLE NO SE ENCUENTRA DISPONIBLE SE LE OFRECEN MAS OPCIONES
A83: 43524 | B83: 67920577 | C83: CLIENTE OLX | D83: 3042490628 | E83: RONALD MENDEZ | F83: DANIEL | G83: SE LE INDICA QUE EL INMUEBLE ESTA DISPONIBLE, SE ASIGNA AL ASESOR DANIEL PERSONA QUE REALIZO LA CAPTACION
A84: 43524 | B84: 67921872 | C84: CLIENTE OLX | D84: =50762166687 -> 50762166687 | E84: RONALD MENDEZ | F84: PENDIENTE POR ASIGNAR | G84: SE DEJE MENSAJE EN EL WPP DEBIDO A QUE ES UN NUMERO INTERNACIONAL, PENDIENTE POR PROGRAMAR CITA Y ASIGNAR ASESOR
A85: 43525 | B85: 4212814 | C85: FINCA RAIZ | D85: Camila | E85: MELBI CASTRILLON | G85: SE SE ASIGNA AL ASESOR QUE LO VA ATENDER YA QUE EL ATO NO ESTA DISPONIBLE
A86: 43525 | C86: PROPERATI | D86: Juan E Cano R | E86: MELBI CASTRILLON
A87: 43529 | B87: 4355458 | C87: Catalina Aristizabal | D87: 3178091099 | E87: RONALD MENDEZ | G87: PREGUNTA POR EL APARTAESTUDIO DE 600.000
A88: 43529 | B88: 679-22166 | C88: Mary Nelly Beltran | D88: 3146744533 | E88: RONALD MENDEZ | F88: DANIEL GUERRA | G88: PREGUNTA POR SAN SEBASTIAN 410 - LE PASE EL CONTACTO A DANIEL
A89: 43529 | B89: 679-22116 | C89: Carolina | D89: 3012308465 | E89: RONALD MENDEZ | F89: JUAN DIEGO | G89: PREGUNTA POR ATALAYA DE SAN JORGE
A90: 43529 | B90: 679-21802 | C90: Cliente OLX | D90: 3504721892 | E90: RONALD MENDEZ | F90: ANDRES MIRANDA | G90: PREGUNTA POR PALMERAS
A91: 43529 | B91: 679-17908 | C91: Zulima | D91: 3145794951 | E91: RONALD MENDEZ | F91: ANDRES MIRANDA | G91: PREGUNTA POR EL APTO DE CIUDADELA DE SAN LUCAS -
A92: 43529 | B92: 679-21872 | C92: Cliente OLX | D92: 3012431733 | E92: RONALD MENDEZ | G92: PREGUNTA POR EL APARTAESTUDIO DE 600.000
A93: 43529 | B93: 679-21314 | C93: Cliente OLX | D93: 3117759077 | E93: RONALD MENDEZ | F93: DANIEL GUERRA | G93: PREGUNTA POR APTO DE REFUGIO DE VILLA VERDE QUE NO ESTA DISPONIBLE PASO INFORMACION PARA OFRECER OTRAS OPCIONES
A94: 43529 | B94: 4141809 | C94: Diana Benito | D94: 3175050599 | E94: RONALD MENDEZ | F94: JUAN PABLO VILLA | G94: CLIENTE INTERESADO EN SANTA MARIA DE LAS LOMAS NO ESTA DISPONIBLE
A95: 43529 | B95: 679-22041 | C95: Alejandro Cano | D95: 3127328981 | E95: RONALD MENDEZ | F95: ANDRES MIRANDA | G95: LLAMO PREGUNTANDO POR AMARETTO 1301 SE PASA INFORMACION ANDRES
A96: 43529 | B96: 4221897 | C96: Carolina Restrepo | D96: 3184020514 | E96: RONALD MENDDEZ | F96: JUAN DIEGO HERRERA | G96: PREGUNTA POR LA CASA SEGUNDO PISO 1.350.000 ALCALA PERO NO ESTA DISPONIBLE PENDIENTE, TAMBIEN PREGUNTA POR EL APTO DE NATURE LE ASIGNO ASESOR
A97: 43530 | B97: 679-21872 | C97: Ramon hernandez olx | D97: 312 7817878 | E97: CAMILA OCHOA | F97: DANIEL GUERRA | G97: PREGUNTA POR APTOESTUDIO ANDALUCIA - LE ASIGUE ASESOR
A98: 43530 | B98: 679-22161 | C98: cliente olx | D98: 3168213780 | E98: CAMILA OCHOA | G98: INTERESADO TIERRA GRATA CUMBRES APTO 1406 - SE LLAMO Y SE LE DEJO MENSAJE VIA WPP Y NO CONTESTO
A99: 43530 | B99: 679-21872 | C99: cliente olx | E99: CAMILA OCHOA | G99: SE LE DEJO CORREO
A100: 43530 | B100: 679-19046 | C100: cliente finca raiz | D100: 3112810747 | E100: CAMILA OCHOA | G100: INTERESADO EN APARTAMENTO OASIS 201 - SE LE ENVIO INFO AL WPP/ PENDIENTE POR ASIGNAR ASESOR
A101: 43531 | B101: 4390446 | C101: sandra finca raiz | D101: 3005907422 | E101: CAMILA OCHOA | G101: INTERESADA EN MAGDALENA DE LA CUENCA 507
A102: 43531 | B102: 4223105 | C102: cliente finca | D102: 3175050599 | E102: CAMILA OCHOA | G102: INTERESADO EN AIRES DEL BOSQUE APTO. 519/ NO SE ENCUENTRA DISPONIBLE SE LE DA MAS OPCIONES/ PENDIENTE POR ASIGNAR ASESOR
A103: 43535 | B103: 679-22158 | C103: natalia mejia | D103: 3127309107 | E103: CAMILA OCHOA | F103: ANDRES MIRANDA | G103: INTERESADA EN CANTA PIEDRA /
...

Sheet Sheet1
A1: INFORME DAHIANA HOYOS ABRIL
A3: 8154 | B3: 0.08 | C3: CASTELLI 907 | D3: 1300000 | E3: 0.005 | F3: =D3*E3 -> 6500
A4: 8156 | B4: 0.1 | C4: MAGDALENA1316 | D4: 1300000 | E4: 0.01 | F4: =D4*E4 -> 13000
A5: 8209 | B5: 0.1 | C5: NATIVO ARENA 1002 | D5: 2500000 | E5: 0.01 | F5: =D5*E5 -> 25000
A6: 8237 | B6: 0.1 | C6: POSITANO 602 | D6: 2600000 | E6: 0.01 | F6: =D6*E6 -> 26000
D7: =SUM(D3:D6) -> 7700000 | F7: =SUM(F3:F6) -> 70500
A9: INFORME DAHIANA HOYOS MAYO
A11: 8253 | B11: 0.1 | C11: PUERTO LUNA 1016 | D11: 2500000 | E11: 0.02 | F11: =D11*E11 -> 50000
A12: 8256 | B12: 0.08 | C12: TOSCANO 1705 | D12: 2200000 | E12: 0.01 | F12: =D12*E12 -> 22000
A13: 8264 | B13: 0.1 | C13: AMARETTO 1301-RUBICACION | D13: 1200000 | E13: 0.02 | F13: =D13*E13 -> 24000
A14: 8280 | B14: 0.1 | C14: BRUJA CAMPESTRE 1605 | D14: 1200000 | E14: 0.02 | F14: =D14*E14 -> 24000
A15: 8302 | B15: 0.1 | C15: PALMERAS 628-REUBICACION | D15: 2100000 | E15: 0.02 | F15: =D15*E15 -> 42000
A16: 8321 | B16: 0.1 | C16: ARBOLEDA DE LAS BRUJAS 706 | D16: 1600000 | E16: 0.02 | F16: =D16*E16 -> 32000
A17: 8336 | B17: 0.1 | C17: VIENTOS DE LA COLINA CASA 180 | D17: 2100000 | E17: 0.02 | F17: =D17*E17 -> 42000
A18: 8389 | B18: 0.1 | C18: BIOCITY 1107 | D18: 1500000 | E18: 0.02 | F18: =D18*E18 -> 30000
A19: 8390 | B19: 0.1 | C19: TRENTTO 1103 | D19: 2000000 | E19: 0.02 | F19: =D19*E19 -> 40000
D20: =SUM(D11:D19) -> 16400000 | F20: =SUM(F11:F19) -> 306000
A22: INFORME DAHIANA HOYOS JUNIO
A24: 8377 | B24: 0.1 | C24: BENEDICTINE PARK 1805 | D24: 2800000 | E24: 0.03 | F24: =D24*E24 -> 84000
A25: 8395 | B25: 0.1 | C25: ROMANZA DE LA ABADIA 304 | D25: 1800000 | E25: 0.03 | F25: =D25*E25 -> 54000
A26: 8413 | B26: 0.1 | C26: CANTO DE LUNA 122 $5.200.000 | D26: 5200000 | E26: 0.03 | F26: =D26*E26 -> 156000
A27: 8426 | B27: 0.1 | C27: MISSISIPI DE LA CUENCA 104 | D27: 1150000 | E27: 0.03 | F27: =D27*E27 -> 34500
A28: 8435 | B28: 0.1 | C28: MAGDALENA DE LA CUENCA 107 | D28: 1200000 | E28: 0.03 | F28: =D28*E28 -> 36000
A29: 8446 | B29: 0.1 | C29: REFUGIO VERDE 509 | D29: 1870000 | E29: 0.03 | F29: =D29*E29 -> 56100
A30: 8483 | B30: 0.1 | C30: MONTIEL 2205 $ | D30: 3900000 | E30: 0.03 | F30: =D30*E30 -> 117000
A31: 8471 | B31: 0.1 | C31: PRIVATO 502 | D31: 2550000 | E31: 0.03 | F31: =D31*E31 -> 76500
A32: 8498 | B32: 0.1 | C32: MAGDALENA DE LA CUENCA 305 | D32: 1350000 | E32: 0.03 | F32: =D32*E32 -> 40500
D33: =SUM(D24:D32) -> 21820000 | F33: =SUM(F24:F32) -> 654600
A35: INFORME DAHIANA HOYOS JULIO
A37: 8521 | B37: 0.08 | C37: LYON 1012 | D37: 1850000 | E37: 0.02 | F37: =D37*E37 -> 37000
A38: 8512 | B38: 0.1 | C38: CUMBRES DEL BOSQUE 609 | D38: 1450000 | E38: 0.03 | F38: =D38*E38 -> 43500
A39: 8510 | B39: 0.1 | C39: ENTREPARQUES 822 | D39: 2000000 | E39: 0.03 | F39: =D39*E39 -> 60000
A40: 8535 | B40: 0.08 | C40: VITTA 1207 | D40: 1400000 | E40: 0.02 | F40: =D40*E40 -> 28000
A41: 8595 | B41: 0.1 | C41: MAGADALENA DE LA CUENCA 804 | D41: 1300000 | E41: 0.03 | F41: =D41*E41 -> 39000
A42: 8579 | B42: 0.1 | C42: MAGDALENA DE LA CUENCA 1306 | D42: 1250000 | E42: 0.03 | F42: =D42*E42 -> 37500
A43: 8548 | B43: 0.1 | C43: AMARELLO IN 902 | D43: 1550000 | E43: 0.03 | F43: =D43*E43 -> 46500
A44: 8586 | B44: 0.1 | C44: GUALI 623 | D44: 1650000 | E44: 0.03 | F44: =D44*E44 -> 49500
A45: 8592 | B45: 0.1 | C45: MISSISSIPPI 608 | D45: 1200000 | E45: 0.03 | F45: =D45*E45 -> 36000
A46: 8636 | B46: 0.1 | C46: MAGDALENA DE LA CUENCA 1215 | D46: 1250000 | E46: 0.03 | F46: =D46*E46 -> 37500
A47: 8643 | B47: 0.1 | C47: MAGDALENA DE LA CUENCA 9916 | D47: 1200000 | E47: 0.03 | F47: =D47*E47 -> 36000
A48: 8613 | B48: 0.1 | C48: MAGDALENA DE LA CUENCA 1303 | D48: 1300000 | E48: 0.03 | F48: =D48*E48 -> 39000
... A50: 8668 | B50: 0.1 | C50: BIOCITY GRAND 1013 | D50: 1450000 | E50: 0.03 | F50: =D50*E50 -> 43500
D51: 21350000 | F51: =SUM(F37:F50) -> 583000
A53: INFORME DAHIANA HOYOS AGOSTO
A55: 8699 | B55: 0.1 | C55: MISSISSIPPI 702 | D55: 1300000 | E55: 0.01 | F55: =D55*E55 -> 13000
A56: 8703 | B56: 0.1 | C56: SIEMPRE VERDE CASA 109 | D56: 3000000 | E56: 0.01 | F56: =D56*E56 -> 30000
A57: 8724 | B57: 0.1 | C57: ENTREPARQUES 706 | D57: 2050000 | E57: 0.01 | F57: =D57*E57 -> 20500
A58: 8737 | B58: 0.1 | C58: TIERRA DEL SOL 210 | D58: 1200000 | E58: 0.01 | F58: =D58*E58 -> 12000
A59: 8785 | B59: 0.1 | C59: BRUJA CAMPESTRE 417 | D59: 2050000 | E59: 0.01 | F59: =D59*E59 -> 20500
A60: 8798 | B60: 0.1 | C60: MAGDALENA DE LA CUENTA 605 | D60: 1300000 | E60: 0.01 | F60: =D60*E60 -> 13000
A61: 8796 | B61: 0.1 | C61: CASA LOS NARANJOS | D61: 2200000 | E61: 0.01 | F61: =D61*E61 -> 22000
D62: =SUM(D55:D61) -> 13100000 | F62: =SUM(F55:F61) -> 131000
A64: INFORME DAHIANA HOYOS SEPTIEMBRE
A66: 8836 | B66: 0.1 | C66: BIOCITY 804 | D66: 1700000 | E66: 0.02 | F66: =D66*E66 -> 34000
A67: 8831 | B67: 0.1 | C67: MAGDALENA DE LA CUENCA 1102 | D67: 1350000 | E67: 0.02 | F67: =D67*E67 -> 27000
A68: 8896 | B68: 0.1 | C68: PIONEROS DE ZUÑIGA 203 | D68: 800000 | E68: 0.02 | F68: =D68*E68 -> 16000
A69: 8882 | B69: 0.1 | C69: QUINTAS DE LOS ALMENDROS CS 188 | D69: 3000000 | E69: 0.02 | F69: =D69*E69 -> 60000
A70: 8811 | B70: 0.08 | C70: TIERRA GRATA ESMERALDAL APTO 809 | D70: 2100000 | E70: 0.01 | F70: =D70*E70 -> 21000
D71: =SUM(D66:D70) -> 8950000 | F71: =SUM(F66:F70) -> 158000
A73: INFORME DAHIANA HOYOS OCTUBRE
A75: 8943 | B75: 0.1 | C75: MAGDALENA DE LA CUENCA 304 | D75: 1350000 | E75: 0.03 | F75: =D75*E75 -> 40500
A76: 8957 | B76: 0.1 | C76: SAN FERMIN 803 | D76: 1900000 | E76: 0.03 | F76: =D76*E76 -> 57000
A77: 8975 | B77: 0.08 | C77: BIOCITY GRAND 1737 | D77: 2600000 | E77: 0.02 | F77: =D77*E77 -> 52000
A78: 9008 | B78: 0.08 | C78: PALO DE ROSA | D78: 2900000 | E78: 0.02 | F78: =D78*E78 -> 58000
A79: 8984 | B79: 0.09 | C79: ESENCCE 501 | D79: 2900000 | E79: 0.02 | F79: =D79*E79 -> 58000
A80: 9053 | B80: 0.1 | C80: MUGA 303 | D80: 3400000 | E80: 0.03 | F80: =D80*E80 -> 102000
A81: 9010 | B81: 0.1 | C81: PUERTO LUNA 610 | D81: 1400000 | E81: 0.03 | F81: =D81*E81 -> 42000
A82: 9032 | B82: 0.1 | C82: ALUNA 708 | D82: 1450000 | E82: 0.03 | F82: =D82*E82 -> 43500
A83: 9025 | B83: 0.1 | C83: ENTREPARQUES 316 | D83: 2400000 | E83: 0.03 | F83: =D83*E83 -> 72000
A84: 9016 | B84: 0.1 | C84: CAMINO DE BRUJAS 325 | D84: 1550000 | E84: 0.03 | F84: =D84*E84 -> 46500
D85: =SUM(D75:D84) -> 21850000 | F85: =SUM(F75:F84) -> 571500
A87: INFORME DAHIANA HOYOS NOVIEMBRE
A89: 9068 | B89: 0.1 | C89: ENTREPINOS 1903 | D89: 3200000 | E89: 0.03 | F89: =D89*E89 -> 96000
A90: 9105 | B90: 0.1 | C90: BRUJA BONITA 301 | D90: 3500000 | E90: 0.03 | F90: =D90*E90 -> 105000
A91: 9067 | B91: 0.1 | C91: PUNTA DEL PARQUE 804 | D91: 2800000 | E91: 0.03 | F91: =D91*E91 -> 84000
A92: 9111 | B92: 0.1 | C92: REGATTA 603 | D92: 2300000 | E92: 0.03 | F92: =D92*E92 -> 69000
A93: 9066 | B93: 0.1 | C93: TORRE LUNA 704 | D93: 1500000 | E93: 0.03 | F93: =D93*E93 -> 45000
A94: 9109 | B94: 0.08 | C94: CITARK 1210 | D94: 2500000 | E94: 0.02 | F94: =D94*E94 -> 50000
A95: 9093 | B95: 0.1 | C95: PUNTA DEL PARQUE 1503 | D95: 2700000 | E95: 0.03 | F95: =D95*E95 -> 81000
A96: 9130 | B96: 0.1 | C96: TRENTTO 507 | D96: 1650000 | E96: 0.03 | F96: =D96*E96 -> 49500
D97: =SUM(D89:D96) -> 20150000 | F97: =SUM(F89:F96) -> 579500
A99: INFORME DAHIANA HOYOS DICIEMBRE
A101: 9188 | B101: 0.08 | C101: MISSISSIPPI 1316 | D101: 1300000 | F101: =D101*E101 -> 0
A102: 9203 | B102: 0.1 | C102: BIOCITY 1005 | D102: 2000000 | F102: =D102*E102 -> 0
A103: 9222 | B103: 0.1 | C103: DOS VELAS 808 | D103: 1500000
A104: 9231 | B104: 0.1 | C104: TORRE GUAYACAN 1004 | D104: 2450000
B105: 0.1 | C105: SALTAMONTES GRAND 906 | D105: 2200000
A106: 9247 | B106: 0.1 | C106: TORRE GUAYACAN 801 | D106: 2000000
B107: 0.1 | C107: RIO SECRETO 2610
D108: =SUM(D101:D107) -> 11450000
A110: TOTAL AÑO 2019
A112: 144.170.000

Sheet INFORME GENERAL 2020
A1: INFORME ENERO 2020 SEDE ENVIGADO
A3: ALEJANDRO BEDOYA
A4: CONSIGNACIONES | B4: CONTRATO | C4: %PROPIETARIO | D4: INMUEBLE | E4: CANON | F4: % | G4: comision | H4: ASESOR 2 | I4: EJECUTIVA | J4: OBSERVACIONES | K4: CONTRATO | L4: INMUEBLE | M4: CANON | N4: %
A5: 20+4 | B5: 9330 | C5: 0.1 | D5: MAGDALENA DE LA CUENCA 410 - 1.350.000 | E5: 1350000 | F5: 0.07 | G5: =E5*F5 -> 94500 | H5: JUAN PABLO VILLA | I5: DAHIANA HOYOS | K5: 9328 | L5: TORRE GUAYACAN 903 | M5: 2100000 | N5: 0.05 | O5: =M5*N5 -> 105000
B6: 9353 | C6: 0.1 | D6: NATIVO MADERA 1704 | E6: 3800000 | F6: 0.07 | G6: =E6*F6 -> 266000 | H6: ANDRES MIRANDA | I6: DAHIANA HOYOS
B7: 9286 | C7: 0.1 | D7: NATIVO FLORA 1401 | E7: 2100000 | F7: 0.12 | G7: =E7*F7 -> 252000 | H7: ALEJANDRO BEDOYA | I7: RONALD MENDEZ
B8: 9303 | C8: 0.1 | D8: TRENTTO 411 | E8: 1700000 | F8: 0.07 | G8: =E8*F8 -> 119000 | H8: JUAN PABLO VILLA | I8: DAHIANA HOYOS
B9: 9399 | C9: 0.1 | D9: BRUJAS CAMPESTRE 909 | E9: 2050000 | F9: 0.07 | G9: =E9*F9 -> 143500 | H9: JUAN PABLO VILLA | I9: DAHIANA HOYOS
B10: 9413 | C10: 0.1 | D10: MUGA 410 | E10: 2300000 | F10: 0.07 | G10: =E10*F10 -> 161000 | H10: PORTADA | I10: RONALD MENDEZ
O12: =SUM(O5:O11) -> 105000
D13: TOTAL | E13: =SUM(E5:E12) -> 13300000 | F13: TOTAL | G13: =SUM(G5:G12) -> 1036000 | L13: TOTAL--------------------------------------> | O13: =O12+G13 -> 1141000
A15: JUAN PABLO VILLA
A16: CONSIGNACIONES | B16: CONTRATO | C16: %PROPIETARIO | D16: INMUEBLE | E16: CANON | F16: % | G16: comision | H16: ASESOR 2 | I16: EJECUTIVA | J16: OBSERVACIONES | K16: CONTRATO | L16: INMUEBLE | M16: CANON | N16: %
A17: 26+7 | B17: 9328 | C17: 0.1 | D17: TORRE GUAYACAN 903 | E17: 2100000 | F17: 0.07 | G17: =E17*F17 -> 147000 | H17: ALEJANDRO BEDOYA | I17: DAHIANA HOYOS | K17: 9303 | L17: TRENTTO 411 | M17: 1700000 | N17: 0.05 | O17: =M17*N17 -> 85000
B18: 9315 | C18: 0.1 | D18: MULTIFAMILIAR LA ABADIA 412 | E18: 1900000 | F18: 0.07 | G18: =E18*F18 -> 133000 | H18: PORTADA | I18: DAHIANA HOYOS | K18: 9330 | L18: MAGDALENA DE LA CUENCA 410 | M18: 1350000 | N18: 0.05 | O18: =M18*N18 -> 67500
B19: 9339 | C19: 0.1 | D19: GUALI 910 | E19: 1700000 | F19: 0.07 | G19: =E19*F19 -> 119000 | H19: PORTADA | I19: RONALD MENDEZ | K19: 9350 | L19: MULTIFAMILIAR LA ABADIA 404 | M19: 1600000 | N19: 0.05 | O19: =M19*N19 -> 80000
B20: 9337 | C20: 0.1 | D20: VIENNA 1301 | E20: 1500000 | F20: 0.07 | G20: =E20*F20 -> 105000 | H20: CAMILO SABANETA | I20: RONALD MENDEZ | K20: 9399 | L20: BRUJAS CAMPESTRE 909 | M20: 2050000 | N20: 0.05 | O20: =M20*N20 -> 102500
B21: 9347 | C21: 0.1 | D21: CASA ALCALA | E21: 1500000 | F21: 0.12 | G21: =E21*F21 -> 180000 | H21: JUAN PABLO VILLA | I21: DAHIANA HOYOS
B22: 9349 | C22: 0.1 | D22: SAN LAURENT 801 | E22: 2300000 | F22: 0.07 | G22: =E22*F22 -> 161000 | H22: ANDRES MIRANDA | I22: DAHIANA HOYOS
B23: 9420 | C23: 0.09 | D23: BIOCITY GRANDE 938 | E23: 2350000 | F23: 0.1 | G23: =E23*F23 -> 235000 | H23: JUAN PABLO VILLA | I23: RONALD MENDEZ
B24: 9390 | C24: 0.1 | D24: CUMBRES DEL BOSQUE 505 | E24: 1600000 | F24: 0.07 | G24: =E24*F24 -> 112000 | H24: ANDRES MIRANDA | I24: RONALD MENDEZ
B25: DESISITIDO | D25: ALTOS DEL ESMERALDAL 704 | O25: =SUM(O17:O23) -> 335000
D26: TOTAL | E26: =SUM(E17:E24) -> 14950000 | F26: TOTAL | G26: =SUM(G17:G24) -> 1192000 | L26: TOTAL--------------------------------------> | O26: =O25+G26 -> 1527000
A28: ANDRES MIRANDA
A29: CONSIGNACIONES | B29: CONTRATO | C29: %PROPIETARIO | D29: INMUEBLE | E29: CANON | F29: % | G29: comision | H29: ASESOR 2 | I29: EJECUTIVA | J29: OBSERVACIONES | K29: CONTRATO | L29: INMUEBLE | M29: CANON | N29: %
A30: 20+4 | B30: 9291 | C30: 0.1 | D30: RIO SECRETO 2204 | E30: 1450000 | F30: 0.05 | G30: =E30*F30 -> 72500 | H30: PORTADA | I30: DAHIANA HOYOS | K30: 9390 | L30: CUMBRES DEL BOSQUE 505 | M30: 1600000 | N30: 0.05 | O30: =M30*N30 -> 80000
B31: 9321 | C31: 0.1 | D31: CORAZON DE ENVIGADO 701 | E31: 900000 | F31: 0.05 | G31: =E31*F31 -> 45000 | H31: PORTADA | I31: RONALD MENDEZ | K31: 9349 | L31: SAN LAURENT 801 | M31: 2300000 | N31: 0.05 | O31: =M31*N31 -> 115000
B32: 9344 | C32: 0.1 | D32: ANTILLAS 411 | E32: 1200000 | F32: 0.05 | G32: =E32*F32 -> 60000 | H32: JUAN ESTBAN MANRIQUE | I32: RONALD MENDEZ | K32: 9353 | L32: NATIVO MADERA 1704 | M32: 3800000 | N32: 0.05 | O32: =M32*N32 -> 190000
B33: 9350 | C33: 0.1 | D33: MULTIFAMILIAR LA ABADIA 404 | E33: 1600000 | F33: 0.05 | G33: =E33*F33 -> 80000 | H33: JUAN PABLO VILLA | I33: RONALD MENDEZ | K33: 9381 | L33: VEGAS PALAZA 2725 | M33: 1320000 | N33: 0.05 | O33: =M33*N33 -> 66000
B34: 9352 | C34: 0.1 | D34: BIOCITY GRAND 1241 | E34: 1700000 | F34: 0.1 | G34: =E34*F34 -> 170000 | H34: ANDRES MIRANDA | I34: DAHIANA HOYOS
O37: =SUM(O30:O36) -> 451000
D38: TOTAL | E38: =SUM(E30:E37) -> 6850000 | F38: TOTAL | G38: =SUM(G30:G37) -> 427500 | L38: TOTAL--------------------------------------> | O38: =O37+G38 -> 878500
A40: JUAN ESTEBAN MANRIQUE
A41: CONSIGNACIONES | B41: CONTRATO | C41: %PROPIETARIO | D41: INMUEBLE | E41: CANON | F41: % | G41: comision | H41: ASESOR 2 | I41: EJECUTIVA | J41: OBSERVACIONES | K41: CONTRATO | L41: INMUEBLE | M41: CANON | N41: %
A42: 14+5 | B42: 9323 | C42: 0.1 | D42: ALTOS DEL ESCOBERO 601 | E42: 1650000 | F42: 0.08 | G42: =E42*F42 -> 132000 | H42: JUAN ESTEBAN MANRIQUE | I42: RONALD MENDZ | K42: 9404 | L42: PALMAR DE LA ABADIA 305 | M42: 1600000 | N42: 0.04 | O42: =M42*N42 -> 64000
O46: =SUM(O42:O45) -> 64000
D47: TOTAL | E47: =SUM(E42:E45) -> 1650000 | F47: TOTAL | G47: =SUM(G42:G46) -> 132000 | L47: TOTAL--------------------------------------> | O47: =O46+G47 -> 196000
A49: PORTADA
A50: CONSIGNACIONES | B50: CONTRATO | C50: %PROPIETARIO | D50: INMUEBLE | E50: CANON | F50: % | G50: comision | H50: ASESOR 2 | I50: EJECUTIVA | J50: OBSERVACIONES | K50: CONTRATO | L50: INMUEBLE | M50: CANON | N50: %
A51: 4 | K51: 9413 | L51: MUGA 410 | M51: 2300000 | N51: 0.05 | O51: =M51*N51 -> 115000
K52: 9315 | L52: MULTIFAMILIAR LA ABADIA 412 | M52: 1900000 | N52: 0.05 | O52: =M52*N52 -> 95000
K53: 9339 | L53: GUALI 910 | M53: 1700000 | N53: 0.05 | O53: =M53*N53 -> 85000
K54: 9291 | L54: RIO SECRETO 2204 | M54: 1450000 | N54: 0.05 | O54: =M54*N54 -> 72500
K55: 9321 | L55: CORAZON DE ENVIGADO 701 | M55: 900000 | N55: 0.05 | O55: =M55*N55 -> 45000
M59: =SUM(M51:M58) -> 8250000 | O59: =SUM(O51:O58) -> 412500
D60: TOTAL | E60: =SUM(E51:E58) -> 0 | F60: TOTAL | G60: =SUM(G51:G59) -> 0 | L60: TOTAL--------------------------------------> | O60: =O59+G60 -> 412500
A62: TOTAL FIRMADO | D62: =E60+E47+E38+E26+E13 -> 36750000
A63: TOTAL EN FIRMAS
A64: TOTAL EN ESTUDIO
A67: INFORME ASESOR INTERNO ENERO 2020 RONALD MENDEZ
A69: # CONTRATO | B69: % PROPIETARIO | C69: UNIDAD | D69: OBSERVACION PORQUE CAMBIA EL % | E69: CANON | F69: % | G69: COMISION | H69: OBSERVACIONES | I69: ASESOR
A70: 9286 | B70: 0.1 | C70: NATIVO FLORA 1401 | D70: ENTREGADO | E70: 2100000 | F70: 0.04 | G70: =E70*F70 -> 84000 | H70: FACTURADO | I70: ALEJANDRO BEDOYA
A71: 9323 | B71: 0.1 | C71: ALTOS DEL ESCOBERO 601 | D71: ENTREGADO | E71: 1650000 | F71: 0.04 | G71: =E71*F71 -> 66000 | H71: FACTURADO | I71: JUAN ESTEBAN MANRIQUE
A72: 9420 | B72: 0.09 | C72: BIOCITY 938 | D72: ENTREGADO | E72: 2350000 | F72: 0.03 | G72: =E72*F72 -> 70500 | H72: FACTURADO | I72: JUAN PABLO VILLA
A73: 9339 | B73: 0.1 | C73: GUALI 910 1´700.000 | D73: ENTREGADO | E73: 1700000 | F73: 0.04 | G73: =E73*F73 -> 68000 | H73: FACTURADO | I73: JUAN PABLO VILLA
A74: 9350 | B74: 0.1 | C74: MULTIFAMILIAR LA ABADIA 404 | D74: ENTREGADO | E74: 1600000 | F74: 0.04 | G74: =E74*F74 -> 64000 | H74: FACTURADO | I74: ANDRES MIRANDA
A75: 9344 | B75: 0.1 | C75: LAS ANTILLAS 411 | D75: ENTREGADO | E75: 1200000 | F75: 0.04 | G75: =E75*F75 -> 48000 | H75: FACTURADO | I75: ANDRES MIRANDA
A76: 9337 | B76: 0.1 | C76: VIENNA 1301 | D76: ENTREGADO | E76: 1500000 | F76: 0.04 | G76: =E76*F76 -> 60000 | H76: FACTURADO | I76: JUAN PABLO VILLA
A77: 9390 | B77: 0.1 | C77: CUMBRES DEL BOSQUE 505 | D77: ENTREGADO | E77: 1600000 | F77: 0.04 | G77: =E77*F77 -> 64000 | H77: FACTURADO | I77: JUAN PABLO VILLA
A78: 9321 | B78: 0.1 | C78: CORAZON ENVIGADO 701 | D78: ENTREGADO | E78: 900000 | F78: 0.04 | G78: =E78*F78 -> 36000 | H78: FACTURADO | I78: ANDRES MIRANDA
A79: 9413 | B79: 0.1 | C79: MUGA 410 | D79: ENTREGADO | E79: 2300000 | F79: 0.04 | G79: =E79*F79 -> 92000 | H79: FACTURADO | I79: ALEJANDRO BEDOYA
B80: 0.1 | C80: ALTOS DEL ESMERALDAL 705 1´800.000$ | D80: DESISTIO | H80: PENDIENTE DE FACTURAR | I80: JUAN PABLO VILLA
E81: =SUM(E70:E80) -> 16900000 | G81: =SUM(G70:G80) -> 652500
A82: INFORME ASESORA INTERNA ENERO 2020 DAHIANA HOYOS
A84: # CONTRATO | B84: % PROPIETARIO | C84: UNIDAD | D84: OBSERVACION PORQUE CAMBIA EL % | E84: CANON | F84: % | G84: COMISION | H84: OBSERVACIONES | I84: ASESOR
A85: 9328 | B85: 0.1 | C85: TORRE GUAYACAN 903 | D85: ENTREGADO | E85: 2100000 | F85: 0.025 | G85: =E85*F85 -> 52500 | H85: FACTURADO | I85: JUAN PABLO VILLA
A86: 9291 | B86: 0.1 | C86: RIO SECRETO 2204 | D86: ENTREGADO | E86: 1450000 | F86: 0.025 | G86: =E86*F86 -> 36250 | H86: FACTURADO | I86: ANDRES MIRANDA
A87: 9330 | B87: 0.1 | C87: MAGDALENA DE LA CUENCA 410 | D87: ENTREGADO | E87: 1350000 | F87: 0.025 | G87: =E87*F87 -> 33750 | H87: FACTURADO | I87: ALEJANDRO BEDOYA
A88: 9353 | B88: 0.1 | C88: NATIVO MADERA 1704 | D88: ENTREGADO | E88: 3800000 | F88: 0.025 | G88: =E88*F88 -> 95000 | H88: FACTURADO | I88: ALEJANDRO BEDOYA
A89: 9315 | B89: 0.1 | C89: MULTIFAMILIAR LA ABADIA 412 | D89: ENTREGADO | E89: 1900000 | F89: 0.025 | G89: =E89*F89 -> 47500 | H89: FACTURADO | I89: JUAN PABLO VILLA
A90: 9303 | B90: 0.1 | C90: TRENTTO 411 | D90: ENTREGADO | E90: 1700000 | F90: 0.025 | G90: =E90*F90 -> 42500 | H90: FACTURADO | I90: ALEJANDRO BEDOYA
A91: 9349 | B91: 0.1 | C91: ST LAURENT 801 | D91: ENTREGADO | E91: 2300000 | F91: 0.025 | G91: =E91*F91 -> 57500 | H91: FACTURADO | I91: JUAN PABLO VILLA
A92: 9347 | B92: 0.1 | C92: APTO TERCER PISO ALCALA | D92: ENTREGADO | E92: 1500000 | F92: 0.025 | G92: =E92*F92 -> 37500 | H92: FACTURADO | I92: JUAN PABLO VILLA
A93: 9352 | B93: 0.1 | C93: BIOCITY 1241 | D93: ENTREGADO | E93: 1700000 | F93: 0.025 | G93: =E93*F93 -> 42500 | H93: FACTURADO | I93: ANDRES MIRANDA
A94: 9399 | B94: 0.1 | C94: BRUJA CAMPESTRE 909 | D94: ENTREGADO | E94: 2050000 | F94: 0.025 | G94: =E94*F94 -> 51250 | H94: FACTURADO | I94: ALEJANDRO BEDOYA
C95: EDIFIICIO CRISTALES 202 $ 2.500.000 | D95: EN ESTUDIO | I95: JUAN ESTEBAN MARIQUE
E96: =SUM(E85:E94) -> 19850000 | G96: =SUM(G85:G95) -> 496250
A97: INFORME INDIVIDUAL ENERO 2020 BIVIANA SALAZAR
A99: # CONTRATO | B99: PORCENTAJE PROPIETARIO | C99: INMUEBLE | D99: OBSERVACION CAMBIO DE % | E99: VALOR DEL CANON | F99: % | G99: COMISION
A100: 9330 | B100: 0.1 | C100: MAGDALENA DE LA CUENCA 410 - 1.350.000 | E100: 1350000 | F100: 0.025 | G100: =E100*F100 -> 33750
A101: 9353 | B101: 0.1 | C101: NATIVO MADERA 1704 | E101: 3800000 | F101: 0.025 | G101: =E101*F101 -> 95000
A102: 9286 | B102: 0.1 | C102: NATIVO FLORA 1401 | E102: 2100000 | F102: 0.025 | G102: =E102*F102 -> 52500
A103: 9303 | B103: 0.1 | C103: TRENTTO 411 | E103: 1700000 | F103: 0.025 | G103: =E103*F103 -> 42500
A104: 9399 | B104: 0.1 | C104: BRUJAS CAMPESTRE 909 | E104: 2050000 | F104: 0.025 | G104: =E104*F104 -> 51250
A105: 9413 | B105: 0.1 | C105: MUGA 410 - 2.300.000 | E105: 2300000 | F105: 0.025 | G105: =E105*F105 -> 57500
A106: 9328 | B106: 0.1 | C106: TORRE GUAYACAN 903 | E106: 2100000 | F106: 0.025 | G106: =E106*F106 -> 52500
A107: 9315 | B107: 0.1 | C107: MULTIFAMILIAR LA ABADIA 412 | E107: 1900000 | F107: 0.025 | G107: =E107*F107 -> 47500
A108: 9339 | B108: 0.1 | C108: GUALI 910 | E108: 1700000 | F108: 0.025 | G108: =E108*F108 -> 42500
A109: 9337 | B109: 0.1 | C109: VIENNA 1301 | E109: 1500000 | F109: 0.025 | G109: =E109*F109 -> 37500
A110: 9347 | B110: 0.1 | C110: CASA ALCALA | E110: 1500000 | F110: 0.025 | G110: =E110*F110 -> 37500
A111: 9349 | B111: 0.1 | C111: SAN LAURENT 801 | E111: 2300000 | F111: 0.025 | G111: =E111*F111 -> 57500
... A119: 9323 | B119: 0.1 | C119: ALTOS DEL ESCOBERO 601 | E119: 1650000 | F119: 0.025 | G119: =E119*F119 -> 41250
E121: =SUM(E100:E120) -> 36750000 | G121: =SUM(G100:G120) -> 895250
A123: SECTOR | B123: CAPTACIONES | C123: ARRIENDOS ($) | D123: TOTAL INMUEBLES ARRENDADOS
B124: =SUM(B125:B156) -> 0
A125: SEÑORIAL - LA CUENCA
A127: CHINGUI
A129: ZUÑIGA
A131: LOMA DEL ESMERALDAL
A133: LOMA DEL ESCOBERO
...
